{
  "type": "Feature",
  "properties": {
    "gn:admin1_code":"15.0",
    "gn:admin2_code":"14.0",
    "gn:admin3_code":"1403.0",
    "gn:asciiname":"Uscana",
    "gn:country_code":"CL",
    "gn:dem":4461,
    "gn:feature_class":"P",
    "gn:feature_code":"PPL",
    "gn:name":"Uscana",
    "gn:population":0,
    "gn:timezone":"America/Santiago",
    "iso:country":"CL",
    "wof:name":"Uscana",
    "wof:placetype":"locality"
},
  "geometry": {"coordinates":[-68.95,-19.28333],"type":"Point"}
}