{
  "type": "Feature",
  "properties": {
    "gn:admin1_code":"4.0",
    "gn:admin2_code":"91.0",
    "gn:admin3_code":"9114.0",
    "gn:asciiname":"Comuy",
    "gn:country_code":"CL",
    "gn:dem":36,
    "gn:feature_class":"P",
    "gn:feature_code":"PPL",
    "gn:name":"Comuy",
    "gn:population":0,
    "gn:timezone":"America/Santiago",
    "iso:country":"CL",
    "name:und_x_variant":[
        "Cumui",
        "Comuy",
        "Cumuy"
    ],
    "wof:name":"Comuy",
    "wof:placetype":"locality"
},
  "geometry": {"coordinates":[-72.96724,-39.02378],"type":"Point"}
}