{
  "type": "Feature",
  "properties": {
    "gn:admin1_code":"17.0",
    "gn:admin2_code":"141.0",
    "gn:admin3_code":"14107.0",
    "gn:asciiname":"Caupolican",
    "gn:country_code":"CL",
    "gn:dem":75,
    "gn:feature_class":"P",
    "gn:feature_code":"PPL",
    "gn:name":"Caupolic\u00e1n",
    "gn:population":0,
    "gn:timezone":"America/Santiago",
    "iso:country":"CL",
    "wof:name":"Caupolican",
    "wof:placetype":"locality"
},
  "geometry": {"coordinates":[-72.91784,-40.07062],"type":"Point"}
}