{
  "type": "Feature",
  "properties": {
    "gn:admin1_code":"5.0",
    "gn:admin2_code":"31.0",
    "gn:admin3_code":"3101.0",
    "gn:asciiname":"Perales",
    "gn:country_code":"CL",
    "gn:dem":197,
    "gn:feature_class":"P",
    "gn:feature_code":"PPL",
    "gn:name":"Perales",
    "gn:population":0,
    "gn:timezone":"America/Santiago",
    "iso:country":"CL",
    "name:ceb_x_preferred":[
        "Perales"
    ],
    "name:eus_x_preferred":[
        "Perales"
    ],
    "name:ita_x_preferred":[
        "Perales"
    ],
    "name:spa_x_preferred":[
        "Perales"
    ],
    "name:srp_x_preferred":[
        "\u041f\u0435\u0440\u0430\u043b\u0435\u0441"
    ],
    "name:swe_x_preferred":[
        "Perales"
    ],
    "wof:name":"Perales",
    "wof:placetype":"locality"
},
  "geometry": {"coordinates":[-70.91660999999998,-27.89061],"type":"Point"}
}