{
  "type": "Feature",
  "properties": {
    "gn:admin1_code":"12.0",
    "gn:admin2_code":"133.0",
    "gn:admin3_code":"13303.0",
    "gn:asciiname":"Cajon de los Valle",
    "gn:country_code":"CL",
    "gn:dem":995,
    "gn:feature_class":"P",
    "gn:feature_code":"PPL",
    "gn:name":"Caj\u00f3n de los Valle",
    "gn:population":0,
    "gn:timezone":"America/Santiago",
    "iso:country":"CL",
    "wof:name":"Cajon de los Valle",
    "wof:placetype":"locality"
},
  "geometry": {"coordinates":[-70.76666999999998,-32.95],"type":"Point"}
}