{
  "type": "Feature",
  "properties": {
    "gn:admin1_code":"11.0",
    "gn:admin2_code":"71.0",
    "gn:admin3_code":"7101.0",
    "gn:asciiname":"Cerrillo Caivan",
    "gn:country_code":"CL",
    "gn:dem":129,
    "gn:feature_class":"P",
    "gn:feature_code":"PPL",
    "gn:name":"Cerrillo Caiv\u00e1n",
    "gn:population":0,
    "gn:timezone":"America/Santiago",
    "iso:country":"CL",
    "name:und_x_variant":[
        "Caiban",
        "Cerrillo Caiv\u00e1n"
    ],
    "wof:name":"Cerrillo Caivan",
    "wof:placetype":"locality"
},
  "geometry": {"coordinates":[-71.65371,-35.47839000000001],"type":"Point"}
}