{
  "type": "Feature",
  "properties": {
    "gn:admin1_code":"14.0",
    "gn:admin2_code":"103.0",
    "gn:admin3_code":"10301.0",
    "gn:asciiname":"Pichil",
    "gn:country_code":"CL",
    "gn:dem":59,
    "gn:feature_class":"P",
    "gn:feature_code":"PPL",
    "gn:name":"Pichil",
    "gn:population":0,
    "gn:timezone":"America/Santiago",
    "iso:country":"CL",
    "wof:name":"Pichil",
    "wof:placetype":"locality"
},
  "geometry": {"coordinates":[-73.0154,-40.70871],"type":"Point"}
}