{
  "type": "Feature",
  "properties": {
    "gn:admin1_code":"12.0",
    "gn:admin2_code":"132.0",
    "gn:admin3_code":"13203.0",
    "gn:asciiname":"El Alfalfal",
    "gn:country_code":"CL",
    "gn:dem":1345,
    "gn:feature_class":"P",
    "gn:feature_code":"PPL",
    "gn:name":"El Alfalfal",
    "gn:population":0,
    "gn:timezone":"America/Santiago",
    "iso:country":"CL",
    "name:und_x_variant":[
        "Alfalfal",
        "El Alfaltal",
        "El Alfalfal"
    ],
    "wof:name":"El Alfalfal",
    "wof:placetype":"locality"
},
  "geometry": {"coordinates":[-70.19485,-33.50157],"type":"Point"}
}