{
  "type": "Feature",
  "properties": {
    "gn:admin1_code":"12.0",
    "gn:admin2_code":"133.0",
    "gn:admin3_code":"13303.0",
    "gn:asciiname":"Los Molinos",
    "gn:country_code":"CL",
    "gn:dem":619,
    "gn:feature_class":"P",
    "gn:feature_code":"PPL",
    "gn:name":"Los Molinos",
    "gn:population":0,
    "gn:timezone":"America/Santiago",
    "iso:country":"CL",
    "wof:name":"Los Molinos",
    "wof:placetype":"locality"
},
  "geometry": {"coordinates":[-70.93004999999999,-33.06657],"type":"Point"}
}