{
  "type": "Feature",
  "properties": {
    "gn:admin1_code":"5.0",
    "gn:admin2_code":"33.0",
    "gn:admin3_code":"3303.0",
    "gn:asciiname":"Los Loros",
    "gn:country_code":"CL",
    "gn:dem":76,
    "gn:feature_class":"P",
    "gn:feature_code":"PPL",
    "gn:name":"Los Loros",
    "gn:population":0,
    "gn:timezone":"America/Santiago",
    "iso:country":"CL",
    "name:spa_x_preferred":[
        "Los Loros"
    ],
    "wof:name":"Los Loros",
    "wof:placetype":"locality"
},
  "geometry": {"coordinates":[-71.09845,-28.49962],"type":"Point"}
}