{
  "type": "Feature",
  "properties": {
    "gn:admin1_code":"10.0",
    "gn:admin2_code":"121.0",
    "gn:admin3_code":"12101.0",
    "gn:asciiname":"Caserio Rio Los Ciervos",
    "gn:country_code":"CL",
    "gn:dem":14,
    "gn:feature_class":"P",
    "gn:feature_code":"PPL",
    "gn:name":"Caser\u00edo R\u00edo Los Ciervos",
    "gn:population":0,
    "gn:timezone":"America/Punta_Arenas",
    "iso:country":"CL",
    "name:spa_x_preferred":[
        "Caser\u00edo R\u00edo Los Ciervos"
    ],
    "name:und_x_variant":[
        "R\u00edo de los Ciervos"
    ],
    "wof:name":"Caserio Rio Los Ciervos",
    "wof:placetype":"locality"
},
  "geometry": {"coordinates":[-70.93585999999998,-53.19914],"type":"Point"}
}