{
  "type": "Feature",
  "properties": {
    "gn:admin1_code":"6.0",
    "gn:admin2_code":"81.0",
    "gn:admin3_code":"8107.0",
    "gn:asciiname":"Cerro Verde",
    "gn:country_code":"CL",
    "gn:dem":59,
    "gn:feature_class":"P",
    "gn:feature_code":"PPL",
    "gn:name":"Cerro Verde",
    "gn:population":0,
    "gn:timezone":"America/Santiago",
    "iso:country":"CL",
    "wof:name":"Cerro Verde",
    "wof:placetype":"locality"
},
  "geometry": {"coordinates":[-72.98333000000002,-36.73333],"type":"Point"}
}