{
  "type": "Feature",
  "properties": {
    "gn:admin1_code":"12.0",
    "gn:admin2_code":"132.0",
    "gn:asciiname":"Las Vertientes",
    "gn:country_code":"CL",
    "gn:dem":822,
    "gn:feature_class":"P",
    "gn:feature_code":"PPL",
    "gn:name":"Las Vertientes",
    "gn:population":0,
    "gn:timezone":"America/Santiago",
    "iso:country":"CL",
    "name:spa_x_preferred":[
        "Las Vertientes"
    ],
    "wof:name":"Las Vertientes",
    "wof:placetype":"locality"
},
  "geometry": {"coordinates":[-70.46746,-33.58815],"type":"Point"}
}