{
  "type": "Feature",
  "properties": {
    "gn:admin1_code":"14.0",
    "gn:admin2_code":"101.0",
    "gn:admin3_code":"10102.0",
    "gn:asciiname":"San Agustin",
    "gn:country_code":"CL",
    "gn:dem":74,
    "gn:feature_class":"P",
    "gn:feature_code":"PPL",
    "gn:name":"San Agust\u00edn",
    "gn:population":0,
    "gn:timezone":"America/Santiago",
    "iso:country":"CL",
    "wof:name":"San Agustin",
    "wof:placetype":"locality"
},
  "geometry": {"coordinates":[-73.06558000000003,-41.70527],"type":"Point"}
}