{
  "type": "Feature",
  "properties": {
    "gn:admin1_code":"5.0",
    "gn:admin2_code":"31.0",
    "gn:admin3_code":"3103.0",
    "gn:asciiname":"Tres Puentes",
    "gn:country_code":"CL",
    "gn:dem":867,
    "gn:feature_class":"P",
    "gn:feature_code":"PPL",
    "gn:name":"Tres Puentes",
    "gn:population":0,
    "gn:timezone":"America/Santiago",
    "iso:country":"CL",
    "name:spa_x_preferred":[
        "Tres Puentes"
    ],
    "wof:name":"Tres Puentes",
    "wof:placetype":"locality"
},
  "geometry": {"coordinates":[-70.14331999999999,-27.80138],"type":"Point"}
}