{
  "type": "Feature",
  "properties": {
    "gn:admin1_code":"11.0",
    "gn:admin2_code":"73.0",
    "gn:admin3_code":"7303.0",
    "gn:asciiname":"Comunidad El Guapi",
    "gn:country_code":"CL",
    "gn:dem":35,
    "gn:feature_class":"P",
    "gn:feature_code":"PPL",
    "gn:name":"Comunidad El Guapi",
    "gn:population":0,
    "gn:timezone":"America/Santiago",
    "iso:country":"CL",
    "name:und_x_variant":[
        "Huapi",
        "Comunidad El Guapi"
    ],
    "wof:name":"Comunidad El Guapi",
    "wof:placetype":"locality"
},
  "geometry": {"coordinates":[-72.10254999999999,-35.03042],"type":"Point"}
}