{
  "type": "Feature",
  "properties": {
    "gn:admin1_code":"1.0",
    "gn:admin2_code":"57.0",
    "gn:admin3_code":"5706.0",
    "gn:asciiname":"Balneario de Jahuel",
    "gn:country_code":"CL",
    "gn:dem":1032,
    "gn:feature_class":"P",
    "gn:feature_code":"PPL",
    "gn:name":"Balneario de Jahuel",
    "gn:population":0,
    "gn:timezone":"America/Santiago",
    "iso:country":"CL",
    "wof:name":"Balneario de Jahuel",
    "wof:placetype":"locality"
},
  "geometry": {"coordinates":[-70.60113,-32.67786],"type":"Point"}
}