{
  "type": "Feature",
  "properties": {
    "gn:admin1_code":"7.0",
    "gn:admin2_code":"42.0",
    "gn:admin3_code":"4202.0",
    "gn:asciiname":"Mincha",
    "gn:country_code":"CL",
    "gn:dem":54,
    "gn:feature_class":"P",
    "gn:feature_code":"PPL",
    "gn:name":"Mincha",
    "gn:population":0,
    "gn:timezone":"America/Santiago",
    "iso:country":"CL",
    "name:bar_x_preferred":[
        "Mincha"
    ],
    "name:cat_x_preferred":[
        "Mincha"
    ],
    "name:ces_x_preferred":[
        "Mincha"
    ],
    "name:deu_x_preferred":[
        "Mincha"
    ],
    "name:fra_x_preferred":[
        "Min'ha"
    ],
    "name:heb_x_preferred":[
        "\u05ea\u05e4\u05d9\u05dc\u05ea \u05de\u05e0\u05d7\u05d4"
    ],
    "name:ita_x_preferred":[
        "Minchah"
    ],
    "name:nld_x_preferred":[
        "Mincha"
    ],
    "name:pol_x_preferred":[
        "Mincha"
    ],
    "name:por_x_preferred":[
        "Minch\u00e1"
    ],
    "name:rus_x_preferred":[
        "\u041c\u0438\u043d\u0445\u0430"
    ],
    "name:spa_x_preferred":[
        "Minj\u00e1"
    ],
    "name:yid_x_preferred":[
        "\u05de\u05e0\u05d7\u05d4"
    ],
    "wof:name":"Mincha",
    "wof:placetype":"locality"
},
  "geometry": {"coordinates":[-71.44679000000002,-31.58723],"type":"Point"}
}