{
  "type": "Feature",
  "properties": {
    "gn:admin1_code":"8.0",
    "gn:admin2_code":"62.0",
    "gn:admin3_code":"6206.0",
    "gn:asciiname":"El Cardal",
    "gn:country_code":"CL",
    "gn:dem":36,
    "gn:feature_class":"P",
    "gn:feature_code":"PPL",
    "gn:name":"El Cardal",
    "gn:population":0,
    "gn:timezone":"America/Santiago",
    "iso:country":"CL",
    "wof:name":"El Cardal",
    "wof:placetype":"locality"
},
  "geometry": {"coordinates":[-71.98108000000001,-34.70221],"type":"Point"}
}