{
  "type": "Feature",
  "properties": {
    "gn:admin1_code":"17.0",
    "gn:admin2_code":"141.0",
    "gn:admin3_code":"14104.0",
    "gn:asciiname":"Malalcuchi",
    "gn:country_code":"CL",
    "gn:dem":126,
    "gn:feature_class":"P",
    "gn:feature_code":"PPL",
    "gn:name":"Malalcuchi",
    "gn:population":0,
    "gn:timezone":"America/Santiago",
    "iso:country":"CL",
    "wof:name":"Malalcuchi",
    "wof:placetype":"locality"
},
  "geometry": {"coordinates":[-72.73295999999998,-39.96619000000001],"type":"Point"}
}