{
  "type": "Feature",
  "properties": {
    "gn:admin1_code":"12.0",
    "gn:admin2_code":"131.0",
    "gn:admin3_code":"13132.0",
    "gn:asciiname":"La Dehesa",
    "gn:country_code":"CL",
    "gn:dem":835,
    "gn:feature_class":"P",
    "gn:feature_code":"PPL",
    "gn:name":"La Dehesa",
    "gn:population":0,
    "gn:timezone":"America/Santiago",
    "iso:country":"CL",
    "name:spa_x_preferred":[
        "La Dehesa"
    ],
    "wof:name":"La Dehesa",
    "wof:placetype":"locality"
},
  "geometry": {"coordinates":[-70.53589000000002,-33.35241],"type":"Point"}
}