{
  "type": "Feature",
  "properties": {
    "gn:admin1_code":"3.0",
    "gn:admin2_code":"21.0",
    "gn:admin3_code":"2104.0",
    "gn:asciiname":"Cascabeles",
    "gn:country_code":"CL",
    "gn:dem":19,
    "gn:feature_class":"P",
    "gn:feature_code":"PPL",
    "gn:name":"Cascabeles",
    "gn:population":0,
    "gn:timezone":"America/Santiago",
    "iso:country":"CL",
    "wof:name":"Cascabeles",
    "wof:placetype":"locality"
},
  "geometry": {"coordinates":[-70.44880999999999,-25.28362000000001],"type":"Point"}
}