{
  "type": "Feature",
  "properties": {
    "iso:country":"CL",
    "name:spa_x_colloquial":[
        "Poblacion Chorrillos"
    ],
    "name:spa_x_preferred":[
        "Poblaci\u00f3n Chorrillos"
    ],
    "qs:gn_fcode":"PPLX",
    "qs:gn_local":0,
    "qs:gn_namadm1":"01",
    "qs:gn_name":"Poblaci\u00f3n Chorrillos",
    "qs:local_max":14219,
    "qs:local_sum":41999,
    "qs:localhoods":9,
    "qs:name":"Poblaci\u00f3n Chorrillos",
    "qs:name_adm0":"Chile",
    "qs:name_adm1":"Valpara\u00edso",
    "qs:name_adm2":"Valparaiso",
    "qs:name_lau":"Vi\u00f1a del Mar",
    "qs:name_local":"Valpara\u00edso",
    "qs:photo_max":362,
    "qs:photo_sum":1044,
    "qs:placetype":"Suburb",
    "qs:quad_count":68,
    "qs:woe_adm0":23424782,
    "qs:woe_adm1":2345018,
    "qs:woe_adm2":26794022,
    "qs:woe_lau":26794359,
    "qs:woe_local":349861,
    "qs:woe_ver":"7.10.0",
    "wof:lang":[
        "spa"
    ],
    "wof:name":"Poblaci\u00f3n Chorrillos",
    "wof:placetype":"neighbourhood"
},
  "geometry": {"coordinates":[-71.53639800000001,-33.028081],"type":"Point"}
}