{
  "type": "Feature",
  "properties": {
    "gn:admin1_code":"4.0",
    "gn:admin2_code":"92.0",
    "gn:admin3_code":"9207.0",
    "gn:asciiname":"Lumaco",
    "gn:country_code":"CL",
    "gn:dem":65,
    "gn:feature_class":"P",
    "gn:feature_code":"PPL",
    "gn:name":"Lumaco",
    "gn:population":0,
    "gn:timezone":"America/Santiago",
    "iso:country":"CL",
    "name:ceb_x_preferred":[
        "Lumaco"
    ],
    "name:eus_x_preferred":[
        "Lumaco"
    ],
    "name:fas_x_preferred":[
        "\u0644\u0648\u0645\u0627\u06a9\u0648"
    ],
    "name:fra_x_preferred":[
        "Lumaco"
    ],
    "name:ita_x_preferred":[
        "Lumaco"
    ],
    "name:kor_x_preferred":[
        "\ub8e8\ub9c8\ucf54"
    ],
    "name:nld_x_preferred":[
        "Lumaco"
    ],
    "name:por_x_preferred":[
        "Lumaco"
    ],
    "name:ron_x_preferred":[
        "Lumaco"
    ],
    "name:rus_x_preferred":[
        "\u041b\u0443\u043c\u0430\u043a\u043e"
    ],
    "name:spa_x_preferred":[
        "Lumaco"
    ],
    "name:swe_x_preferred":[
        "Lumaco"
    ],
    "name:zho_x_preferred":[
        "\u76e7\u99ac\u79d1"
    ],
    "wof:name":"Lumaco",
    "wof:placetype":"locality"
},
  "geometry": {"coordinates":[-72.90550999999998,-38.16485],"type":"Point"}
}