{
  "type": "Feature",
  "properties": {
    "gn:admin1_code":"4.0",
    "gn:admin2_code":"92.0",
    "gn:admin3_code":"9207.0",
    "gn:asciiname":"Lumaco",
    "gn:country_code":"CL",
    "gn:dem":65,
    "gn:feature_class":"P",
    "gn:feature_code":"PPL",
    "gn:name":"Lumaco",
    "gn:population":0,
    "gn:timezone":"America/Santiago",
    "iso:country":"CL",
    "wof:name":"Lumaco",
    "wof:placetype":"locality"
},
  "geometry": {"coordinates":[-72.90550999999998,-38.16485],"type":"Point"}
}