{
  "type": "Feature",
  "properties": {
    "gn:admin1_code":"15.0",
    "gn:admin2_code":"14.0",
    "gn:admin3_code":"1403.0",
    "gn:asciiname":"Chalviri",
    "gn:country_code":"CL",
    "gn:dem":3895,
    "gn:feature_class":"P",
    "gn:feature_code":"PPL",
    "gn:name":"Chalviri",
    "gn:population":0,
    "gn:timezone":"America/Santiago",
    "iso:country":"CL",
    "name:spa_x_preferred":[
        "Chalviri"
    ],
    "name:und_x_variant":[
        "Charviri"
    ],
    "wof:name":"Chalviri",
    "wof:placetype":"locality"
},
  "geometry": {"coordinates":[-68.58523000000001,-19.55554],"type":"Point"}
}