{
  "type": "Feature",
  "properties": {
    "gn:admin1_code":"11.0",
    "gn:admin2_code":"73.0",
    "gn:admin3_code":"7303.0",
    "gn:asciiname":"El Peral",
    "gn:country_code":"CL",
    "gn:dem":353,
    "gn:feature_class":"P",
    "gn:feature_code":"PPL",
    "gn:name":"El Peral",
    "gn:population":0,
    "gn:timezone":"America/Santiago",
    "iso:country":"CL",
    "wof:name":"El Peral",
    "wof:placetype":"locality"
},
  "geometry": {"coordinates":[-72.09999999999999,-34.95],"type":"Point"}
}