{
  "type": "Feature",
  "properties": {
    "gn:admin1_code":"6.0",
    "gn:admin2_code":"84.0",
    "gn:admin3_code":"8402.0",
    "gn:asciiname":"Placeres",
    "gn:country_code":"CL",
    "gn:dem":90,
    "gn:feature_class":"P",
    "gn:feature_code":"PPL",
    "gn:name":"Placeres",
    "gn:population":0,
    "gn:timezone":"America/Santiago",
    "iso:country":"CL",
    "wof:name":"Placeres",
    "wof:placetype":"locality"
},
  "geometry": {"coordinates":[-72.3201,-36.7939],"type":"Point"}
}