{
  "type": "Feature",
  "properties": {
    "gn:admin1_code":"14.0",
    "gn:admin2_code":"102.0",
    "gn:admin3_code":"10202.0",
    "gn:asciiname":"Mechaico",
    "gn:country_code":"CL",
    "gn:dem":105,
    "gn:feature_class":"P",
    "gn:feature_code":"PPL",
    "gn:name":"Mechaico",
    "gn:population":0,
    "gn:timezone":"America/Santiago",
    "iso:country":"CL",
    "name:spa_x_preferred":[
        "Mechaico"
    ],
    "wof:name":"Mechaico",
    "wof:placetype":"locality"
},
  "geometry": {"coordinates":[-73.81106,-41.92816],"type":"Point"}
}