{
  "type": "Feature",
  "properties": {
    "gn:admin1_code":"15.0",
    "gn:admin2_code":"14.0",
    "gn:admin3_code":"1405.0",
    "gn:asciiname":"Casa de Lata",
    "gn:country_code":"CL",
    "gn:dem":4393,
    "gn:feature_class":"P",
    "gn:feature_code":"PPL",
    "gn:name":"Casa de Lata",
    "gn:population":0,
    "gn:timezone":"America/Santiago",
    "iso:country":"CL",
    "name:spa_x_preferred":[
        "Casa de Lata"
    ],
    "name:spa_x_variant":[
        "Casa De Lata"
    ],
    "wof:name":"Casa de Lata",
    "wof:placetype":"locality"
},
  "geometry": {"coordinates":[-68.75929000000001,-20.96858],"type":"Point"}
}