{
  "type": "Feature",
  "properties": {
    "gn:admin1_code":"7.0",
    "gn:admin2_code":"43.0",
    "gn:admin3_code":"4301.0",
    "gn:asciiname":"El Acacio",
    "gn:country_code":"CL",
    "gn:dem":255,
    "gn:feature_class":"P",
    "gn:feature_code":"PPL",
    "gn:name":"El Acacio",
    "gn:population":0,
    "gn:timezone":"America/Santiago",
    "iso:country":"CL",
    "wof:name":"El Acacio",
    "wof:placetype":"locality"
},
  "geometry": {"coordinates":[-71.28525999999999,-30.70005],"type":"Point"}
}