{
  "type": "Feature",
  "properties": {
    "gn:admin1_code":"6.0",
    "gn:admin2_code":"84.0",
    "gn:asciiname":"Tamenelo",
    "gn:country_code":"CL",
    "gn:dem":13,
    "gn:feature_class":"P",
    "gn:feature_code":"PPL",
    "gn:name":"Tame\u00f1elo",
    "gn:population":0,
    "gn:timezone":"America/Santiago",
    "iso:country":"CL",
    "wof:name":"Tamenelo",
    "wof:placetype":"locality"
},
  "geometry": {"coordinates":[-72.8075,-36.25192],"type":"Point"}
}