{
  "type": "Feature",
  "properties": {
    "gn:admin1_code":"11.0",
    "gn:admin2_code":"71.0",
    "gn:admin3_code":"7107.0",
    "gn:asciiname":"El Peumo",
    "gn:country_code":"CL",
    "gn:dem":123,
    "gn:feature_class":"P",
    "gn:feature_code":"PPL",
    "gn:name":"El Peumo",
    "gn:population":0,
    "gn:timezone":"America/Santiago",
    "iso:country":"CL",
    "wof:name":"El Peumo",
    "wof:placetype":"locality"
},
  "geometry": {"coordinates":[-72.0488,-35.3957],"type":"Point"}
}