{
  "type": "Feature",
  "properties": {
    "gn:admin1_code":"14.0",
    "gn:admin2_code":"101.0",
    "gn:admin3_code":"10101.0",
    "gn:asciiname":"Colonia Alerce",
    "gn:country_code":"CL",
    "gn:dem":137,
    "gn:feature_class":"P",
    "gn:feature_code":"PPL",
    "gn:name":"Colonia Alerce",
    "gn:population":0,
    "gn:timezone":"America/Santiago",
    "iso:country":"CL",
    "name:und_x_variant":[
        "Array\u00e1n",
        "Colonia Alerce"
    ],
    "wof:name":"Colonia Alerce",
    "wof:placetype":"locality"
},
  "geometry": {"coordinates":[-72.87998,-41.3884],"type":"Point"}
}