{
  "type": "Feature",
  "properties": {
    "gn:admin1_code":"15.0",
    "gn:admin2_code":"14.0",
    "gn:admin3_code":"1402.0",
    "gn:asciiname":"Francia",
    "gn:country_code":"CL",
    "gn:dem":1776,
    "gn:feature_class":"P",
    "gn:feature_code":"PPL",
    "gn:name":"Francia",
    "gn:population":0,
    "gn:timezone":"America/Santiago",
    "iso:country":"CL",
    "name:spa_x_preferred":[
        "Francia"
    ],
    "wof:name":"Francia",
    "wof:placetype":"locality"
},
  "geometry": {"coordinates":[-69.57011,-19.38038],"type":"Point"}
}