{
  "type": "Feature",
  "properties": {
    "gn:country":"CL",
    "gn:fcode":"PPL",
    "gn:population":0,
    "iso:country":"CL",
    "name:spa_x_preferred":[
        "Chiuch\u00edu"
    ],
    "name:und_x_variant":[
        "Chiuchu"
    ],
    "qs:name":"Ch\u00educh\u00edu",
    "qs:name_adm0":"Chile",
    "qs:name_adm1":"Antofagasta",
    "qs:photos":341,
    "qs:photos_1k":69,
    "qs:photos_9k":2,
    "qs:photos_9r":5,
    "qs:photos_all":341,
    "qs:photos_sr":5,
    "qs:placetype":"Town",
    "qs:pop_sr":"0",
    "wof:name":"Ch\u00educh\u00edu",
    "wof:placetype":"locality",
    "wof:population":0
},
  "geometry": {"coordinates":[-68.65034,-22.34167],"type":"Point"}
}