{
  "type": "Feature",
  "properties": {
    "gn:admin1_code":"16.0",
    "gn:admin2_code":"152.0",
    "gn:admin3_code":"15202.0",
    "gn:asciiname":"Chislluma",
    "gn:country_code":"CL",
    "gn:dem":4245,
    "gn:feature_class":"P",
    "gn:feature_code":"PPL",
    "gn:name":"Chislluma",
    "gn:population":0,
    "gn:timezone":"America/Santiago",
    "iso:country":"CL",
    "name:spa_x_preferred":[
        "Chislluma"
    ],
    "wof:name":"Chislluma",
    "wof:placetype":"locality"
},
  "geometry": {"coordinates":[-69.68805,-17.69758],"type":"Point"}
}