{
  "type": "Feature",
  "properties": {
    "gn:admin1_code":"1.0",
    "gn:admin2_code":"53.0",
    "gn:asciiname":"Los Chalets",
    "gn:country_code":"CL",
    "gn:dem":1009,
    "gn:feature_class":"P",
    "gn:feature_code":"PPL",
    "gn:name":"Los Chalets",
    "gn:population":0,
    "gn:timezone":"America/Santiago",
    "iso:country":"CL",
    "name:spa_x_preferred":[
        "Los Chalets"
    ],
    "wof:name":"Los Chalets",
    "wof:placetype":"locality"
},
  "geometry": {"coordinates":[-70.46394000000002,-32.85375],"type":"Point"}
}