{
  "type": "Feature",
  "properties": {
    "gn:admin1_code":"10.0",
    "gn:admin2_code":"121.0",
    "gn:asciiname":"Monte Alto",
    "gn:country_code":"CL",
    "gn:dem":208,
    "gn:feature_class":"P",
    "gn:feature_code":"PPL",
    "gn:name":"Monte Alto",
    "gn:population":0,
    "gn:timezone":"America/Punta_Arenas",
    "iso:country":"CL",
    "name:ceb_x_preferred":[
        "Monte Alto"
    ],
    "name:ita_x_preferred":[
        "Monte Alto"
    ],
    "name:mlg_x_preferred":[
        "Monte Alto"
    ],
    "name:nld_x_preferred":[
        "Monte Alto"
    ],
    "name:pol_x_preferred":[
        "Monte Alto"
    ],
    "name:por_x_preferred":[
        "Monte Alto"
    ],
    "name:spa_x_preferred":[
        "Monte Alto"
    ],
    "name:srp_x_preferred":[
        "\u041c\u043e\u043d\u0442\u0435 \u0410\u043b\u0442\u043e"
    ],
    "name:swe_x_preferred":[
        "Monte Alto"
    ],
    "wof:name":"Monte Alto",
    "wof:placetype":"locality"
},
  "geometry": {"coordinates":[-71.89575000000001,-52.05118],"type":"Point"}
}