{
  "type": "Feature",
  "properties": {
    "iso:country":"CL",
    "name:bre_x_preferred":[
        "San Fernando"
    ],
    "name:bul_x_preferred":[
        "\u0421\u0430\u043d \u0424\u0435\u0440\u043d\u0430\u043d\u0434\u043e"
    ],
    "name:cat_x_preferred":[
        "San Fernando"
    ],
    "name:ceb_x_preferred":[
        "San Fernando"
    ],
    "name:ces_x_preferred":[
        "San Fernando"
    ],
    "name:deu_x_preferred":[
        "San Fernando"
    ],
    "name:epo_x_preferred":[
        "San Fernando"
    ],
    "name:eus_x_preferred":[
        "San Fernando"
    ],
    "name:fas_x_preferred":[
        "\u0633\u0627\u0646 \u0641\u0631\u0646\u0627\u0646\u062f\u0648"
    ],
    "name:fra_x_preferred":[
        "San Fernando"
    ],
    "name:glg_x_preferred":[
        "San Fernando"
    ],
    "name:heb_x_preferred":[
        "\u05e1\u05df \u05e4\u05e8\u05e0\u05e0\u05d3\u05d5"
    ],
    "name:hrv_x_preferred":[
        "San Fernando"
    ],
    "name:hun_x_preferred":[
        "San Fernando"
    ],
    "name:ilo_x_preferred":[
        "San Fernando"
    ],
    "name:ita_x_preferred":[
        "San Fernando"
    ],
    "name:jpn_x_preferred":[
        "\u30b5\u30f3\u30d5\u30a7\u30eb\u30ca\u30f3\u30c9"
    ],
    "name:kor_x_preferred":[
        "\uc0b0\ud398\ub974\ub09c\ub3c4"
    ],
    "name:lit_x_preferred":[
        "San Fernandas"
    ],
    "name:mlg_x_preferred":[
        "San Fernando"
    ],
    "name:msa_x_preferred":[
        "San Fernando"
    ],
    "name:nld_x_preferred":[
        "San Fernando"
    ],
    "name:nor_x_preferred":[
        "San Fernando"
    ],
    "name:pol_x_preferred":[
        "San Fernando"
    ],
    "name:por_x_preferred":[
        "S\u00e3o Fernando"
    ],
    "name:rus_x_preferred":[
        "\u0421\u0430\u043d-\u0424\u0435\u0440\u043d\u0430\u043d\u0434\u043e"
    ],
    "name:sco_x_preferred":[
        "San Fernando"
    ],
    "name:spa_x_preferred":[
        "San Fernando"
    ],
    "name:srp_x_preferred":[
        "\u0421\u0430\u043d \u0424\u0435\u0440\u043d\u0430\u043d\u0434\u043e"
    ],
    "name:swa_x_preferred":[
        "San Fernando"
    ],
    "name:swe_x_preferred":[
        "San Fernando"
    ],
    "name:tur_x_preferred":[
        "San Fernando"
    ],
    "name:ukr_x_preferred":[
        "\u0421\u0430\u043d-\u0424\u0435\u0440\u043d\u0430\u043d\u0434\u043e"
    ],
    "name:vie_x_preferred":[
        "San Fernando"
    ],
    "name:war_x_preferred":[
        "San Fernando"
    ],
    "qs:name":"San Fernando",
    "qs:name_adm0":"Chile",
    "qs:name_adm1":"Libertador General Bernardo O'Higgins",
    "qs:photos":2,
    "qs:photos_1k":1,
    "qs:photos_9k":4,
    "qs:photos_9r":6,
    "qs:photos_all":847,
    "qs:photos_sr":1,
    "qs:placetype":"LocalAdmin",
    "qs:pop_sr":"0",
    "wd:wordcount":216,
    "wof:name":"San Fernando",
    "wof:placetype":"localadmin"
},
  "geometry": {"coordinates":[-70.98515999999999,-34.584747],"type":"Point"}
}