{
  "type": "Feature",
  "properties": {
    "iso:country":"CL",
    "qs:name":"San Fernando",
    "qs:name_adm0":"Chile",
    "qs:name_adm1":"Libertador General Bernardo O'Higgins",
    "qs:photos":2,
    "qs:photos_1k":1,
    "qs:photos_9k":4,
    "qs:photos_9r":6,
    "qs:photos_all":847,
    "qs:photos_sr":1,
    "qs:placetype":"LocalAdmin",
    "qs:pop_sr":"0",
    "wd:wordcount":216,
    "wof:name":"San Fernando",
    "wof:placetype":"localadmin"
},
  "geometry": {"coordinates":[-70.98515999999999,-34.584747],"type":"Point"}
}