{
  "type": "Feature",
  "properties": {
    "gn:admin1_code":"15.0",
    "gn:admin2_code":"11.0",
    "gn:asciiname":"Cavancha",
    "gn:country_code":"CL",
    "gn:dem":12,
    "gn:feature_class":"P",
    "gn:feature_code":"PPL",
    "gn:name":"Cavancha",
    "gn:population":0,
    "gn:timezone":"America/Santiago",
    "iso:country":"CL",
    "wof:name":"Cavancha",
    "wof:placetype":"locality"
},
  "geometry": {"coordinates":[-70.14976999999999,-20.23679],"type":"Point"}
}