{
  "type": "Feature",
  "properties": {
    "gn:admin1_code":"3.0",
    "gn:admin2_code":"21.0",
    "gn:admin3_code":"2104.0",
    "gn:asciiname":"Yolanda Norte",
    "gn:country_code":"CL",
    "gn:dem":2316,
    "gn:feature_class":"P",
    "gn:feature_code":"PPL",
    "gn:name":"Yolanda Norte",
    "gn:population":0,
    "gn:timezone":"America/Santiago",
    "iso:country":"CL",
    "wof:name":"Yolanda Norte",
    "wof:placetype":"locality"
},
  "geometry": {"coordinates":[-70.11667,-24.91667],"type":"Point"}
}