{
  "type": "Feature",
  "properties": {
    "gn:country":"CL",
    "gn:fcode":"PPL",
    "gn:pop":0,
    "iso:country":"CL",
    "name:eng_x_preferred":[
        "Melinka"
    ],
    "name:fas_x_preferred":[
        "\u0645\u0644\u06cc\u0646\u06a9\u0627"
    ],
    "name:fra_x_preferred":[
        "Melinka"
    ],
    "name:ita_x_preferred":[
        "Melinka"
    ],
    "name:jpn_x_preferred":[
        "\u30e1\u30ea\u30f3\u30ab"
    ],
    "name:lit_x_preferred":[
        "Melinka"
    ],
    "name:nld_x_preferred":[
        "Melinka"
    ],
    "name:ron_x_preferred":[
        "Melinka"
    ],
    "name:spa_x_preferred":[
        "Melinka"
    ],
    "name:unk_x_variant":[
        "Melinca"
    ],
    "qs:name":"Melinka",
    "qs:name_adm0":"Chile",
    "qs:name_adm1":"Aisen del General Carlos Ibanez Del Campo",
    "qs:photos":57,
    "qs:photos_1k":12,
    "qs:photos_9k":1,
    "qs:photos_9r":2,
    "qs:photos_all":57,
    "qs:photos_sr":2,
    "qs:placetype":"Town",
    "qs:pop_sr":"0",
    "wd:wordcount":156,
    "wof:name":"Melinka",
    "wof:placetype":"locality",
    "wof:population":0
},
  "geometry": {"coordinates":[-73.74559000000001,-43.89696],"type":"Point"}
}