{
  "type": "Feature",
  "properties": {
    "gn:admin1_code":"11.0",
    "gn:admin2_code":"73.0",
    "gn:admin3_code":"7308.0",
    "gn:asciiname":"Montella",
    "gn:country_code":"CL",
    "gn:dem":320,
    "gn:feature_class":"P",
    "gn:feature_code":"PPL",
    "gn:name":"Montella",
    "gn:population":0,
    "gn:timezone":"America/Santiago",
    "iso:country":"CL",
    "name:und_x_variant":[
        "Monterilla",
        "Monteria",
        "Montella"
    ],
    "wof:name":"Montella",
    "wof:placetype":"locality"
},
  "geometry": {"coordinates":[-71.07124,-34.83574],"type":"Point"}
}