{
  "type": "Feature",
  "properties": {
    "gn:admin1_code":"11.0",
    "gn:admin2_code":"73.0",
    "gn:admin3_code":"7308.0",
    "gn:asciiname":"Montella",
    "gn:country_code":"CL",
    "gn:dem":320,
    "gn:feature_class":"P",
    "gn:feature_code":"PPL",
    "gn:name":"Montella",
    "gn:population":0,
    "gn:timezone":"America/Santiago",
    "iso:country":"CL",
    "name:azb_x_preferred":[
        "\u0645\u0648\u0646\u062a\u0644\u0627"
    ],
    "name:bar_x_preferred":[
        "Montella"
    ],
    "name:bul_x_preferred":[
        "\u041c\u043e\u043d\u0442\u0435\u043b\u0430"
    ],
    "name:ceb_x_preferred":[
        "Montella"
    ],
    "name:deu_x_preferred":[
        "Montella"
    ],
    "name:epo_x_preferred":[
        "Montella"
    ],
    "name:eus_x_preferred":[
        "Montella"
    ],
    "name:fas_x_preferred":[
        "\u0645\u0648\u0646\u062a\u0644\u0627"
    ],
    "name:fin_x_preferred":[
        "Montella"
    ],
    "name:fra_x_preferred":[
        "Montella"
    ],
    "name:hun_x_preferred":[
        "Montella"
    ],
    "name:hye_x_preferred":[
        "\u0544\u0578\u0576\u057f\u0565\u056c\u0561"
    ],
    "name:ina_x_preferred":[
        "Montella"
    ],
    "name:ita_x_preferred":[
        "Montella"
    ],
    "name:jpn_x_preferred":[
        "\u30e2\u30f3\u30c6\u30c3\u30e9"
    ],
    "name:kaz_x_preferred":[
        "\u041c\u043e\u043d\u0442\u0435\u043b\u043b\u0430"
    ],
    "name:kor_x_preferred":[
        "\ubaac\ud154\ub77c"
    ],
    "name:lat_x_preferred":[
        "Montella"
    ],
    "name:lmo_x_preferred":[
        "Montella"
    ],
    "name:mkd_x_preferred":[
        "\u041c\u043e\u043d\u0442\u0435\u043b\u0430"
    ],
    "name:msa_x_preferred":[
        "Montella"
    ],
    "name:nap_x_preferred":[
        "Montella"
    ],
    "name:nld_x_preferred":[
        "Montella"
    ],
    "name:pms_x_preferred":[
        "Montella"
    ],
    "name:pol_x_preferred":[
        "Montella"
    ],
    "name:por_x_preferred":[
        "Montella"
    ],
    "name:ron_x_preferred":[
        "Montella"
    ],
    "name:rus_x_preferred":[
        "\u041c\u043e\u043d\u0442\u0435\u043b\u043b\u0430"
    ],
    "name:scn_x_preferred":[
        "Muntella"
    ],
    "name:spa_x_preferred":[
        "Montella"
    ],
    "name:srp_x_preferred":[
        "\u041c\u043e\u043d\u0442\u0435\u043b\u0430"
    ],
    "name:swe_x_preferred":[
        "Montella"
    ],
    "name:tgl_x_preferred":[
        "Montella"
    ],
    "name:ukr_x_preferred":[
        "\u041c\u043e\u043d\u0442\u0435\u043b\u043b\u0430"
    ],
    "name:und_x_variant":[
        "Monterilla",
        "Monteria",
        "Montella"
    ],
    "name:vec_x_preferred":[
        "Montella"
    ],
    "name:vie_x_preferred":[
        "Montella"
    ],
    "name:vol_x_preferred":[
        "Montella"
    ],
    "name:war_x_preferred":[
        "Montella"
    ],
    "name:zho_x_preferred":[
        "\u8499\u6cf0\u62c9"
    ],
    "wof:name":"Montella",
    "wof:placetype":"locality"
},
  "geometry": {"coordinates":[-71.07124,-34.83574],"type":"Point"}
}