{
  "type": "Feature",
  "properties": {
    "gn:admin1_code":"7.0",
    "gn:admin2_code":"43.0",
    "gn:admin3_code":"4301.0",
    "gn:asciiname":"Talinay Bajo",
    "gn:country_code":"CL",
    "gn:dem":250,
    "gn:feature_class":"P",
    "gn:feature_code":"PPL",
    "gn:name":"Talinay Bajo",
    "gn:population":0,
    "gn:timezone":"America/Santiago",
    "iso:country":"CL",
    "wof:name":"Talinay Bajo",
    "wof:placetype":"locality"
},
  "geometry": {"coordinates":[-71.61535000000001,-30.8652],"type":"Point"}
}