{
  "type": "Feature",
  "properties": {
    "gn:admin1_code":"15.0",
    "gn:admin2_code":"14.0",
    "gn:admin3_code":"1403.0",
    "gn:asciiname":"Vilacollo",
    "gn:country_code":"CL",
    "gn:dem":4262,
    "gn:feature_class":"P",
    "gn:feature_code":"PPL",
    "gn:name":"Vilacollo",
    "gn:population":0,
    "gn:timezone":"America/Santiago",
    "iso:country":"CL",
    "name:spa_x_preferred":[
        "Vilacollo"
    ],
    "name:spa_x_variant":[
        "Parajalla"
    ],
    "name:und_x_variant":[
        "Parajalla Vilacollo"
    ],
    "wof:name":"Vilacollo",
    "wof:placetype":"locality"
},
  "geometry": {"coordinates":[-68.93061,-19.08554],"type":"Point"}
}