{
  "type": "Feature",
  "properties": {
    "gn:admin1_code":"14.0",
    "gn:admin2_code":"101.0",
    "gn:admin3_code":"10102.0",
    "gn:asciiname":"Ahinco",
    "gn:country_code":"CL",
    "gn:dem":3,
    "gn:feature_class":"P",
    "gn:feature_code":"PPL",
    "gn:name":"Ahinco",
    "gn:population":0,
    "gn:timezone":"America/Santiago",
    "iso:country":"CL",
    "name:und_x_variant":[
        "Ainco",
        "Auc\u00f3",
        "Ahinco"
    ],
    "wof:name":"Ahinco",
    "wof:placetype":"locality"
},
  "geometry": {"coordinates":[-73.51487,-41.78234000000001],"type":"Point"}
}