{
  "type": "Feature",
  "properties": {
    "gn:admin1_code":"8.0",
    "gn:admin2_code":"62.0",
    "gn:admin3_code":"6205.0",
    "gn:asciiname":"El Maiten",
    "gn:country_code":"CL",
    "gn:dem":71,
    "gn:feature_class":"P",
    "gn:feature_code":"PPL",
    "gn:name":"El Mait\u00e9n",
    "gn:population":0,
    "gn:timezone":"America/Santiago",
    "iso:country":"CL",
    "wof:name":"El Maiten",
    "wof:placetype":"locality"
},
  "geometry": {"coordinates":[-71.81572,-33.99815],"type":"Point"}
}