{
  "type": "Feature",
  "properties": {
    "gn:admin1_code":"3.0",
    "gn:admin2_code":"22.0",
    "gn:admin3_code":"2201.0",
    "gn:asciiname":"Toconce",
    "gn:country_code":"CL",
    "gn:dem":3322,
    "gn:feature_class":"P",
    "gn:feature_code":"PPL",
    "gn:name":"Toconce",
    "gn:population":0,
    "gn:timezone":"America/Santiago",
    "iso:country":"CL",
    "wof:name":"Toconce",
    "wof:placetype":"locality"
},
  "geometry": {"coordinates":[-68.16565,-22.26505],"type":"Point"}
}