{
  "type": "Feature",
  "properties": {
    "iso:country":"CL",
    "qs:name":"Rancagua",
    "qs:name_adm0":"Chile",
    "qs:name_adm1":"Libertador General Bernardo O'Higgins",
    "qs:photos":41,
    "qs:photos_1k":8,
    "qs:photos_9k":11,
    "qs:photos_9r":10,
    "qs:photos_all":2535,
    "qs:photos_sr":2,
    "qs:placetype":"LocalAdmin",
    "qs:pop_sr":"0",
    "wd:wordcount":1346,
    "wof:name":"Rancagua",
    "wof:placetype":"localadmin"
},
  "geometry": {"coordinates":[-70.728263,-34.167925],"type":"Point"}
}