{
  "type": "Feature",
  "properties": {
    "gn:admin1_code":"12.0",
    "gn:admin2_code":"135.0",
    "gn:admin3_code":"13505.0",
    "gn:asciiname":"Lo Chacon",
    "gn:country_code":"CL",
    "gn:dem":173,
    "gn:feature_class":"P",
    "gn:feature_code":"PPL",
    "gn:name":"Lo Chac\u00f3n",
    "gn:population":0,
    "gn:timezone":"America/Santiago",
    "iso:country":"CL",
    "name:und_x_variant":[
        "Chacon",
        "Lo Chac\u00f3n"
    ],
    "wof:name":"Lo Chacon",
    "wof:placetype":"locality"
},
  "geometry": {"coordinates":[-71.30978,-33.98847],"type":"Point"}
}