{
  "type": "Feature",
  "properties": {
    "gn:admin1_code":"5.0",
    "gn:admin2_code":"33.0",
    "gn:admin3_code":"3301.0",
    "gn:asciiname":"Cachiyuyo",
    "gn:country_code":"CL",
    "gn:dem":823,
    "gn:feature_class":"P",
    "gn:feature_code":"PPL",
    "gn:name":"Cachiyuyo",
    "gn:population":0,
    "gn:timezone":"America/Santiago",
    "iso:country":"CL",
    "name:spa_x_preferred":[
        "Cachiyuyo"
    ],
    "wof:name":"Cachiyuyo",
    "wof:placetype":"locality"
},
  "geometry": {"coordinates":[-70.89788,-29.03637],"type":"Point"}
}