{
  "type": "Feature",
  "properties": {
    "gn:admin1_code":"1.0",
    "gn:admin2_code":"58.0",
    "gn:admin3_code":"5801.0",
    "gn:asciiname":"El Llano del Totoral",
    "gn:cc2":"CL",
    "gn:country_code":"CL",
    "gn:dem":550,
    "gn:feature_class":"P",
    "gn:feature_code":"PPL",
    "gn:name":"El Llano del Totoral",
    "gn:population":0,
    "gn:timezone":"America/Santiago",
    "iso:country":"CL",
    "name:und_x_variant":[
        "El Llano",
        "El Llano del Totoral"
    ],
    "wof:name":"El Llano del Totoral",
    "wof:placetype":"locality"
},
  "geometry": {"coordinates":[-71.26666999999998,-33.18333],"type":"Point"}
}