{
  "type": "Feature",
  "properties": {
    "gn:admin1_code":"15.0",
    "gn:admin2_code":"14.0",
    "gn:admin3_code":"1403.0",
    "gn:asciiname":"Pansuta",
    "gn:country_code":"CL",
    "gn:dem":4218,
    "gn:feature_class":"P",
    "gn:feature_code":"PPL",
    "gn:name":"Pansuta",
    "gn:population":0,
    "gn:timezone":"America/Santiago",
    "iso:country":"CL",
    "name:spa_x_preferred":[
        "Pansuta"
    ],
    "wof:name":"Pansuta",
    "wof:placetype":"locality"
},
  "geometry": {"coordinates":[-68.89253000000001,-19.06249],"type":"Point"}
}