{
  "type": "Feature",
  "properties": {
    "iso:country":"CL",
    "qs:name":"Bulnes",
    "qs:name_adm0":"Chile",
    "qs:name_adm1":"Biobio",
    "qs:photos":1,
    "qs:photos_1k":1,
    "qs:photos_9k":1,
    "qs:photos_9r":3,
    "qs:photos_all":92,
    "qs:photos_sr":1,
    "qs:placetype":"LocalAdmin",
    "qs:pop_sr":"0",
    "wd:wordcount":96,
    "wof:name":"Bulnes",
    "wof:placetype":"localadmin"
},
  "geometry": {"coordinates":[-72.296188,-36.743973],"type":"Point"}
}