{
  "type": "Feature",
  "properties": {
    "gn:admin1_code":"7.0",
    "gn:admin2_code":"43.0",
    "gn:admin3_code":"4301.0",
    "gn:asciiname":"Bali",
    "gn:country_code":"CL",
    "gn:dem":90,
    "gn:feature_class":"P",
    "gn:feature_code":"PPL",
    "gn:name":"Bal\u00ed",
    "gn:population":0,
    "gn:timezone":"America/Santiago",
    "iso:country":"CL",
    "wof:name":"Bali",
    "wof:placetype":"locality"
},
  "geometry": {"coordinates":[-71.43078,-30.6387],"type":"Point"}
}