{
  "type": "Feature",
  "properties": {
    "gn:admin1_code":"8.0",
    "gn:admin2_code":"61.0",
    "gn:admin3_code":"6109.0",
    "gn:asciiname":"Monte Atajo",
    "gn:country_code":"CL",
    "gn:dem":589,
    "gn:feature_class":"P",
    "gn:feature_code":"PPL",
    "gn:name":"Monte Atajo",
    "gn:population":0,
    "gn:timezone":"America/Santiago",
    "iso:country":"CL",
    "wof:name":"Monte Atajo",
    "wof:placetype":"locality"
},
  "geometry": {"coordinates":[-70.96666999999999,-34.43333],"type":"Point"}
}