{
  "type": "Feature",
  "properties": {
    "gn:admin1_code":"7.0",
    "gn:admin2_code":"43.0",
    "gn:admin3_code":"4303.0",
    "gn:asciiname":"El Maqui",
    "gn:country_code":"CL",
    "gn:dem":1108,
    "gn:feature_class":"P",
    "gn:feature_code":"PPL",
    "gn:name":"El Maqui",
    "gn:population":0,
    "gn:timezone":"America/Santiago",
    "iso:country":"CL",
    "name:fas_x_preferred":[
        "\u0627\u0644 \u0645\u0627\u06a9\u06cc"
    ],
    "wof:name":"El Maqui",
    "wof:placetype":"locality"
},
  "geometry": {"coordinates":[-70.65058000000001,-30.82872],"type":"Point"}
}