{
  "type": "Feature",
  "properties": {
    "iso:country":"CL",
    "qs:name":"Nogales",
    "qs:name_adm0":"Chile",
    "qs:name_adm1":"Valpara\u00edso",
    "qs:photos":1,
    "qs:photos_1k":1,
    "qs:photos_9k":1,
    "qs:photos_9r":2,
    "qs:photos_all":45,
    "qs:photos_sr":1,
    "qs:placetype":"LocalAdmin",
    "qs:pop_sr":"0",
    "wd:wordcount":49,
    "wof:name":"Nogales",
    "wof:placetype":"localadmin"
},
  "geometry": {"coordinates":[-71.201179,-32.728418],"type":"Point"}
}