{
  "type": "Feature",
  "properties": {
    "iso:country":"CL",
    "name:cat_x_preferred":[
        "Nogales"
    ],
    "name:ceb_x_preferred":[
        "Nogales"
    ],
    "name:ces_x_preferred":[
        "Nogales"
    ],
    "name:deu_x_preferred":[
        "Nogales"
    ],
    "name:epo_x_preferred":[
        "Nogales"
    ],
    "name:est_x_preferred":[
        "Nogales"
    ],
    "name:eus_x_preferred":[
        "Nogales"
    ],
    "name:fra_x_preferred":[
        "Nogales"
    ],
    "name:glg_x_preferred":[
        "Nogales"
    ],
    "name:heb_x_preferred":[
        "\u05e0\u05d5\u05d2\u05dc\u05e1"
    ],
    "name:hun_x_preferred":[
        "Nogales"
    ],
    "name:ita_x_preferred":[
        "Nogales"
    ],
    "name:jpn_x_preferred":[
        "\u30ce\u30ac\u30fc\u30ec\u30b9"
    ],
    "name:kor_x_preferred":[
        "\ub178\uac08\ub808\uc2a4"
    ],
    "name:lit_x_preferred":[
        "Nogalesas"
    ],
    "name:msa_x_preferred":[
        "Nogales"
    ],
    "name:nld_x_preferred":[
        "Nogales"
    ],
    "name:nor_x_preferred":[
        "Nogales"
    ],
    "name:pol_x_preferred":[
        "Nogales"
    ],
    "name:por_x_preferred":[
        "Nogales"
    ],
    "name:rus_x_preferred":[
        "\u041d\u043e\u0433\u0430\u043b\u0435\u0441"
    ],
    "name:sco_x_preferred":[
        "Nogales"
    ],
    "name:spa_x_preferred":[
        "Nogales"
    ],
    "name:srp_x_preferred":[
        "\u041d\u043e\u0433\u0430\u043b\u0435\u0441"
    ],
    "name:swe_x_preferred":[
        "Nogales"
    ],
    "name:vie_x_preferred":[
        "Nogales"
    ],
    "name:war_x_preferred":[
        "Nogales"
    ],
    "qs:name":"Nogales",
    "qs:name_adm0":"Chile",
    "qs:name_adm1":"Valpara\u00edso",
    "qs:photos":1,
    "qs:photos_1k":1,
    "qs:photos_9k":1,
    "qs:photos_9r":2,
    "qs:photos_all":45,
    "qs:photos_sr":1,
    "qs:placetype":"LocalAdmin",
    "qs:pop_sr":"0",
    "wd:wordcount":49,
    "wof:name":"Nogales",
    "wof:placetype":"localadmin"
},
  "geometry": {"coordinates":[-71.201179,-32.728418],"type":"Point"}
}