{
  "type": "Feature",
  "properties": {
    "gn:admin1_code":"6.0",
    "gn:admin2_code":"84.0",
    "gn:admin3_code":"8403.0",
    "gn:asciiname":"Tiuquilemu",
    "gn:country_code":"CL",
    "gn:dem":15,
    "gn:feature_class":"P",
    "gn:feature_code":"PPL",
    "gn:name":"Tiuquilemu",
    "gn:population":0,
    "gn:timezone":"America/Santiago",
    "iso:country":"CL",
    "wof:name":"Tiuquilemu",
    "wof:placetype":"locality"
},
  "geometry": {"coordinates":[-72.77605,-36.06842],"type":"Point"}
}