{
  "type": "Feature",
  "properties": {
    "gn:admin1_code":"10.0",
    "gn:admin2_code":"121.0",
    "gn:asciiname":"Seccion Las Vacas",
    "gn:country_code":"CL",
    "gn:dem":374,
    "gn:feature_class":"P",
    "gn:feature_code":"PPL",
    "gn:name":"Secci\u00f3n Las Vacas",
    "gn:population":0,
    "gn:timezone":"America/Punta_Arenas",
    "iso:country":"CL",
    "name:spa_x_preferred":[
        "Secci\u00f3n Las Vacas"
    ],
    "wof:name":"Seccion Las Vacas",
    "wof:placetype":"locality"
},
  "geometry": {"coordinates":[-71.59595999999998,-52.31107],"type":"Point"}
}