{
  "type": "Feature",
  "properties": {
    "gn:admin1_code":"5.0",
    "gn:admin2_code":"31.0",
    "gn:admin3_code":"3101.0",
    "gn:asciiname":"Carpa Numero Cuatro",
    "gn:country_code":"CL",
    "gn:dem":315,
    "gn:feature_class":"P",
    "gn:feature_code":"PPL",
    "gn:name":"Carpa N\u00famero Cuatro",
    "gn:population":0,
    "gn:timezone":"America/Santiago",
    "iso:country":"CL",
    "name:und_x_variant":[
        "Carpa 4",
        "Carpa N\u00famero 4",
        "Carpa N\u00famero Cuatro"
    ],
    "wof:name":"Carpa Numero Cuatro",
    "wof:placetype":"locality"
},
  "geometry": {"coordinates":[-70.40382,-27.31538],"type":"Point"}
}