{
  "type": "Feature",
  "properties": {
    "gn:admin1_code":"14.0",
    "gn:admin2_code":"101.0",
    "gn:admin3_code":"10103.0",
    "gn:asciiname":"Quila",
    "gn:country_code":"CL",
    "gn:dem":939,
    "gn:feature_class":"P",
    "gn:feature_code":"PPL",
    "gn:name":"Quila",
    "gn:population":0,
    "gn:timezone":"America/Santiago",
    "iso:country":"CL",
    "wof:name":"Quila",
    "wof:placetype":"locality"
},
  "geometry": {"coordinates":[-72.23333000000002,-41.45],"type":"Point"}
}