{
  "type": "Feature",
  "properties": {
    "gn:admin1_code":"5.0",
    "gn:admin2_code":"31.0",
    "gn:admin3_code":"3103.0",
    "gn:asciiname":"Ramadilla",
    "gn:country_code":"CL",
    "gn:dem":2148,
    "gn:feature_class":"P",
    "gn:feature_code":"PPL",
    "gn:name":"Ramadilla",
    "gn:population":0,
    "gn:timezone":"America/Santiago",
    "iso:country":"CL",
    "wof:name":"Ramadilla",
    "wof:placetype":"locality"
},
  "geometry": {"coordinates":[-69.74559000000001,-28.11118],"type":"Point"}
}