{
  "type": "Feature",
  "properties": {
    "gn:country":"CL",
    "gn:fcode":"ADM3",
    "gn:population":0,
    "iso:country":"CL",
    "name:ara_x_preferred":[
        "\u0633\u0627\u0646 \u0631\u0627\u0645\u0648\u0646"
    ],
    "name:ben_x_preferred":[
        "\u09b8\u09be\u09a8 \u09b0\u09be\u09ae\u09cb\u09a8"
    ],
    "name:ell_x_preferred":[
        "\u03a3\u03b1\u03bd \u03a1\u03b1\u03bc\u03cc\u03bd"
    ],
    "name:fas_x_preferred":[
        "\u0633\u0646 \u0631\u0627\u0645\u0648\u0646"
    ],
    "name:fra_x_preferred":[
        "San Ram\u00f3n"
    ],
    "name:heb_x_preferred":[
        "\u05e1\u05df \u05e8\u05de\u05d5\u05df"
    ],
    "name:hin_x_preferred":[
        "\u0938\u0948\u0928 \u0930\u0947\u092e\u0928"
    ],
    "name:hun_x_preferred":[
        "San Ramon"
    ],
    "name:ind_x_preferred":[
        "San Ramon"
    ],
    "name:ita_x_preferred":[
        "San Ram\u00f3n"
    ],
    "name:kor_x_preferred":[
        "\uc0b0\ub77c\ubaac"
    ],
    "name:pol_x_preferred":[
        "San Ramon"
    ],
    "name:por_x_preferred":[
        "San Ram\u00f3n"
    ],
    "name:rus_x_preferred":[
        "\u0421\u0430\u043d-\u0420\u0430\u043c\u043e\u043d"
    ],
    "name:swe_x_preferred":[
        "San Ramon"
    ],
    "name:tur_x_preferred":[
        "San Ramon"
    ],
    "name:ukr_x_preferred":[
        "\u0421\u0430\u043d-\u0420\u0430\u043c\u043e\u043d"
    ],
    "name:urd_x_preferred":[
        "\u0633\u0627\u0646 \u0631\u06cc\u0645\u0648\u0646"
    ],
    "name:vie_x_preferred":[
        "San Ramon"
    ],
    "name:zho_cn_x_preferred":[
        "\u5723\u62c9\u8499"
    ],
    "name:zho_tw_x_preferred":[
        "\u8056\u62c9\u8499"
    ],
    "qs_pg:aaroncc":"CL",
    "qs_pg:gn_country":"CL",
    "qs_pg:gn_fcode":"ADM3",
    "qs_pg:gn_pop":0,
    "qs_pg:name":"San Ramon",
    "qs_pg:name_adm0":"Chile",
    "qs_pg:name_adm1":"Santiago",
    "qs_pg:photos_9k":1,
    "qs_pg:photos_9r":3,
    "qs_pg:photos_all":78,
    "qs_pg:photos_sr":0,
    "qs_pg:pop_sr":0,
    "qs_pg:qs_pg_placetype":"localadmin",
    "qs_pg:qs_pg_placetype_gp":"LocalAdmin",
    "qs_pg:woe_adm0":23424782,
    "woe:adm0_id":23424782,
    "woe:name_adm0":"Chile",
    "woe:name_adm1":"Santiago",
    "woe:placetype":"LocalAdmin",
    "wof:name":"San Ramon",
    "wof:placetype":"localadmin"
},
  "geometry": {"coordinates":[-70.6422,-33.53142],"type":"Point"}
}