{
  "type": "Feature",
  "properties": {
    "gn:gn_country":"CL",
    "gn:gn_fcode":"ADM3",
    "gn:gn_pop":0,
    "iso:country":"CL",
    "qs_pg:aaroncc":"CL",
    "qs_pg:gn_country":"CL",
    "qs_pg:gn_fcode":"ADM3",
    "qs_pg:gn_pop":0,
    "qs_pg:name":"San Ramon",
    "qs_pg:name_adm0":"Chile",
    "qs_pg:name_adm1":"Santiago",
    "qs_pg:photos_9k":1,
    "qs_pg:photos_9r":3,
    "qs_pg:photos_all":78,
    "qs_pg:photos_sr":0,
    "qs_pg:pop_sr":0,
    "qs_pg:qs_pg_placetype":"localadmin",
    "qs_pg:qs_pg_placetype_gp":"LocalAdmin",
    "qs_pg:woe_adm0":23424782,
    "woe:adm0_id":23424782,
    "woe:name_adm0":"Chile",
    "woe:name_adm1":"Santiago",
    "woe:placetype":"LocalAdmin",
    "wof:name":"San Ramon",
    "wof:placetype":"localadmin"
},
  "geometry": {"coordinates":[-70.6422,-33.53142],"type":"Point"}
}