{
  "type": "Feature",
  "properties": {
    "gn:admin1_code":"8.0",
    "gn:admin2_code":"63.0",
    "gn:admin3_code":"6301.0",
    "gn:asciiname":"Talcarehue",
    "gn:country_code":"CL",
    "gn:dem":414,
    "gn:feature_class":"P",
    "gn:feature_code":"PPL",
    "gn:name":"Talcarehue",
    "gn:population":0,
    "gn:timezone":"America/Santiago",
    "iso:country":"CL",
    "wof:name":"Talcarehue",
    "wof:placetype":"locality"
},
  "geometry": {"coordinates":[-70.92511999999998,-34.62313],"type":"Point"}
}