{
  "type": "Feature",
  "properties": {
    "gn:admin1_code":"8.0",
    "gn:admin2_code":"62.0",
    "gn:admin3_code":"6204.0",
    "gn:asciiname":"Polcura",
    "gn:country_code":"CL",
    "gn:dem":198,
    "gn:feature_class":"P",
    "gn:feature_code":"PPL",
    "gn:name":"Polcura",
    "gn:population":0,
    "gn:timezone":"America/Santiago",
    "iso:country":"CL",
    "wof:name":"Polcura",
    "wof:placetype":"locality"
},
  "geometry": {"coordinates":[-71.63951,-34.32188],"type":"Point"}
}