{
  "type": "Feature",
  "properties": {
    "gn:admin1_code":"14.0",
    "gn:admin2_code":"103.0",
    "gn:admin3_code":"10303.0",
    "gn:asciiname":"Corte Alto",
    "gn:country_code":"CL",
    "gn:dem":139,
    "gn:feature_class":"P",
    "gn:feature_code":"PPL",
    "gn:name":"Corte Alto",
    "gn:population":0,
    "gn:timezone":"America/Santiago",
    "iso:country":"CL",
    "name:spa_x_preferred":[
        "Corte Alto"
    ],
    "wof:name":"Corte Alto",
    "wof:placetype":"locality"
},
  "geometry": {"coordinates":[-73.16074,-40.95166],"type":"Point"}
}