{
  "type": "Feature",
  "properties": {
    "iso:country":"CL",
    "name:ara_x_preferred":[
        "\u0643\u0648\u0644\u064a\u0628\u064a\u0648\u0644\u064a"
    ],
    "name:arn_x_preferred":[
        "Collipulli"
    ],
    "name:ben_x_preferred":[
        "\u0995\u09cb\u09b2\u09cd\u09b2\u09bf\u09aa\u09c1\u09b2\u09cd\u09b2\u09bf"
    ],
    "name:cat_x_preferred":[
        "Collipulli"
    ],
    "name:ceb_x_preferred":[
        "Collipulli"
    ],
    "name:deu_x_preferred":[
        "Collipulli"
    ],
    "name:ell_x_preferred":[
        "\u039a\u03bf\u03b3\u03b9\u03c0\u03bf\u03cd\u03b3\u03b9"
    ],
    "name:eng_x_preferred":[
        "Collipulli"
    ],
    "name:eus_x_preferred":[
        "Collipulli"
    ],
    "name:fas_x_preferred":[
        "\u06a9\u0648\u0644\u06cc\u067e\u0648\u0644\u06cc"
    ],
    "name:fra_x_preferred":[
        "Collipulli"
    ],
    "name:heb_x_preferred":[
        "\u05e7\u05d5\u05d9\u05d9\u05e4\u05d5\u05d9\u05d9"
    ],
    "name:hin_x_preferred":[
        "\u0915\u094b\u0932\u0940\u092a\u0941\u0932\u0940"
    ],
    "name:hun_x_preferred":[
        "Collipulli"
    ],
    "name:ind_x_preferred":[
        "Collipulli"
    ],
    "name:ita_x_preferred":[
        "Collipulli"
    ],
    "name:jpn_x_preferred":[
        "\u30b3\u30b8\u30d7\u30b8"
    ],
    "name:kor_x_preferred":[
        "\ucf54\uc774\ud478\uc774"
    ],
    "name:nan_x_preferred":[
        "Collipulli"
    ],
    "name:nld_x_preferred":[
        "Collipulli"
    ],
    "name:oci_x_preferred":[
        "Collipulli"
    ],
    "name:pol_x_preferred":[
        "Collipulli"
    ],
    "name:por_x_preferred":[
        "Collipulli"
    ],
    "name:ron_x_preferred":[
        "Collipulli"
    ],
    "name:rus_x_preferred":[
        "\u041a\u043e\u043b\u044c\u0438\u043f\u0443\u043b\u044c\u0438"
    ],
    "name:spa_x_preferred":[
        "Collipulli"
    ],
    "name:swe_x_preferred":[
        "Collipulli"
    ],
    "name:tur_x_preferred":[
        "Collipulli"
    ],
    "name:ukr_x_preferred":[
        "\u041a\u043e\u043b\u043b\u0456\u043f\u0443\u043b\u043b\u0456"
    ],
    "name:ukr_x_variant":[
        "\u041a\u043e\u043b\u044c\u0457\u043f\u0443\u043b\u044c\u0457"
    ],
    "name:urd_x_preferred":[
        "\u06a9\u0648\u0644\u06cc\u067e\u0644\u06cc"
    ],
    "name:vie_x_preferred":[
        "Collipulli"
    ],
    "name:zho_x_preferred":[
        "\u79d1\u5229\u666e\u5229"
    ],
    "qs:name":"Collipulli",
    "qs:name_adm0":"Chile",
    "qs:name_adm1":"Araucania",
    "qs:photos":1,
    "qs:photos_1k":1,
    "qs:photos_9k":1,
    "qs:photos_9r":4,
    "qs:photos_all":224,
    "qs:photos_sr":1,
    "qs:placetype":"LocalAdmin",
    "qs:pop_sr":"0",
    "wd:wordcount":416,
    "wof:name":"Collipulli",
    "wof:placetype":"localadmin"
},
  "geometry": {"coordinates":[-72.431659,-37.958275],"type":"Point"}
}