{
  "type": "Feature",
  "properties": {
    "iso:country":"CL",
    "qs:name":"Collipulli",
    "qs:name_adm0":"Chile",
    "qs:name_adm1":"Araucania",
    "qs:photos":1,
    "qs:photos_1k":1,
    "qs:photos_9k":1,
    "qs:photos_9r":4,
    "qs:photos_all":224,
    "qs:photos_sr":1,
    "qs:placetype":"LocalAdmin",
    "qs:pop_sr":"0",
    "wd:wordcount":416,
    "wof:name":"Collipulli",
    "wof:placetype":"localadmin"
},
  "geometry": {"coordinates":[-72.431659,-37.958275],"type":"Point"}
}