{
  "type": "Feature",
  "properties": {
    "gn:admin1_code":"10.0",
    "gn:admin2_code":"123.0",
    "gn:admin3_code":"12301.0",
    "gn:asciiname":"Bersovio el Covacio",
    "gn:country_code":"CL",
    "gn:dem":38,
    "gn:feature_class":"P",
    "gn:feature_code":"PPL",
    "gn:name":"Bersovio el Covacio",
    "gn:population":0,
    "gn:timezone":"America/Punta_Arenas",
    "iso:country":"CL",
    "name:und_x_variant":[
        "Kovacic",
        "Bersovio el Covacio"
    ],
    "wof:name":"Bersovio el Covacio",
    "wof:placetype":"locality"
},
  "geometry": {"coordinates":[-70.06862,-53.43419],"type":"Point"}
}