{
  "type": "Feature",
  "properties": {
    "gn:admin1_code":"8.0",
    "gn:admin2_code":"63.0",
    "gn:admin3_code":"6310.0",
    "gn:asciiname":"Capellania",
    "gn:country_code":"CL",
    "gn:dem":175,
    "gn:feature_class":"P",
    "gn:feature_code":"PPL",
    "gn:name":"Capellan\u00eda",
    "gn:population":0,
    "gn:timezone":"America/Santiago",
    "iso:country":"CL",
    "wof:name":"Capellania",
    "wof:placetype":"locality"
},
  "geometry": {"coordinates":[-71.34924000000002,-34.64277],"type":"Point"}
}