{
  "type": "Feature",
  "properties": {
    "gn:admin1_code":"10.0",
    "gn:admin2_code":"121.0",
    "gn:asciiname":"Puerto Harris",
    "gn:country_code":"CL",
    "gn:dem":6,
    "gn:feature_class":"P",
    "gn:feature_code":"PPL",
    "gn:name":"Puerto Harris",
    "gn:population":0,
    "gn:timezone":"America/Punta_Arenas",
    "iso:country":"CL",
    "name:spa_x_preferred":[
        "Puerto Harris"
    ],
    "wof:name":"Puerto Harris",
    "wof:placetype":"locality"
},
  "geometry": {"coordinates":[-70.4517,-53.83503],"type":"Point"}
}