{
  "type": "Feature",
  "properties": {
    "gn:admin1_code":"14.0",
    "gn:admin2_code":"104.0",
    "gn:asciiname":"El Raizal",
    "gn:country_code":"CL",
    "gn:dem":219,
    "gn:feature_class":"P",
    "gn:feature_code":"PPL",
    "gn:name":"El Raizal",
    "gn:population":0,
    "gn:timezone":"America/Santiago",
    "iso:country":"CL",
    "name:spa_x_preferred":[
        "El Raizal"
    ],
    "wof:name":"El Raizal",
    "wof:placetype":"locality"
},
  "geometry": {"coordinates":[-72.01711,-43.34575],"type":"Point"}
}