{
  "type": "Feature",
  "properties": {
    "gn:admin1_code":"11.0",
    "gn:admin2_code":"73.0",
    "gn:admin3_code":"7309.0",
    "gn:asciiname":"La Montana",
    "gn:country_code":"CL",
    "gn:dem":135,
    "gn:feature_class":"P",
    "gn:feature_code":"PPL",
    "gn:name":"La Monta\u00f1a",
    "gn:population":0,
    "gn:timezone":"America/Santiago",
    "iso:country":"CL",
    "wof:name":"La Montana",
    "wof:placetype":"locality"
},
  "geometry": {"coordinates":[-71.96619,-34.90541],"type":"Point"}
}