{
  "type": "Feature",
  "properties": {
    "gn:admin1_code":"5.0",
    "gn:admin2_code":"31.0",
    "gn:asciiname":"Agua",
    "gn:country_code":"CL",
    "gn:dem":44,
    "gn:feature_class":"P",
    "gn:feature_code":"PPL",
    "gn:name":"Agua",
    "gn:population":0,
    "gn:timezone":"America/Santiago",
    "iso:country":"CL",
    "name:spa_x_preferred":[
        "Agua"
    ],
    "wof:name":"Agua",
    "wof:placetype":"locality"
},
  "geometry": {"coordinates":[-70.81849,-27.07607],"type":"Point"}
}