{
  "type": "Feature",
  "properties": {
    "gn:admin1_code":"11.0",
    "gn:admin2_code":"71.0",
    "gn:admin3_code":"7102.0",
    "gn:asciiname":"La Palmilla",
    "gn:cc2":"CL",
    "gn:country_code":"CL",
    "gn:dem":120,
    "gn:feature_class":"P",
    "gn:feature_code":"PPL",
    "gn:name":"La Palmilla",
    "gn:population":0,
    "gn:timezone":"America/Santiago",
    "iso:country":"CL",
    "name:und_x_variant":[
        "Palmilla",
        "La Palmilla"
    ],
    "name:urd_x_preferred":[
        "\u0644\u0627 \u067e\u0627\u0644\u0645\u06cc\u0644\u0627"
    ],
    "wof:name":"La Palmilla",
    "wof:placetype":"locality"
},
  "geometry": {"coordinates":[-72.23333000000002,-35.16667],"type":"Point"}
}