{
  "type": "Feature",
  "properties": {
    "iso:country":"CL",
    "qs:name":"Loanco",
    "qs:name_adm0":"Chile",
    "qs:name_adm1":"Maule",
    "qs:photos":58,
    "qs:photos_1k":12,
    "qs:photos_9k":1,
    "qs:photos_9r":2,
    "qs:photos_all":58,
    "qs:photos_sr":2,
    "qs:placetype":"Town",
    "qs:pop_sr":"0",
    "wof:name":"Loanco",
    "wof:placetype":"locality"
},
  "geometry": {"coordinates":[-72.619457,-35.573146],"type":"Point"}
}