{
  "type": "Feature",
  "properties": {
    "gn:admin1_code":"15.0",
    "gn:admin2_code":"14.0",
    "gn:admin3_code":"1403.0",
    "gn:asciiname":"Chapi",
    "gn:country_code":"CL",
    "gn:dem":3685,
    "gn:feature_class":"P",
    "gn:feature_code":"PPL",
    "gn:name":"Chapi",
    "gn:population":0,
    "gn:timezone":"America/Santiago",
    "iso:country":"CL",
    "wof:name":"Chapi",
    "wof:placetype":"locality"
},
  "geometry": {"coordinates":[-68.51666999999999,-19.41667],"type":"Point"}
}