{
  "type": "Feature",
  "properties": {
    "gn:admin1_code":"12.0",
    "gn:admin2_code":"136.0",
    "gn:admin3_code":"13605.0",
    "gn:asciiname":"Alicia de Penaflor",
    "gn:country_code":"CL",
    "gn:dem":379,
    "gn:feature_class":"P",
    "gn:feature_code":"PPL",
    "gn:name":"Alicia de Pe\u00f1aflor",
    "gn:population":0,
    "gn:timezone":"America/Santiago",
    "iso:country":"CL",
    "name:und_x_variant":[
        "Alicia de Pe\u00f1aflor"
    ],
    "wof:name":"Alicia de Penaflor",
    "wof:placetype":"locality"
},
  "geometry": {"coordinates":[-70.90000000000001,-33.61667],"type":"Point"}
}