{
  "type": "Feature",
  "properties": {
    "gn:admin1_code":"6.0",
    "gn:admin2_code":"82.0",
    "gn:admin3_code":"8203.0",
    "gn:asciiname":"Hosteria Lanalhue",
    "gn:country_code":"CL",
    "gn:dem":22,
    "gn:feature_class":"P",
    "gn:feature_code":"PPL",
    "gn:name":"Hoster\u00eda Lanalhue",
    "gn:population":0,
    "gn:timezone":"America/Santiago",
    "iso:country":"CL",
    "name:und_x_variant":[
        "Hostoria",
        "Hosteria",
        "Hoster\u00eda Lanalhue"
    ],
    "wof:name":"Hosteria Lanalhue",
    "wof:placetype":"locality"
},
  "geometry": {"coordinates":[-73.32484000000002,-37.93648],"type":"Point"}
}