{
  "type": "Feature",
  "properties": {
    "gn:admin1_code":"2.0",
    "gn:admin2_code":"111.0",
    "gn:admin3_code":"11101.0",
    "gn:asciiname":"Villa Ortega",
    "gn:country_code":"CL",
    "gn:dem":672,
    "gn:feature_class":"P",
    "gn:feature_code":"PPL",
    "gn:name":"Villa Ortega",
    "gn:population":0,
    "gn:timezone":"America/Santiago",
    "iso:country":"CL",
    "wof:name":"Villa Ortega",
    "wof:placetype":"locality"
},
  "geometry": {"coordinates":[-71.99942,-45.40002],"type":"Point"}
}