{
  "type": "Feature",
  "properties": {
    "gn:admin1_code":"14.0",
    "gn:admin2_code":"101.0",
    "gn:asciiname":"La Cochilla",
    "gn:country_code":"CL",
    "gn:dem":13,
    "gn:feature_class":"P",
    "gn:feature_code":"PPLL",
    "gn:name":"La Cochilla",
    "gn:population":0,
    "gn:timezone":"America/Santiago",
    "iso:country":"CL",
    "name:spa_x_preferred":[
        "La Cochilla"
    ],
    "wof:name":"La Cochilla",
    "wof:placetype":"locality"
},
  "geometry": {"coordinates":[-73.1031,-41.76325],"type":"Point"}
}