{
  "type": "Feature",
  "properties": {
    "gn:admin1_code":"16.0",
    "gn:admin2_code":"152.0",
    "gn:admin3_code":"15201.0",
    "gn:asciiname":"Culiculini",
    "gn:country_code":"CL",
    "gn:dem":4492,
    "gn:feature_class":"P",
    "gn:feature_code":"PPL",
    "gn:name":"Culiculini",
    "gn:population":0,
    "gn:timezone":"America/Santiago",
    "iso:country":"CL",
    "name:spa_x_preferred":[
        "Culiculini"
    ],
    "wof:name":"Culiculini",
    "wof:placetype":"locality"
},
  "geometry": {"coordinates":[-69.18212,-18.05852],"type":"Point"}
}