{
  "type": "Feature",
  "properties": {
    "gn:admin1_code":"12.0",
    "gn:admin2_code":"131.0",
    "gn:admin3_code":"13115.0",
    "gn:asciiname":"Paso Marchant",
    "gn:country_code":"CL",
    "gn:dem":2181,
    "gn:feature_class":"P",
    "gn:feature_code":"PPL",
    "gn:name":"Paso Marchant",
    "gn:population":0,
    "gn:timezone":"America/Santiago",
    "iso:country":"CL",
    "wof:name":"Paso Marchant",
    "wof:placetype":"locality"
},
  "geometry": {"coordinates":[-70.34504,-33.25221],"type":"Point"}
}