{
  "type": "Feature",
  "properties": {
    "gn:admin1_code":"11.0",
    "gn:admin2_code":"73.0",
    "gn:admin3_code":"7309.0",
    "gn:asciiname":"Las Apancoras",
    "gn:country_code":"CL",
    "gn:dem":98,
    "gn:feature_class":"P",
    "gn:feature_code":"PPL",
    "gn:name":"Las Apancoras",
    "gn:population":0,
    "gn:timezone":"America/Santiago",
    "iso:country":"CL",
    "name:und_x_variant":[
        "Las Pancoras",
        "Pancoras",
        "Las Apancoras"
    ],
    "wof:name":"Las Apancoras",
    "wof:placetype":"locality"
},
  "geometry": {"coordinates":[-72.02739,-34.73575],"type":"Point"}
}