{
  "type": "Feature",
  "properties": {
    "gn:admin1_code":"5.0",
    "gn:admin2_code":"31.0",
    "gn:asciiname":"Calderilla",
    "gn:country_code":"CL",
    "gn:dem":11,
    "gn:feature_class":"P",
    "gn:feature_code":"PPL",
    "gn:name":"Calderilla",
    "gn:population":0,
    "gn:timezone":"America/Santiago",
    "iso:country":"CL",
    "name:spa_x_preferred":[
        "Calderilla"
    ],
    "wof:name":"Calderilla",
    "wof:placetype":"locality"
},
  "geometry": {"coordinates":[-70.85694000000002,-27.08886],"type":"Point"}
}