{
  "type": "Feature",
  "properties": {
    "gn:country":"CL",
    "gn:fcode":"ADM3",
    "gn:pop":0,
    "iso:country":"CL",
    "qs:name":"Tal-Tal",
    "qs:photos_9r":0,
    "qs:photos_sr":0,
    "qs:pop_sr":"0",
    "wof:name":"Tal-Tal",
    "wof:placetype":"localadmin",
    "wof:population":0
},
  "geometry": {"coordinates":[-69.86568,-25.31359],"type":"Point"}
}