{
  "type": "Feature",
  "properties": {
    "gn:admin1_code":"16.0",
    "gn:admin2_code":"152.0",
    "gn:admin3_code":"15202.0",
    "gn:asciiname":"Sarayuma",
    "gn:country_code":"CL",
    "gn:dem":4041,
    "gn:feature_class":"P",
    "gn:feature_code":"PPL",
    "gn:name":"Sarayuma",
    "gn:population":0,
    "gn:timezone":"America/Santiago",
    "iso:country":"CL",
    "name:spa_x_preferred":[
        "Sarayuma"
    ],
    "wof:name":"Sarayuma",
    "wof:placetype":"locality"
},
  "geometry": {"coordinates":[-69.69369,-17.82446000000001],"type":"Point"}
}