{
  "type": "Feature",
  "properties": {
    "gn:admin1_code":"5.0",
    "gn:admin2_code":"33.0",
    "gn:admin3_code":"3303.0",
    "gn:asciiname":"Labrar",
    "gn:country_code":"CL",
    "gn:dem":637,
    "gn:feature_class":"P",
    "gn:feature_code":"PPL",
    "gn:name":"Labrar",
    "gn:population":0,
    "gn:timezone":"America/Santiago",
    "iso:country":"CL",
    "wof:name":"Labrar",
    "wof:placetype":"locality"
},
  "geometry": {"coordinates":[-71.18288000000003,-28.826],"type":"Point"}
}