{
  "type": "Feature",
  "properties": {
    "gn:admin1_code":"14.0",
    "gn:admin2_code":"104.0",
    "gn:admin3_code":"10404.0",
    "gn:asciiname":"El Aceite",
    "gn:country_code":"CL",
    "gn:dem":332,
    "gn:feature_class":"P",
    "gn:feature_code":"PPL",
    "gn:name":"El Aceite",
    "gn:population":0,
    "gn:timezone":"America/Santiago",
    "iso:country":"CL",
    "wof:name":"El Aceite",
    "wof:placetype":"locality"
},
  "geometry": {"coordinates":[-71.79154,-43.58369],"type":"Point"}
}