{
  "type": "Feature",
  "properties": {
    "gn:admin1_code":"15.0",
    "gn:admin2_code":"14.0",
    "gn:asciiname":"Tillujaya",
    "gn:country_code":"CL",
    "gn:dem":3994,
    "gn:feature_class":"P",
    "gn:feature_code":"PPL",
    "gn:name":"Tillujaya",
    "gn:population":0,
    "gn:timezone":"America/Santiago",
    "iso:country":"CL",
    "wof:name":"Tillujaya",
    "wof:placetype":"locality"
},
  "geometry": {"coordinates":[-68.5705,-19.61716],"type":"Point"}
}