{
  "type": "Feature",
  "properties": {
    "gn:admin1_code":"2.0",
    "gn:admin2_code":"113.0",
    "gn:asciiname":"Pampa Grande",
    "gn:country_code":"CL",
    "gn:dem":359,
    "gn:feature_class":"P",
    "gn:feature_code":"PPL",
    "gn:name":"Pampa Grande",
    "gn:population":0,
    "gn:timezone":"America/Santiago",
    "iso:country":"CL",
    "name:spa_x_preferred":[
        "Pampa Grande"
    ],
    "wof:name":"Pampa Grande",
    "wof:placetype":"locality"
},
  "geometry": {"coordinates":[-72.49262,-48.2961],"type":"Point"}
}