{
  "type": "Feature",
  "properties": {
    "gn:admin1_code":"15.0",
    "gn:admin2_code":"14.0",
    "gn:asciiname":"Estancia Pusuta",
    "gn:country_code":"CL",
    "gn:dem":3919,
    "gn:feature_class":"P",
    "gn:feature_code":"PPL",
    "gn:name":"Estancia Pusuta",
    "gn:population":0,
    "gn:timezone":"America/Santiago",
    "iso:country":"CL",
    "name:spa_x_preferred":[
        "Estancia Pusuta"
    ],
    "wof:name":"Estancia Pusuta",
    "wof:placetype":"locality"
},
  "geometry": {"coordinates":[-68.50981999999999,-19.53072],"type":"Point"}
}