{
  "type": "Feature",
  "properties": {
    "gn:admin1_code":"16.0",
    "gn:admin2_code":"151.0",
    "gn:asciiname":"Jaroma",
    "gn:country_code":"CL",
    "gn:dem":3581,
    "gn:feature_class":"P",
    "gn:feature_code":"PPL",
    "gn:name":"Jaroma",
    "gn:population":0,
    "gn:timezone":"America/Santiago",
    "iso:country":"CL",
    "name:spa_x_preferred":[
        "Jaroma"
    ],
    "wof:name":"Jaroma",
    "wof:placetype":"locality"
},
  "geometry": {"coordinates":[-69.30898000000001,-18.94853],"type":"Point"}
}