{
  "type": "Feature",
  "properties": {
    "gn:admin1_code":"5.0",
    "gn:admin2_code":"32.0",
    "gn:admin3_code":"3202.0",
    "gn:asciiname":"La Abundancia",
    "gn:country_code":"CL",
    "gn:dem":2036,
    "gn:feature_class":"P",
    "gn:feature_code":"PPL",
    "gn:name":"La Abundancia",
    "gn:population":0,
    "gn:timezone":"America/Santiago",
    "iso:country":"CL",
    "wof:name":"La Abundancia",
    "wof:placetype":"locality"
},
  "geometry": {"coordinates":[-69.73333000000001,-26.55],"type":"Point"}
}