{
  "type": "Feature",
  "properties": {
    "gn:admin1_code":"4.0",
    "gn:admin2_code":"91.0",
    "gn:admin3_code":"9104.0",
    "gn:asciiname":"Puhala",
    "gn:country_code":"CL",
    "gn:dem":404,
    "gn:feature_class":"P",
    "gn:feature_code":"PPL",
    "gn:name":"Puhala",
    "gn:population":0,
    "gn:timezone":"America/Santiago",
    "iso:country":"CL",
    "wof:name":"Puhala",
    "wof:placetype":"locality"
},
  "geometry": {"coordinates":[-71.55445999999998,-39.39879000000001],"type":"Point"}
}