{
  "type": "Feature",
  "properties": {
    "gn:admin1_code":"6.0",
    "gn:admin2_code":"81.0",
    "gn:admin3_code":"8111.0",
    "gn:asciiname":"Pissis",
    "gn:country_code":"CL",
    "gn:dem":189,
    "gn:feature_class":"P",
    "gn:feature_code":"PPL",
    "gn:name":"Pissis",
    "gn:population":0,
    "gn:timezone":"America/Santiago",
    "iso:country":"CL",
    "wof:name":"Pissis",
    "wof:placetype":"locality"
},
  "geometry": {"coordinates":[-72.80458,-36.61457],"type":"Point"}
}