{
  "type": "Feature",
  "properties": {
    "gn:admin1_code":"7.0",
    "gn:admin2_code":"43.0",
    "gn:admin3_code":"4303.0",
    "gn:asciiname":"Zemita",
    "gn:country_code":"CL",
    "gn:dem":692,
    "gn:feature_class":"P",
    "gn:feature_code":"PPL",
    "gn:name":"Zemita",
    "gn:population":0,
    "gn:timezone":"America/Santiago",
    "iso:country":"CL",
    "wof:name":"Zemita",
    "wof:placetype":"locality"
},
  "geometry": {"coordinates":[-70.79413000000002,-30.81758],"type":"Point"}
}