{
  "type": "Feature",
  "properties": {
    "iso:country":"CL",
    "qs:name":"Cartagena",
    "qs:name_adm0":"Chile",
    "qs:name_adm1":"Valpara\u00edso",
    "qs:photos":9,
    "qs:photos_1k":2,
    "qs:photos_9k":2,
    "qs:photos_9r":5,
    "qs:photos_all":422,
    "qs:photos_sr":1,
    "qs:placetype":"LocalAdmin",
    "qs:pop_sr":"0",
    "wd:wordcount":511,
    "wof:name":"Cartagena",
    "wof:placetype":"localadmin"
},
  "geometry": {"coordinates":[-71.600646,-33.542682],"type":"Point"}
}