{
  "type": "Feature",
  "properties": {
    "iso:country":"CL",
    "name:ara_x_preferred":[
        "\u0642\u0631\u0637\u0627\u062c\u0646\u0629"
    ],
    "name:bre_x_preferred":[
        "Cartagena"
    ],
    "name:bul_x_preferred":[
        "\u041a\u0430\u0440\u0442\u0430\u0445\u0435\u043d\u0430"
    ],
    "name:cat_x_preferred":[
        "Cartagena"
    ],
    "name:ceb_x_preferred":[
        "Cartagena"
    ],
    "name:ces_x_preferred":[
        "Cartagena"
    ],
    "name:cym_x_preferred":[
        "Cartagena"
    ],
    "name:dan_x_preferred":[
        "Cartagena"
    ],
    "name:deu_x_preferred":[
        "Cartagena"
    ],
    "name:ell_x_preferred":[
        "\u039a\u03b1\u03c1\u03c4\u03b1\u03c7\u03ad\u03bd\u03b1"
    ],
    "name:epo_x_preferred":[
        "Kartageno"
    ],
    "name:est_x_preferred":[
        "Cartagena"
    ],
    "name:fas_x_preferred":[
        "\u06a9\u0627\u0631\u062a\u0627\u06af\u0646\u0627"
    ],
    "name:fin_x_preferred":[
        "Cartagena"
    ],
    "name:fra_x_preferred":[
        "Carthag\u00e8ne"
    ],
    "name:glg_x_preferred":[
        "Cartagena"
    ],
    "name:heb_x_preferred":[
        "\u05e7\u05e8\u05d8\u05d7\u05e0\u05d4"
    ],
    "name:hun_x_preferred":[
        "Cartagena"
    ],
    "name:ido_x_preferred":[
        "Cartagena"
    ],
    "name:ind_x_preferred":[
        "Cartagena"
    ],
    "name:ita_x_preferred":[
        "Cartagena"
    ],
    "name:jpn_x_preferred":[
        "\u30ab\u30eb\u30bf\u30d8\u30ca"
    ],
    "name:kor_x_preferred":[
        "\uce74\ub974\ud0c0\ud5e4\ub098"
    ],
    "name:lit_x_preferred":[
        "Kartachena"
    ],
    "name:mlg_x_preferred":[
        "Cartagena"
    ],
    "name:msa_x_preferred":[
        "Cartagena"
    ],
    "name:nld_x_preferred":[
        "Cartagena"
    ],
    "name:nor_x_preferred":[
        "Cartagena"
    ],
    "name:oci_x_preferred":[
        "Cartagena"
    ],
    "name:pol_x_preferred":[
        "Cartagena"
    ],
    "name:por_x_preferred":[
        "Cartagena"
    ],
    "name:que_x_preferred":[
        "Cartagena"
    ],
    "name:ron_x_preferred":[
        "Cartagena"
    ],
    "name:rus_x_preferred":[
        "\u041a\u0430\u0440\u0442\u0430\u0445\u0435\u043d\u0430"
    ],
    "name:sco_x_preferred":[
        "Cartagena"
    ],
    "name:slk_x_preferred":[
        "Cartagena"
    ],
    "name:spa_x_preferred":[
        "Cartagena"
    ],
    "name:srp_x_preferred":[
        "\u041a\u0430\u0440\u0442\u0430\u0445\u0435\u043d\u0430"
    ],
    "name:swe_x_preferred":[
        "Cartagena"
    ],
    "name:tur_x_preferred":[
        "Cartagena"
    ],
    "name:ukr_x_preferred":[
        "\u041a\u0430\u0440\u0442\u0430\u0445\u0435\u043d\u0430"
    ],
    "name:vie_x_preferred":[
        "Cartagena"
    ],
    "name:war_x_preferred":[
        "Cartagena"
    ],
    "name:zho_x_preferred":[
        "\u5361\u5854\u8d6b\u7eb3"
    ],
    "qs:name":"Cartagena",
    "qs:name_adm0":"Chile",
    "qs:name_adm1":"Valpara\u00edso",
    "qs:photos":9,
    "qs:photos_1k":2,
    "qs:photos_9k":2,
    "qs:photos_9r":5,
    "qs:photos_all":422,
    "qs:photos_sr":1,
    "qs:placetype":"LocalAdmin",
    "qs:pop_sr":"0",
    "wd:wordcount":511,
    "wof:name":"Cartagena",
    "wof:placetype":"localadmin"
},
  "geometry": {"coordinates":[-71.600646,-33.542682],"type":"Point"}
}