{
  "type": "Feature",
  "properties": {
    "gn:admin1_code":"5.0",
    "gn:admin2_code":"31.0",
    "gn:admin3_code":"3103.0",
    "gn:asciiname":"Molino",
    "gn:country_code":"CL",
    "gn:dem":1265,
    "gn:feature_class":"P",
    "gn:feature_code":"PPL",
    "gn:name":"Molino",
    "gn:population":0,
    "gn:timezone":"America/Santiago",
    "iso:country":"CL",
    "name:ceb_x_preferred":[
        "Molino"
    ],
    "name:deu_x_preferred":[
        "Molino"
    ],
    "name:epo_x_preferred":[
        "Molino"
    ],
    "name:fra_x_preferred":[
        "Molino"
    ],
    "name:ita_x_preferred":[
        "Molino"
    ],
    "name:por_x_preferred":[
        "Molino"
    ],
    "name:spa_x_preferred":[
        "Molino"
    ],
    "name:srp_x_preferred":[
        "Molino"
    ],
    "name:swe_x_preferred":[
        "Molino"
    ],
    "name:tgl_x_preferred":[
        "Molino"
    ],
    "wof:name":"Molino",
    "wof:placetype":"locality"
},
  "geometry": {"coordinates":[-69.93883000000001,-28.04072],"type":"Point"}
}