{
  "type": "Feature",
  "properties": {
    "iso:country":"CL",
    "qs:name":"Chanco",
    "qs:name_adm0":"Chile",
    "qs:name_adm1":"Maule",
    "qs:photos":1,
    "qs:photos_1k":1,
    "qs:photos_9k":1,
    "qs:photos_9r":4,
    "qs:photos_all":209,
    "qs:photos_sr":1,
    "qs:placetype":"LocalAdmin",
    "qs:pop_sr":"0",
    "wd:wordcount":987,
    "wof:name":"Chanco",
    "wof:placetype":"localadmin"
},
  "geometry": {"coordinates":[-72.533327,-35.734138],"type":"Point"}
}