{
  "type": "Feature",
  "properties": {
    "gn:admin1_code":"1.0",
    "gn:admin2_code":"57.0",
    "gn:admin3_code":"5702.0",
    "gn:asciiname":"El Cobre",
    "gn:country_code":"CL",
    "gn:dem":468,
    "gn:feature_class":"P",
    "gn:feature_code":"PPL",
    "gn:name":"El Cobre",
    "gn:population":0,
    "gn:timezone":"America/Santiago",
    "iso:country":"CL",
    "name:bre_x_preferred":[
        "El Cobre"
    ],
    "name:ceb_x_preferred":[
        "El Cobre"
    ],
    "name:deu_x_preferred":[
        "El Cobre"
    ],
    "name:swe_x_preferred":[
        "El Cobre"
    ],
    "wof:name":"El Cobre",
    "wof:placetype":"locality"
},
  "geometry": {"coordinates":[-70.96814000000001,-32.75527],"type":"Point"}
}