{
  "type": "Feature",
  "properties": {
    "iso:country":"CL",
    "name:deu_x_preferred":[
        "San Felipe"
    ],
    "name:fas_x_preferred":[
        "\u0633\u0627\u0646 \u0641\u06cc\u0644\u06cc\u067e\u0647"
    ],
    "name:heb_x_preferred":[
        "\u05e1\u05df \u05e4\u05dc\u05d9\u05e4\u05d4"
    ],
    "name:hun_x_preferred":[
        "San Felipe"
    ],
    "qs:name":"San Felipe",
    "qs:name_adm0":"Chile",
    "qs:name_adm1":"Valpara\u00edso",
    "qs:photos":226,
    "qs:photos_1k":46,
    "qs:photos_9k":4,
    "qs:photos_9r":6,
    "qs:photos_all":881,
    "qs:photos_sr":4,
    "qs:placetype":"LocalAdmin",
    "qs:pop_sr":"0",
    "wof:name":"San Felipe",
    "wof:placetype":"localadmin"
},
  "geometry": {"coordinates":[-70.71968,-32.747796],"type":"Point"}
}