{
  "type": "Feature",
  "properties": {
    "iso:country":"CL",
    "qs:name":"San Felipe",
    "qs:name_adm0":"Chile",
    "qs:name_adm1":"Valpara\u00edso",
    "qs:photos":226,
    "qs:photos_1k":46,
    "qs:photos_9k":4,
    "qs:photos_9r":6,
    "qs:photos_all":881,
    "qs:photos_sr":4,
    "qs:placetype":"LocalAdmin",
    "qs:pop_sr":"0",
    "wof:name":"San Felipe",
    "wof:placetype":"localadmin"
},
  "geometry": {"coordinates":[-70.71968,-32.747796],"type":"Point"}
}