{
  "type": "Feature",
  "properties": {
    "gn:admin1_code":"11.0",
    "gn:admin2_code":"71.0",
    "gn:admin3_code":"7103.0",
    "gn:asciiname":"Loma Blanca",
    "gn:country_code":"CL",
    "gn:dem":192,
    "gn:feature_class":"P",
    "gn:feature_code":"PPL",
    "gn:name":"Loma Blanca",
    "gn:population":0,
    "gn:timezone":"America/Santiago",
    "iso:country":"CL",
    "wof:name":"Loma Blanca",
    "wof:placetype":"locality"
},
  "geometry": {"coordinates":[-72.09482,-35.1897],"type":"Point"}
}