{
  "type": "Feature",
  "properties": {
    "gn:admin1_code":"8.0",
    "gn:admin2_code":"61.0",
    "gn:admin3_code":"6107.0",
    "gn:asciiname":"Casas de Lata",
    "gn:country_code":"CL",
    "gn:dem":135,
    "gn:feature_class":"P",
    "gn:feature_code":"PPL",
    "gn:name":"Casas de Lata",
    "gn:population":0,
    "gn:timezone":"America/Santiago",
    "iso:country":"CL",
    "wof:name":"Casas de Lata",
    "wof:placetype":"locality"
},
  "geometry": {"coordinates":[-71.27476,-34.20696],"type":"Point"}
}