{
  "type": "Feature",
  "properties": {
    "gn:admin1_code":"5.0",
    "gn:admin2_code":"33.0",
    "gn:admin3_code":"3304.0",
    "gn:asciiname":"El Pino",
    "gn:country_code":"CL",
    "gn:dem":45,
    "gn:feature_class":"P",
    "gn:feature_code":"PPL",
    "gn:name":"El Pino",
    "gn:population":0,
    "gn:timezone":"America/Santiago",
    "iso:country":"CL",
    "name:ast_x_preferred":[
        "El Pino"
    ],
    "name:ceb_x_preferred":[
        "El Pino"
    ],
    "name:deu_x_preferred":[
        "El Pino"
    ],
    "name:glg_x_preferred":[
        "O Pino"
    ],
    "name:spa_x_preferred":[
        "El Pino"
    ],
    "name:srp_x_preferred":[
        "\u0415\u043b \u041f\u0438\u043d\u043e"
    ],
    "name:swe_x_preferred":[
        "El Pino"
    ],
    "wof:name":"El Pino",
    "wof:placetype":"locality"
},
  "geometry": {"coordinates":[-71.15089999999999,-28.48811],"type":"Point"}
}