{
  "type": "Feature",
  "properties": {
    "gn:admin1_code":"17.0",
    "gn:admin2_code":"141.0",
    "gn:admin3_code":"14101.0",
    "gn:asciiname":"El Bolson",
    "gn:country_code":"CL",
    "gn:dem":22,
    "gn:feature_class":"P",
    "gn:feature_code":"PPL",
    "gn:name":"El Bols\u00f3n",
    "gn:population":0,
    "gn:timezone":"America/Santiago",
    "iso:country":"CL",
    "name:und_x_variant":[
        "Bols\u00f3n",
        "El Bols\u00f3n"
    ],
    "wof:name":"El Bolson",
    "wof:placetype":"locality"
},
  "geometry": {"coordinates":[-73.23309999999999,-39.71483],"type":"Point"}
}