{
  "type": "Feature",
  "properties": {
    "gn:admin1_code":"14.0",
    "gn:admin2_code":"104.0",
    "gn:admin3_code":"10403.0",
    "gn:asciiname":"Poza Aulen",
    "gn:country_code":"CL",
    "gn:dem":16,
    "gn:feature_class":"P",
    "gn:feature_code":"PPL",
    "gn:name":"Poza Aul\u00e9n",
    "gn:population":0,
    "gn:timezone":"America/Santiago",
    "iso:country":"CL",
    "name:spa_x_preferred":[
        "Poza Aul\u00e9n"
    ],
    "wof:name":"Poza Aulen",
    "wof:placetype":"locality"
},
  "geometry": {"coordinates":[-72.81130999999998,-41.87933],"type":"Point"}
}