{
  "type": "Feature",
  "properties": {
    "gn:admin1_code":"15.0",
    "gn:admin2_code":"14.0",
    "gn:admin3_code":"1405.0",
    "gn:asciiname":"Collaguasi",
    "gn:country_code":"CL",
    "gn:dem":4735,
    "gn:feature_class":"P",
    "gn:feature_code":"PPL",
    "gn:name":"Collaguasi",
    "gn:population":0,
    "gn:timezone":"America/Santiago",
    "iso:country":"CL",
    "name:spa_x_preferred":[
        "Collaguasi"
    ],
    "wof:name":"Collaguasi",
    "wof:placetype":"locality"
},
  "geometry": {"coordinates":[-68.68571,-20.97538],"type":"Point"}
}