{
  "type": "Feature",
  "properties": {
    "gn:admin1_code":"1.0",
    "gn:admin2_code":"58.0",
    "gn:admin3_code":"5801.0",
    "gn:asciiname":"Los Peumos",
    "gn:country_code":"CL",
    "gn:dem":847,
    "gn:feature_class":"P",
    "gn:feature_code":"PPL",
    "gn:name":"Los Peumos",
    "gn:population":0,
    "gn:timezone":"America/Santiago",
    "iso:country":"CL",
    "wof:name":"Los Peumos",
    "wof:placetype":"locality"
},
  "geometry": {"coordinates":[-71.23333000000002,-33.18333],"type":"Point"}
}