{
  "type": "Feature",
  "properties": {
    "gn:admin1_code":"7.0",
    "gn:admin2_code":"42.0",
    "gn:asciiname":"Placilla",
    "gn:country_code":"CL",
    "gn:dem":355,
    "gn:feature_class":"P",
    "gn:feature_code":"PPL",
    "gn:name":"Placilla",
    "gn:population":0,
    "gn:timezone":"America/Santiago",
    "iso:country":"CL",
    "name:bak_x_preferred":[
        "\u041f\u043b\u0430\u0441\u0438\u043b\u044c\u044f"
    ],
    "name:ceb_x_preferred":[
        "Placilla"
    ],
    "name:eus_x_preferred":[
        "Placilla"
    ],
    "name:fas_x_preferred":[
        "\u067e\u0644\u0627\u062b\u06cc\u0627"
    ],
    "name:fra_x_preferred":[
        "Placilla"
    ],
    "name:ita_x_preferred":[
        "Placilla"
    ],
    "name:kor_x_preferred":[
        "\ud50c\ub77c\uc2dc\uc57c"
    ],
    "name:nld_x_preferred":[
        "Placilla"
    ],
    "name:por_x_preferred":[
        "Placilla"
    ],
    "name:ron_x_preferred":[
        "Placilla"
    ],
    "name:rus_x_preferred":[
        "\u041f\u043b\u0430\u0441\u0438\u043b\u044c\u044f"
    ],
    "name:sco_x_preferred":[
        "Placilla"
    ],
    "name:spa_x_preferred":[
        "Placilla"
    ],
    "name:swe_x_preferred":[
        "Placilla"
    ],
    "name:zho_x_preferred":[
        "\u666e\u62c9\u897f\u4e9e"
    ],
    "wof:name":"Placilla",
    "wof:placetype":"locality"
},
  "geometry": {"coordinates":[-71.37730999999999,-31.49716],"type":"Point"}
}