{
  "type": "Feature",
  "properties": {
    "gn:admin1_code":"7.0",
    "gn:admin2_code":"42.0",
    "gn:asciiname":"Placilla",
    "gn:country_code":"CL",
    "gn:dem":355,
    "gn:feature_class":"P",
    "gn:feature_code":"PPL",
    "gn:name":"Placilla",
    "gn:population":0,
    "gn:timezone":"America/Santiago",
    "iso:country":"CL",
    "name:spa_x_preferred":[
        "Placilla"
    ],
    "wof:name":"Placilla",
    "wof:placetype":"locality"
},
  "geometry": {"coordinates":[-71.37730999999999,-31.49716],"type":"Point"}
}