{
  "type": "Feature",
  "properties": {
    "gn:admin1_code":"12.0",
    "gn:admin2_code":"136.0",
    "gn:admin3_code":"13603.0",
    "gn:asciiname":"Villita Arriba",
    "gn:country_code":"CL",
    "gn:dem":359,
    "gn:feature_class":"P",
    "gn:feature_code":"PPL",
    "gn:name":"Villita Arriba",
    "gn:population":0,
    "gn:timezone":"America/Santiago",
    "iso:country":"CL",
    "wof:name":"Villita Arriba",
    "wof:placetype":"locality"
},
  "geometry": {"coordinates":[-70.87996,-33.76857],"type":"Point"}
}