{
  "type": "Feature",
  "properties": {
    "gn:admin1_code":"6.0",
    "gn:admin2_code":"82.0",
    "gn:admin3_code":"8207.0",
    "gn:asciiname":"Casa de Piedra",
    "gn:country_code":"CL",
    "gn:dem":542,
    "gn:feature_class":"P",
    "gn:feature_code":"PPL",
    "gn:name":"Casa de Piedra",
    "gn:population":0,
    "gn:timezone":"America/Santiago",
    "iso:country":"CL",
    "wof:name":"Casa de Piedra",
    "wof:placetype":"locality"
},
  "geometry": {"coordinates":[-73.46607,-38.47337],"type":"Point"}
}