{
  "type": "Feature",
  "properties": {
    "gn:admin1_code":"11.0",
    "gn:admin2_code":"73.0",
    "gn:asciiname":"La Pesca",
    "gn:country_code":"CL",
    "gn:dem":15,
    "gn:feature_class":"P",
    "gn:feature_code":"PPL",
    "gn:name":"La Pesca",
    "gn:population":0,
    "gn:timezone":"America/Santiago",
    "iso:country":"CL",
    "wof:name":"La Pesca",
    "wof:placetype":"locality"
},
  "geometry": {"coordinates":[-72.18425000000001,-34.96005],"type":"Point"}
}