{
  "type": "Feature",
  "properties": {
    "gn:admin1_code":"11.0",
    "gn:admin2_code":"74.0",
    "gn:admin3_code":"7406.0",
    "gn:asciiname":"Poeta Gonzalez Bastias",
    "gn:country_code":"CL",
    "gn:dem":53,
    "gn:feature_class":"P",
    "gn:feature_code":"PPL",
    "gn:name":"Poeta Gonz\u00e1lez Bastias",
    "gn:population":0,
    "gn:timezone":"America/Santiago",
    "iso:country":"CL",
    "wof:name":"Poeta Gonzalez Bastias",
    "wof:placetype":"locality"
},
  "geometry": {"coordinates":[-72.0273,-35.44168],"type":"Point"}
}