{
  "type": "Feature",
  "properties": {
    "gn:admin1_code":"1.0",
    "gn:admin2_code":"57.0",
    "gn:admin3_code":"5705.0",
    "gn:asciiname":"Resguardo de los Patos",
    "gn:country_code":"CL",
    "gn:dem":1198,
    "gn:feature_class":"P",
    "gn:feature_code":"PPL",
    "gn:name":"Resguardo de los Patos",
    "gn:population":0,
    "gn:timezone":"America/Santiago",
    "iso:country":"CL",
    "wof:name":"Resguardo de los Patos",
    "wof:placetype":"locality"
},
  "geometry": {"coordinates":[-70.58136,-32.50098],"type":"Point"}
}