{
  "type": "Feature",
  "properties": {
    "gn:admin1_code":"5.0",
    "gn:admin2_code":"33.0",
    "gn:asciiname":"Quebrada Pinte",
    "gn:country_code":"CL",
    "gn:dem":1448,
    "gn:feature_class":"P",
    "gn:feature_code":"PPL",
    "gn:name":"Quebrada Pinte",
    "gn:population":0,
    "gn:timezone":"America/Santiago",
    "iso:country":"CL",
    "name:spa_x_preferred":[
        "Quebrada Pinte"
    ],
    "wof:name":"Quebrada Pinte",
    "wof:placetype":"locality"
},
  "geometry": {"coordinates":[-70.28318,-28.97945],"type":"Point"}
}