{
  "type": "Feature",
  "properties": {
    "iso:country":"CL",
    "qs:name":"Puerto Octay",
    "qs:name_adm0":"Chile",
    "qs:name_adm1":"Los Lagos",
    "qs:photos":2,
    "qs:photos_1k":1,
    "qs:photos_9k":2,
    "qs:photos_9r":5,
    "qs:photos_all":376,
    "qs:photos_sr":1,
    "qs:placetype":"LocalAdmin",
    "qs:pop_sr":"0",
    "wd:wordcount":529,
    "wof:name":"Puerto Octay",
    "wof:placetype":"localadmin"
},
  "geometry": {"coordinates":[-72.883644,-40.978148],"type":"Point"}
}