{
  "type": "Feature",
  "properties": {
    "iso:country":"CL",
    "name:cat_x_preferred":[
        "Puerto Octay"
    ],
    "name:ceb_x_preferred":[
        "Puerto Octay"
    ],
    "name:deu_x_preferred":[
        "Puerto Octay"
    ],
    "name:eng_x_preferred":[
        "Puerto Octay"
    ],
    "name:eus_x_preferred":[
        "Puerto Octay"
    ],
    "name:fas_x_preferred":[
        "\u067e\u0648\u0631\u062a\u0648 \u0627\u06a9\u062a\u0627\u0626\u06cc"
    ],
    "name:fra_x_preferred":[
        "Puerto Octay"
    ],
    "name:ita_x_preferred":[
        "Puerto Octay"
    ],
    "name:jpn_x_preferred":[
        "\u30d7\u30a8\u30eb\u30c8\u30fb\u30aa\u30af\u30bf\u30a4"
    ],
    "name:kor_x_preferred":[
        "\ud478\uc5d0\ub974\ud1a0\uc625\ud14c\uc774"
    ],
    "name:nan_x_preferred":[
        "Puerto Octay"
    ],
    "name:nld_x_preferred":[
        "Puerto Octay"
    ],
    "name:oci_x_preferred":[
        "Puerto Octay"
    ],
    "name:por_x_preferred":[
        "Puerto Octay"
    ],
    "name:ron_x_preferred":[
        "Puerto Octay"
    ],
    "name:rus_x_preferred":[
        "\u041f\u0443\u044d\u0440\u0442\u043e-\u041e\u043a\u0442\u0430\u0439"
    ],
    "name:spa_x_preferred":[
        "Puerto Octay"
    ],
    "name:swe_x_preferred":[
        "Puerto Octay"
    ],
    "name:zho_x_preferred":[
        "\u5967\u514b\u6cf0\u6e2f"
    ],
    "qs:name":"Puerto Octay",
    "qs:name_adm0":"Chile",
    "qs:name_adm1":"Los Lagos",
    "qs:photos":2,
    "qs:photos_1k":1,
    "qs:photos_9k":2,
    "qs:photos_9r":5,
    "qs:photos_all":376,
    "qs:photos_sr":1,
    "qs:placetype":"LocalAdmin",
    "qs:pop_sr":"0",
    "wd:wordcount":529,
    "wof:name":"Puerto Octay",
    "wof:placetype":"localadmin"
},
  "geometry": {"coordinates":[-72.883644,-40.978148],"type":"Point"}
}