{
  "type": "Feature",
  "properties": {
    "gn:admin1_code":"10.0",
    "gn:admin2_code":"121.0",
    "gn:asciiname":"Lugar La Cabana",
    "gn:country_code":"CL",
    "gn:dem":19,
    "gn:feature_class":"P",
    "gn:feature_code":"PPL",
    "gn:name":"Lugar La Caba\u00f1a",
    "gn:population":0,
    "gn:timezone":"America/Punta_Arenas",
    "iso:country":"CL",
    "name:spa_x_preferred":[
        "Lugar La Caba\u00f1a"
    ],
    "wof:name":"Lugar La Cabana",
    "wof:placetype":"locality"
},
  "geometry": {"coordinates":[-71.31860999999998,-53.10307],"type":"Point"}
}