{
  "type": "Feature",
  "properties": {
    "gn:admin1_code":"6.0",
    "gn:admin2_code":"84.0",
    "gn:admin3_code":"8405.0",
    "gn:asciiname":"Coleal",
    "gn:country_code":"CL",
    "gn:dem":401,
    "gn:feature_class":"P",
    "gn:feature_code":"PPL",
    "gn:name":"Coleal",
    "gn:population":0,
    "gn:timezone":"America/Santiago",
    "iso:country":"CL",
    "wof:name":"Coleal",
    "wof:placetype":"locality"
},
  "geometry": {"coordinates":[-71.78354,-36.70146],"type":"Point"}
}