{
  "type": "Feature",
  "properties": {
    "gn:admin1_code":"12.0",
    "gn:admin2_code":"135.0",
    "gn:admin3_code":"13503.0",
    "gn:asciiname":"El Trebolar",
    "gn:cc2":"CL",
    "gn:country_code":"CL",
    "gn:dem":543,
    "gn:feature_class":"P",
    "gn:feature_code":"PPL",
    "gn:name":"El Trebolar",
    "gn:population":0,
    "gn:timezone":"America/Santiago",
    "iso:country":"CL",
    "name:und_x_variant":[
        "El Tr\u00e9bol",
        "El Trebolar"
    ],
    "wof:name":"El Trebolar",
    "wof:placetype":"locality"
},
  "geometry": {"coordinates":[-71.15000000000001,-33.25],"type":"Point"}
}