{
  "type": "Feature",
  "properties": {
    "gn:admin1_code":"11.0",
    "gn:admin2_code":"71.0",
    "gn:admin3_code":"7102.0",
    "gn:asciiname":"La Ovejeria",
    "gn:country_code":"CL",
    "gn:dem":188,
    "gn:feature_class":"P",
    "gn:feature_code":"PPL",
    "gn:name":"La Ovejer\u00eda",
    "gn:population":0,
    "gn:timezone":"America/Santiago",
    "iso:country":"CL",
    "name:und_x_variant":[
        "Ovejer\u00eda",
        "La Ovejer\u00eda"
    ],
    "wof:name":"La Ovejeria",
    "wof:placetype":"locality"
},
  "geometry": {"coordinates":[-72.30543,-35.30699],"type":"Point"}
}