{
  "type": "Feature",
  "properties": {
    "gn:admin1_code":"10.0",
    "gn:admin2_code":"122.0",
    "gn:admin3_code":"12201.0",
    "gn:asciiname":"Estancia Yendegai",
    "gn:country_code":"CL",
    "gn:dem":8,
    "gn:feature_class":"P",
    "gn:feature_code":"PPL",
    "gn:name":"Estancia Yendegai",
    "gn:population":0,
    "gn:timezone":"America/Punta_Arenas",
    "iso:country":"CL",
    "name:spa_x_preferred":[
        "Estancia Yendegai"
    ],
    "name:und_x_variant":[
        "Caleta Ferrari",
        "Estancia Yendegaia"
    ],
    "wof:name":"Estancia Yendegai",
    "wof:placetype":"locality"
},
  "geometry": {"coordinates":[-68.82203,-54.85728],"type":"Point"}
}