{
  "type": "Feature",
  "properties": {
    "gn:admin1_code":"8.0",
    "gn:admin2_code":"63.0",
    "gn:admin3_code":"6302.0",
    "gn:asciiname":"Los Callejones",
    "gn:country_code":"CL",
    "gn:dem":206,
    "gn:feature_class":"P",
    "gn:feature_code":"PPL",
    "gn:name":"Los Callejones",
    "gn:population":0,
    "gn:timezone":"America/Santiago",
    "iso:country":"CL",
    "name:und_x_variant":[
        "Callejones",
        "Los Callejones"
    ],
    "wof:name":"Los Callejones",
    "wof:placetype":"locality"
},
  "geometry": {"coordinates":[-71.41759999999999,-34.76517],"type":"Point"}
}