{
  "type": "Feature",
  "properties": {
    "gn:admin1_code":"7.0",
    "gn:admin2_code":"42.0",
    "gn:admin3_code":"4203.0",
    "gn:asciiname":"Casuto",
    "gn:country_code":"CL",
    "gn:dem":446,
    "gn:feature_class":"P",
    "gn:feature_code":"PPL",
    "gn:name":"Casuto",
    "gn:population":0,
    "gn:timezone":"America/Santiago",
    "iso:country":"CL",
    "wof:name":"Casuto",
    "wof:placetype":"locality"
},
  "geometry": {"coordinates":[-71.43125000000001,-31.82794],"type":"Point"}
}