{
  "type": "Feature",
  "properties": {
    "gn:admin1_code":"12.0",
    "gn:admin2_code":"135.0",
    "gn:admin3_code":"13501.0",
    "gn:asciiname":"Los Guindos",
    "gn:country_code":"CL",
    "gn:dem":131,
    "gn:feature_class":"P",
    "gn:feature_code":"PPL",
    "gn:name":"Los Guindos",
    "gn:population":0,
    "gn:timezone":"America/Santiago",
    "iso:country":"CL",
    "wof:name":"Los Guindos",
    "wof:placetype":"locality"
},
  "geometry": {"coordinates":[-71.23869000000001,-33.89012],"type":"Point"}
}