{
  "type": "Feature",
  "properties": {
    "gn:admin1_code":"15.0",
    "gn:admin2_code":"14.0",
    "gn:admin3_code":"1402.0",
    "gn:asciiname":"Yalamanta",
    "gn:country_code":"CL",
    "gn:dem":1837,
    "gn:feature_class":"P",
    "gn:feature_code":"PPL",
    "gn:name":"Yalamanta",
    "gn:population":0,
    "gn:timezone":"America/Santiago",
    "iso:country":"CL",
    "name:spa_x_preferred":[
        "Yalamanta"
    ],
    "wof:name":"Yalamanta",
    "wof:placetype":"locality"
},
  "geometry": {"coordinates":[-69.57991,-19.39062],"type":"Point"}
}