{
  "type": "Feature",
  "properties": {
    "gn:admin1_code":"15.0",
    "gn:admin2_code":"14.0",
    "gn:admin3_code":"1403.0",
    "gn:asciiname":"Pachixsa",
    "gn:country_code":"CL",
    "gn:dem":3910,
    "gn:feature_class":"P",
    "gn:feature_code":"PPL",
    "gn:name":"Pachixsa",
    "gn:population":0,
    "gn:timezone":"America/Santiago",
    "iso:country":"CL",
    "name:spa_x_preferred":[
        "Pachixsa"
    ],
    "wof:name":"Pachixsa",
    "wof:placetype":"locality"
},
  "geometry": {"coordinates":[-68.74413,-19.32477],"type":"Point"}
}