{
  "type": "Feature",
  "properties": {
    "gn:gn_country":"CL",
    "gn:gn_fcode":"PPLX",
    "gn:gn_pop":0,
    "iso:country":"CL",
    "name:afr_x_preferred":[
        "Quinta Normal"
    ],
    "name:cat_x_preferred":[
        "Quinta Normal"
    ],
    "name:ceb_x_preferred":[
        "Quinta Normal"
    ],
    "name:deu_x_preferred":[
        "Quinta Normal"
    ],
    "name:eng_x_preferred":[
        "Quinta Normal"
    ],
    "name:eus_x_preferred":[
        "Quinta Normal"
    ],
    "name:fas_x_preferred":[
        "\u06a9\u06cc\u0646\u062a\u0627 \u0646\u0631\u0645\u0627\u0644"
    ],
    "name:fra_x_preferred":[
        "Quinta Normal"
    ],
    "name:glg_x_preferred":[
        "Quinta Normal"
    ],
    "name:ita_x_preferred":[
        "Quinta Normal"
    ],
    "name:kor_x_preferred":[
        "\ud0a8\ud0c0\ub178\ub974\ub9d0"
    ],
    "name:nan_x_preferred":[
        "Quinta Normal"
    ],
    "name:nld_x_preferred":[
        "Quinta Normal"
    ],
    "name:oci_x_preferred":[
        "Quinta Normal"
    ],
    "name:por_x_preferred":[
        "Quinta Normal"
    ],
    "name:ron_x_preferred":[
        "Quinta Normal"
    ],
    "name:rus_x_preferred":[
        "\u041a\u0438\u043d\u0442\u0430-\u041d\u043e\u0440\u043c\u0430\u043b\u044c"
    ],
    "name:sco_x_preferred":[
        "Quinta Normal"
    ],
    "name:spa_x_preferred":[
        "Quinta Normal"
    ],
    "name:srp_x_preferred":[
        "\u041a\u0438\u043d\u0442\u0430 \u041d\u043e\u0440\u043c\u0430\u043b"
    ],
    "name:swe_x_preferred":[
        "Quinta Normal"
    ],
    "name:zho_x_preferred":[
        "\u91d1\u5854\u8afe\u99ac\u723e"
    ],
    "qs_pg:aaroncc":"CL",
    "qs_pg:gn_country":"CL",
    "qs_pg:gn_fcode":"PPLX",
    "qs_pg:gn_pop":0,
    "qs_pg:name":"Quinta Normal",
    "qs_pg:name_adm0":"Chile",
    "qs_pg:name_adm1":"Santiago",
    "qs_pg:photos":417,
    "qs_pg:photos_1k":84,
    "qs_pg:photos_9k":2,
    "qs_pg:photos_9r":5,
    "qs_pg:photos_all":417,
    "qs_pg:photos_sr":6,
    "qs_pg:pop_sr":0,
    "qs_pg:qs_pg_placetype":"locality_gp_neighbourhood_gn",
    "qs_pg:qs_pg_placetype_gp":"Town",
    "qs_pg:woe_adm0":23424782,
    "woe:adm0_id":23424782,
    "woe:name_adm0":"Chile",
    "woe:name_adm1":"Santiago",
    "woe:placetype":"Town",
    "wof:name":"Quinta Normal",
    "wof:placetype":"locality"
},
  "geometry": {"coordinates":[-70.67899,-33.44186],"type":"Point"}
}