{
  "type": "Feature",
  "properties": {
    "gn:admin1_code":"16.0",
    "gn:admin2_code":"151.0",
    "gn:admin3_code":"15102.0",
    "gn:asciiname":"Timar",
    "gn:country_code":"CL",
    "gn:dem":2372,
    "gn:feature_class":"P",
    "gn:feature_code":"PPL",
    "gn:name":"Timar",
    "gn:population":0,
    "gn:timezone":"America/Santiago",
    "iso:country":"CL",
    "name:spa_x_preferred":[
        "Timar"
    ],
    "wof:name":"Timar",
    "wof:placetype":"locality"
},
  "geometry": {"coordinates":[-69.69129000000001,-18.74961],"type":"Point"}
}