{
  "type": "Feature",
  "properties": {
    "gn:admin1_code":"15.0",
    "gn:admin2_code":"14.0",
    "gn:asciiname":"Luz",
    "gn:country_code":"CL",
    "gn:dem":31,
    "gn:feature_class":"P",
    "gn:feature_code":"PPL",
    "gn:name":"Luz",
    "gn:population":0,
    "gn:timezone":"America/Santiago",
    "iso:country":"CL",
    "name:por_x_preferred":[
        "Luz"
    ],
    "name:spa_x_preferred":[
        "Luz"
    ],
    "name:tam_x_preferred":[
        "\u0bb2\u0bc2\u0b9a\u0bc1"
    ],
    "wof:name":"Luz",
    "wof:placetype":"locality"
},
  "geometry": {"coordinates":[-70.23283000000001,-19.59943],"type":"Point"}
}