{
  "type": "Feature",
  "properties": {
    "gn:admin1_code":"14.0",
    "gn:admin2_code":"102.0",
    "gn:admin3_code":"10209.0",
    "gn:asciiname":"Colu",
    "gn:country_code":"CL",
    "gn:dem":27,
    "gn:feature_class":"P",
    "gn:feature_code":"PPL",
    "gn:name":"Col\u00fa",
    "gn:population":0,
    "gn:timezone":"America/Santiago",
    "iso:country":"CL",
    "name:deu_x_preferred":[
        "DC-Universum#Planeten"
    ],
    "name:ita_x_preferred":[
        "Colu"
    ],
    "name:spa_x_preferred":[
        "Colu"
    ],
    "wof:name":"Colu",
    "wof:placetype":"locality"
},
  "geometry": {"coordinates":[-73.39724,-42.25908],"type":"Point"}
}