{
  "type": "Feature",
  "properties": {
    "gn:admin1_code":"7.0",
    "gn:admin2_code":"43.0",
    "gn:admin3_code":"4302.0",
    "gn:asciiname":"Los Bolones",
    "gn:country_code":"CL",
    "gn:dem":979,
    "gn:feature_class":"P",
    "gn:feature_code":"PPL",
    "gn:name":"Los Bolones",
    "gn:population":0,
    "gn:timezone":"America/Santiago",
    "iso:country":"CL",
    "name:und_x_variant":[
        "Los Botones",
        "Los Bolones"
    ],
    "wof:name":"Los Bolones",
    "wof:placetype":"locality"
},
  "geometry": {"coordinates":[-71.01244,-31.2046],"type":"Point"}
}