{
  "type": "Feature",
  "properties": {
    "gn:admin1_code":"14.0",
    "gn:admin2_code":"101.0",
    "gn:admin3_code":"10102.0",
    "gn:asciiname":"Queullin",
    "gn:country_code":"CL",
    "gn:dem":28,
    "gn:feature_class":"P",
    "gn:feature_code":"PPL",
    "gn:name":"Queull\u00edn",
    "gn:population":0,
    "gn:timezone":"America/Santiago",
    "iso:country":"CL",
    "name:spa_x_preferred":[
        "Queull\u00edn"
    ],
    "wof:name":"Queullin",
    "wof:placetype":"locality"
},
  "geometry": {"coordinates":[-72.90196,-41.89026],"type":"Point"}
}