{
  "type": "Feature",
  "properties": {
    "gn:admin1_code":"7.0",
    "gn:admin2_code":"41.0",
    "gn:admin3_code":"4101.0",
    "gn:asciiname":"Almirante Latorre",
    "gn:country_code":"CL",
    "gn:dem":919,
    "gn:feature_class":"P",
    "gn:feature_code":"PPL",
    "gn:name":"Almirante Latorre",
    "gn:population":0,
    "gn:timezone":"America/Santiago",
    "iso:country":"CL",
    "wof:name":"Almirante Latorre",
    "wof:placetype":"locality"
},
  "geometry": {"coordinates":[-70.95546999999998,-29.63674],"type":"Point"}
}