{
  "type": "Feature",
  "properties": {
    "gn:admin1_code":"7.0",
    "gn:admin2_code":"41.0",
    "gn:admin3_code":"4102.0",
    "gn:asciiname":"Palo Negro",
    "gn:country_code":"CL",
    "gn:dem":136,
    "gn:feature_class":"P",
    "gn:feature_code":"PPL",
    "gn:name":"Palo Negro",
    "gn:population":0,
    "gn:timezone":"America/Santiago",
    "iso:country":"CL",
    "name:ceb_x_preferred":[
        "Palo Negro"
    ],
    "name:fra_x_preferred":[
        "Palo Negro"
    ],
    "name:swe_x_preferred":[
        "Palo Negro"
    ],
    "wof:name":"Palo Negro",
    "wof:placetype":"locality"
},
  "geometry": {"coordinates":[-71.24763,-30.10236],"type":"Point"}
}