{
  "type": "Feature",
  "properties": {
    "gn:admin1_code":"7.0",
    "gn:admin2_code":"41.0",
    "gn:admin3_code":"4101.0",
    "gn:asciiname":"Romeral",
    "gn:country_code":"CL",
    "gn:dem":260,
    "gn:feature_class":"P",
    "gn:feature_code":"PPL",
    "gn:name":"Romeral",
    "gn:population":0,
    "gn:timezone":"America/Santiago",
    "iso:country":"CL",
    "name:und_x_variant":[
        "El Romeral",
        "Romeral"
    ],
    "wof:name":"Romeral",
    "wof:placetype":"locality"
},
  "geometry": {"coordinates":[-71.21729999999999,-29.72145],"type":"Point"}
}