{
  "type": "Feature",
  "properties": {
    "gn:admin1_code":"7.0",
    "gn:admin2_code":"41.0",
    "gn:admin3_code":"4101.0",
    "gn:asciiname":"Romeral",
    "gn:country_code":"CL",
    "gn:dem":260,
    "gn:feature_class":"P",
    "gn:feature_code":"PPL",
    "gn:name":"Romeral",
    "gn:population":0,
    "gn:timezone":"America/Santiago",
    "iso:country":"CL",
    "name:ceb_x_preferred":[
        "Romeral"
    ],
    "name:eus_x_preferred":[
        "Romeral"
    ],
    "name:fas_x_preferred":[
        "\u0631\u0648\u0645\u0631\u0627\u0644"
    ],
    "name:fra_x_preferred":[
        "Romeral"
    ],
    "name:ita_x_preferred":[
        "Romeral"
    ],
    "name:kor_x_preferred":[
        "\ub85c\uba54\ub784"
    ],
    "name:nld_x_preferred":[
        "Romeral"
    ],
    "name:por_x_preferred":[
        "Romeral"
    ],
    "name:ron_x_preferred":[
        "Romeral"
    ],
    "name:rus_x_preferred":[
        "\u0420\u043e\u043c\u0435\u0440\u0430\u043b\u044c"
    ],
    "name:spa_x_preferred":[
        "Romeral"
    ],
    "name:und_x_variant":[
        "El Romeral",
        "Romeral"
    ],
    "name:zho_x_preferred":[
        "\u7f85\u6885\u62c9\u723e"
    ],
    "wof:name":"Romeral",
    "wof:placetype":"locality"
},
  "geometry": {"coordinates":[-71.21729999999999,-29.72145],"type":"Point"}
}