{
  "type": "Feature",
  "properties": {
    "gn:admin1_code":"10.0",
    "gn:admin2_code":"124.0",
    "gn:admin3_code":"12402.0",
    "gn:asciiname":"La Victorina",
    "gn:country_code":"CL",
    "gn:dem":171,
    "gn:feature_class":"P",
    "gn:feature_code":"PPL",
    "gn:name":"La Victorina",
    "gn:population":0,
    "gn:timezone":"America/Punta_Arenas",
    "iso:country":"CL",
    "name:spa_x_preferred":[
        "La Victorina"
    ],
    "wof:name":"La Victorina",
    "wof:placetype":"locality"
},
  "geometry": {"coordinates":[-72.91501,-50.83099],"type":"Point"}
}