{
  "type": "Feature",
  "properties": {
    "gn:admin1_code":"15.0",
    "gn:admin2_code":"14.0",
    "gn:admin3_code":"1403.0",
    "gn:asciiname":"Tacupa",
    "gn:country_code":"CL",
    "gn:dem":3773,
    "gn:feature_class":"P",
    "gn:feature_code":"PPL",
    "gn:name":"Tacupa",
    "gn:population":0,
    "gn:timezone":"America/Santiago",
    "iso:country":"CL",
    "wof:name":"Tacupa",
    "wof:placetype":"locality"
},
  "geometry": {"coordinates":[-68.64423000000001,-19.45005],"type":"Point"}
}