{
  "type": "Feature",
  "properties": {
    "gn:admin1_code":"5.0",
    "gn:admin2_code":"33.0",
    "gn:admin3_code":"3303.0",
    "gn:asciiname":"La Laja",
    "gn:country_code":"CL",
    "gn:dem":1204,
    "gn:feature_class":"P",
    "gn:feature_code":"PPL",
    "gn:name":"La Laja",
    "gn:population":0,
    "gn:timezone":"America/Santiago",
    "iso:country":"CL",
    "name:ita_x_preferred":[
        "La Laja"
    ],
    "name:spa_x_preferred":[
        "La Laja"
    ],
    "name:zho_x_preferred":[
        "\u62c9\u62c9\u54c8"
    ],
    "wof:name":"La Laja",
    "wof:placetype":"locality"
},
  "geometry": {"coordinates":[-71.05736999999998,-29.15618],"type":"Point"}
}