{
  "type": "Feature",
  "properties": {
    "iso:country":"CL",
    "name:bre_x_preferred":[
        "La Serena"
    ],
    "name:ceb_x_preferred":[
        "La Serena"
    ],
    "name:deu_x_preferred":[
        "La Serena"
    ],
    "name:epo_x_preferred":[
        "La Serena"
    ],
    "name:nld_x_preferred":[
        "La Serena"
    ],
    "name:por_x_preferred":[
        "Serena"
    ],
    "name:rus_x_preferred":[
        "\u041b\u0430-\u0421\u0435\u0440\u0435\u043d\u0430"
    ],
    "name:spa_x_preferred":[
        "La Serena"
    ],
    "name:vie_x_preferred":[
        "La Serena"
    ],
    "qs:name":"La Serena",
    "qs:name_adm0":"Chile",
    "qs:name_adm1":"Coquimbo",
    "qs:photos":1,
    "qs:photos_1k":1,
    "qs:photos_9k":23,
    "qs:photos_9r":14,
    "qs:photos_all":5250,
    "qs:photos_sr":1,
    "qs:placetype":"LocalAdmin",
    "qs:pop_sr":"0",
    "wd:wordcount":35,
    "wof:name":"La Serena",
    "wof:placetype":"localadmin"
},
  "geometry": {"coordinates":[-71.249167,-29.901972],"type":"Point"}
}