{
  "type": "Feature",
  "properties": {
    "iso:country":"CL",
    "qs:name":"La Serena",
    "qs:name_adm0":"Chile",
    "qs:name_adm1":"Coquimbo",
    "qs:photos":1,
    "qs:photos_1k":1,
    "qs:photos_9k":23,
    "qs:photos_9r":14,
    "qs:photos_all":5250,
    "qs:photos_sr":1,
    "qs:placetype":"LocalAdmin",
    "qs:pop_sr":"0",
    "wd:wordcount":35,
    "wof:name":"La Serena",
    "wof:placetype":"localadmin"
},
  "geometry": {"coordinates":[-71.249167,-29.901972],"type":"Point"}
}