{
  "type": "Feature",
  "properties": {
    "gn:admin1_code":"15.0",
    "gn:admin2_code":"14.0",
    "gn:admin3_code":"1404.0",
    "gn:asciiname":"Quipinta",
    "gn:country_code":"CL",
    "gn:dem":3124,
    "gn:feature_class":"P",
    "gn:feature_code":"PPL",
    "gn:name":"Quipinta",
    "gn:population":0,
    "gn:timezone":"America/Santiago",
    "iso:country":"CL",
    "wof:name":"Quipinta",
    "wof:placetype":"locality"
},
  "geometry": {"coordinates":[-69.51666999999999,-19.15],"type":"Point"}
}