{
  "type": "Feature",
  "properties": {
    "gn:admin1_code":"16.0",
    "gn:admin2_code":"152.0",
    "gn:admin3_code":"15202.0",
    "gn:asciiname":"Airo",
    "gn:country_code":"CL",
    "gn:dem":4229,
    "gn:feature_class":"P",
    "gn:feature_code":"PPL",
    "gn:name":"Airo",
    "gn:population":0,
    "gn:timezone":"America/Santiago",
    "iso:country":"CL",
    "name:slv_x_preferred":[
        "Airo"
    ],
    "name:spa_x_preferred":[
        "Airo"
    ],
    "wof:name":"Airo",
    "wof:placetype":"locality"
},
  "geometry": {"coordinates":[-69.68114,-17.70242],"type":"Point"}
}