{
  "type": "Feature",
  "properties": {
    "gn:admin1_code":"16.0",
    "gn:admin2_code":"151.0",
    "gn:asciiname":"Esquina",
    "gn:country_code":"CL",
    "gn:dem":2178,
    "gn:feature_class":"P",
    "gn:feature_code":"PPL",
    "gn:name":"Esqui\u00f1a",
    "gn:population":0,
    "gn:timezone":"America/Santiago",
    "iso:country":"CL",
    "name:ceb_x_preferred":[
        "Esquina"
    ],
    "name:deu_x_preferred":[
        "Esquina"
    ],
    "name:nld_x_preferred":[
        "Esquina"
    ],
    "name:por_x_preferred":[
        "Esquina"
    ],
    "name:slk_x_preferred":[
        "Esquina"
    ],
    "name:spa_x_preferred":[
        "Esqui\u00f1a"
    ],
    "name:spa_x_variant":[
        "Esquina"
    ],
    "name:swe_x_preferred":[
        "Esquina"
    ],
    "wof:name":"Esquina",
    "wof:placetype":"locality"
},
  "geometry": {"coordinates":[-69.53008,-18.93593],"type":"Point"}
}