{
  "type": "Feature",
  "properties": {
    "gn:admin1_code":"11.0",
    "gn:admin2_code":"73.0",
    "gn:admin3_code":"7304.0",
    "gn:asciiname":"Pichingal",
    "gn:country_code":"CL",
    "gn:dem":304,
    "gn:feature_class":"P",
    "gn:feature_code":"PPL",
    "gn:name":"Pichingal",
    "gn:population":0,
    "gn:timezone":"America/Santiago",
    "iso:country":"CL",
    "wof:name":"Pichingal",
    "wof:placetype":"locality"
},
  "geometry": {"coordinates":[-71.21338,-35.11712],"type":"Point"}
}