{
  "type": "Feature",
  "properties": {
    "gn:admin1_code":"14.0",
    "gn:admin2_code":"102.0",
    "gn:admin3_code":"10210.0",
    "gn:asciiname":"Lalin",
    "gn:country_code":"CL",
    "gn:dem":23,
    "gn:feature_class":"P",
    "gn:feature_code":"PPL",
    "gn:name":"Lal\u00edn",
    "gn:population":0,
    "gn:timezone":"America/Santiago",
    "iso:country":"CL",
    "name:ceb_x_preferred":[
        "Lalin"
    ],
    "name:fra_x_preferred":[
        "Lalin"
    ],
    "wof:name":"Lalin",
    "wof:placetype":"locality"
},
  "geometry": {"coordinates":[-73.33333,-42.43333],"type":"Point"}
}