{
  "type": "Feature",
  "properties": {
    "gn:admin1_code":"11.0",
    "gn:admin2_code":"71.0",
    "gn:admin3_code":"7102.0",
    "gn:asciiname":"Junquillar",
    "gn:country_code":"CL",
    "gn:dem":15,
    "gn:feature_class":"P",
    "gn:feature_code":"PPL",
    "gn:name":"Junquillar",
    "gn:population":0,
    "gn:timezone":"America/Santiago",
    "iso:country":"CL",
    "wof:name":"Junquillar",
    "wof:placetype":"locality"
},
  "geometry": {"coordinates":[-72.34777,-35.27327000000001],"type":"Point"}
}