{
  "type": "Feature",
  "properties": {
    "iso:country":"CL",
    "qs:name":"Huachipato",
    "qs:name_adm0":"Chile",
    "qs:name_adm1":"Biobio",
    "qs:photos":71,
    "qs:photos_1k":14,
    "qs:photos_9k":1,
    "qs:photos_9r":2,
    "qs:photos_all":71,
    "qs:photos_sr":2,
    "qs:placetype":"Town",
    "qs:pop_sr":"0",
    "wd:wordcount":732,
    "wof:name":"Huachipato",
    "wof:placetype":"locality"
},
  "geometry": {"coordinates":[-73.122253,-36.744518],"type":"Point"}
}