{
  "type": "Feature",
  "properties": {
    "iso:country":"CL",
    "name:ara_x_preferred":[
        "\u0647\u0648\u0627\u062a\u0634\u064a\u0628\u0627\u062a\u0648"
    ],
    "name:arn_x_preferred":[
        "Huachipato"
    ],
    "name:arz_x_preferred":[
        "\u0647\u0648\u0627\u062a\u0634\u064a\u0628\u0627\u062a\u0648"
    ],
    "name:bel_x_preferred":[
        "\u0423\u0430\u0447\u044b\u043f\u0430\u0442\u0430"
    ],
    "name:bul_x_preferred":[
        "\u0423\u0430\u0447\u0438\u043f\u0430\u0442\u043e"
    ],
    "name:deu_x_preferred":[
        "CD Huachipato"
    ],
    "name:nob_x_preferred":[
        "Huachipato"
    ],
    "name:pol_x_preferred":[
        "Huachipato Talcahuano"
    ],
    "name:rus_x_preferred":[
        "\u0423\u0430\u0447\u0438\u043f\u0430\u0442\u043e"
    ],
    "name:tur_x_preferred":[
        "CD Huachipato"
    ],
    "name:ukr_x_preferred":[
        "\u0423\u0430\u0447\u0438\u043f\u0430\u0442\u043e"
    ],
    "name:zho_x_preferred":[
        "\u74e6\u5947\u5df4\u6258\u4f53\u80b2\u4ff1\u4e50\u90e8"
    ],
    "qs:name":"Huachipato",
    "qs:name_adm0":"Chile",
    "qs:name_adm1":"Biobio",
    "qs:photos":71,
    "qs:photos_1k":14,
    "qs:photos_9k":1,
    "qs:photos_9r":2,
    "qs:photos_all":71,
    "qs:photos_sr":2,
    "qs:placetype":"Town",
    "qs:pop_sr":"0",
    "wd:wordcount":732,
    "wof:name":"Huachipato",
    "wof:placetype":"locality"
},
  "geometry": {"coordinates":[-73.122253,-36.744518],"type":"Point"}
}