{
  "type": "Feature",
  "properties": {
    "gn:admin1_code":"6.0",
    "gn:admin2_code":"83.0",
    "gn:admin3_code":"8310.0",
    "gn:asciiname":"Turquia",
    "gn:country_code":"CL",
    "gn:dem":73,
    "gn:feature_class":"P",
    "gn:feature_code":"PPL",
    "gn:name":"Turqu\u00eda",
    "gn:population":0,
    "gn:timezone":"America/Santiago",
    "iso:country":"CL",
    "wof:name":"Turquia",
    "wof:placetype":"locality"
},
  "geometry": {"coordinates":[-72.64024999999999,-37.21665],"type":"Point"}
}