{
  "type": "Feature",
  "properties": {
    "gn:admin1_code":"14.0",
    "gn:admin2_code":"101.0",
    "gn:asciiname":"Puerto del Yate",
    "gn:country_code":"CL",
    "gn:dem":32,
    "gn:feature_class":"P",
    "gn:feature_code":"PPL",
    "gn:name":"Puerto del Yate",
    "gn:population":0,
    "gn:timezone":"America/Santiago",
    "iso:country":"CL",
    "wof:name":"Puerto del Yate",
    "wof:placetype":"locality"
},
  "geometry": {"coordinates":[-72.40708000000002,-41.70286],"type":"Point"}
}