{
  "type": "Feature",
  "properties": {
    "gn:admin1_code":"16.0",
    "gn:admin2_code":"151.0",
    "gn:admin3_code":"15101.0",
    "gn:asciiname":"Guanta",
    "gn:country_code":"CL",
    "gn:dem":974,
    "gn:feature_class":"P",
    "gn:feature_code":"PPL",
    "gn:name":"Guanta",
    "gn:population":0,
    "gn:timezone":"America/Santiago",
    "iso:country":"CL",
    "name:ast_x_preferred":[
        "Guanta"
    ],
    "name:epo_x_preferred":[
        "Guanta"
    ],
    "name:fra_x_preferred":[
        "Guanta"
    ],
    "name:pol_x_preferred":[
        "Guanta"
    ],
    "name:por_x_preferred":[
        "Guanta"
    ],
    "name:rus_x_preferred":[
        "\u0413\u0443\u0430\u043d\u0442\u0430"
    ],
    "name:spa_x_preferred":[
        "Guanta"
    ],
    "wof:name":"Guanta",
    "wof:placetype":"locality"
},
  "geometry": {"coordinates":[-70.01463000000001,-18.39203],"type":"Point"}
}