{
  "type": "Feature",
  "properties": {
    "gn:admin1_code":"5.0",
    "gn:admin2_code":"33.0",
    "gn:asciiname":"Los Cristales",
    "gn:country_code":"CL",
    "gn:dem":1380,
    "gn:feature_class":"P",
    "gn:feature_code":"PPL",
    "gn:name":"Los Cristales",
    "gn:population":0,
    "gn:timezone":"America/Santiago",
    "iso:country":"CL",
    "name:spa_x_preferred":[
        "Los Cristales"
    ],
    "wof:name":"Los Cristales",
    "wof:placetype":"locality"
},
  "geometry": {"coordinates":[-71.02892,-29.15225],"type":"Point"}
}