{
  "type": "Feature",
  "properties": {
    "gn:admin1_code":"6.0",
    "gn:admin2_code":"82.0",
    "gn:admin3_code":"8202.0",
    "gn:asciiname":"Rumena",
    "gn:country_code":"CL",
    "gn:dem":32,
    "gn:feature_class":"P",
    "gn:feature_code":"PPL",
    "gn:name":"Rumena",
    "gn:population":0,
    "gn:timezone":"America/Santiago",
    "iso:country":"CL",
    "wof:name":"Rumena",
    "wof:placetype":"locality"
},
  "geometry": {"coordinates":[-73.61336,-37.17988],"type":"Point"}
}