{
  "type": "Feature",
  "properties": {
    "gn:admin1_code":"11.0",
    "gn:admin2_code":"73.0",
    "gn:admin3_code":"7302.0",
    "gn:asciiname":"Mira Rios",
    "gn:country_code":"CL",
    "gn:dem":52,
    "gn:feature_class":"P",
    "gn:feature_code":"PPL",
    "gn:name":"Mira R\u00edos",
    "gn:population":0,
    "gn:timezone":"America/Santiago",
    "iso:country":"CL",
    "name:und_x_variant":[
        "Mira R\u00edo",
        "Mira R\u00edos"
    ],
    "wof:name":"Mira Rios",
    "wof:placetype":"locality"
},
  "geometry": {"coordinates":[-71.74316,-35.00565],"type":"Point"}
}