{
  "type": "Feature",
  "properties": {
    "gn:admin1_code":"1.0",
    "gn:admin2_code":"54.0",
    "gn:admin3_code":"5401.0",
    "gn:asciiname":"La Canela",
    "gn:country_code":"CL",
    "gn:dem":161,
    "gn:feature_class":"P",
    "gn:feature_code":"PPL",
    "gn:name":"La Canela",
    "gn:population":0,
    "gn:timezone":"America/Santiago",
    "iso:country":"CL",
    "wof:name":"La Canela",
    "wof:placetype":"locality"
},
  "geometry": {"coordinates":[-71.15848000000003,-32.36136],"type":"Point"}
}