{
  "type": "Feature",
  "properties": {
    "iso:country":"CL",
    "name:cat_x_preferred":[
        "Zapallar"
    ],
    "name:ceb_x_preferred":[
        "Zapallar"
    ],
    "name:deu_x_preferred":[
        "Zapallar"
    ],
    "name:eng_x_preferred":[
        "Zapallar"
    ],
    "name:eus_x_preferred":[
        "Zapallar"
    ],
    "name:fas_x_preferred":[
        "\u0632\u0627\u067e\u0627\u06cc\u0627\u0631"
    ],
    "name:fra_x_preferred":[
        "Zapallar"
    ],
    "name:ind_x_preferred":[
        "Zapallar"
    ],
    "name:ita_x_preferred":[
        "Zapallar"
    ],
    "name:jpn_x_preferred":[
        "\u30b5\u30d1\u30b8\u30e3\u30fc\u30eb"
    ],
    "name:kor_x_preferred":[
        "\uc0ac\ud30c\uc57c\ub974"
    ],
    "name:nan_x_preferred":[
        "Zapallar"
    ],
    "name:nld_x_preferred":[
        "Zapallar"
    ],
    "name:por_x_preferred":[
        "Zapallar"
    ],
    "name:ron_x_preferred":[
        "Zapallar"
    ],
    "name:rus_x_preferred":[
        "\u0421\u0430\u043f\u0430\u043b\u044c\u044f\u0440"
    ],
    "name:spa_x_preferred":[
        "Zapallar"
    ],
    "name:swe_x_preferred":[
        "Zapallar"
    ],
    "name:zho_x_preferred":[
        "\u85a9\u5e15\u5229\u4e9e\u723e"
    ],
    "qs:name":"Zapallar",
    "qs:name_adm0":"Chile",
    "qs:name_adm1":"Valpara\u00edso",
    "qs:photos":205,
    "qs:photos_1k":42,
    "qs:photos_9k":6,
    "qs:photos_9r":7,
    "qs:photos_all":1288,
    "qs:photos_sr":4,
    "qs:placetype":"LocalAdmin",
    "qs:pop_sr":"0",
    "wd:wordcount":432,
    "wof:name":"Zapallar",
    "wof:placetype":"localadmin"
},
  "geometry": {"coordinates":[-71.460571,-32.554771],"type":"Point"}
}