{
  "type": "Feature",
  "properties": {
    "iso:country":"CL",
    "qs:name":"Zapallar",
    "qs:name_adm0":"Chile",
    "qs:name_adm1":"Valpara\u00edso",
    "qs:photos":205,
    "qs:photos_1k":42,
    "qs:photos_9k":6,
    "qs:photos_9r":7,
    "qs:photos_all":1288,
    "qs:photos_sr":4,
    "qs:placetype":"LocalAdmin",
    "qs:pop_sr":"0",
    "wd:wordcount":432,
    "wof:name":"Zapallar",
    "wof:placetype":"localadmin"
},
  "geometry": {"coordinates":[-71.460571,-32.554771],"type":"Point"}
}