{
  "type": "Feature",
  "properties": {
    "gn:admin1_code":"15.0",
    "gn:admin2_code":"14.0",
    "gn:admin3_code":"1404.0",
    "gn:asciiname":"Junin",
    "gn:cc2":"CL",
    "gn:country_code":"CL",
    "gn:dem":252,
    "gn:feature_class":"P",
    "gn:feature_code":"PPL",
    "gn:name":"Jun\u00edn",
    "gn:population":0,
    "gn:timezone":"America/Santiago",
    "iso:country":"CL",
    "name:und_x_variant":[
        "Caleta Jun\u00edn",
        "Jun\u00edn"
    ],
    "wof:name":"Junin",
    "wof:placetype":"locality"
},
  "geometry": {"coordinates":[-70.16667,-19.66667],"type":"Point"}
}