{
  "type": "Feature",
  "properties": {
    "gn:admin1_code":"15.0",
    "gn:admin2_code":"14.0",
    "gn:admin3_code":"1401.0",
    "gn:asciiname":"Macaya",
    "gn:country_code":"CL",
    "gn:dem":2718,
    "gn:feature_class":"P",
    "gn:feature_code":"PPL",
    "gn:name":"Macaya",
    "gn:population":0,
    "gn:timezone":"America/Santiago",
    "iso:country":"CL",
    "name:spa_x_preferred":[
        "Macaya"
    ],
    "wof:name":"Macaya",
    "wof:placetype":"locality"
},
  "geometry": {"coordinates":[-69.18156999999999,-20.13391],"type":"Point"}
}