{
  "type": "Feature",
  "properties": {
    "gn:admin1_code":"6.0",
    "gn:admin2_code":"84.0",
    "gn:admin3_code":"8405.0",
    "gn:asciiname":"Tanilvoro",
    "gn:country_code":"CL",
    "gn:dem":342,
    "gn:feature_class":"P",
    "gn:feature_code":"PPL",
    "gn:name":"Tanilvoro",
    "gn:population":0,
    "gn:timezone":"America/Santiago",
    "iso:country":"CL",
    "wof:name":"Tanilvoro",
    "wof:placetype":"locality"
},
  "geometry": {"coordinates":[-71.84061,-36.7076],"type":"Point"}
}