{
  "type": "Feature",
  "properties": {
    "gn:admin1_code":"3.0",
    "gn:admin2_code":"21.0",
    "gn:asciiname":"Francke",
    "gn:country_code":"CL",
    "gn:dem":1735,
    "gn:feature_class":"P",
    "gn:feature_code":"PPL",
    "gn:name":"Francke",
    "gn:population":0,
    "gn:timezone":"America/Santiago",
    "iso:country":"CL",
    "name:nor_x_preferred":[
        "Francke"
    ],
    "wof:name":"Francke",
    "wof:placetype":"locality"
},
  "geometry": {"coordinates":[-69.86377,-25.83132],"type":"Point"}
}