{
  "type": "Feature",
  "properties": {
    "gn:admin1_code":"15.0",
    "gn:admin2_code":"14.0",
    "gn:admin3_code":"1401.0",
    "gn:asciiname":"Alto de Tuna",
    "gn:country_code":"CL",
    "gn:dem":3161,
    "gn:feature_class":"P",
    "gn:feature_code":"PPL",
    "gn:name":"Alto de Tuna",
    "gn:population":0,
    "gn:timezone":"America/Santiago",
    "iso:country":"CL",
    "wof:name":"Alto de Tuna",
    "wof:placetype":"locality"
},
  "geometry": {"coordinates":[-69.03364999999999,-20.87928],"type":"Point"}
}