{
  "type": "Feature",
  "properties": {
    "gn:admin1_code":"6.0",
    "gn:admin2_code":"83.0",
    "gn:admin3_code":"8303.0",
    "gn:asciiname":"El Manzano",
    "gn:country_code":"CL",
    "gn:dem":168,
    "gn:feature_class":"P",
    "gn:feature_code":"PPL",
    "gn:name":"El Manzano",
    "gn:population":0,
    "gn:timezone":"America/Santiago",
    "iso:country":"CL",
    "name:und_x_variant":[
        "Manzano",
        "El Manzano"
    ],
    "wof:name":"El Manzano",
    "wof:placetype":"locality"
},
  "geometry": {"coordinates":[-72.28584000000002,-37.15613],"type":"Point"}
}