{
  "type": "Feature",
  "properties": {
    "gn:admin1_code":"16.0",
    "gn:admin2_code":"151.0",
    "gn:asciiname":"Caritaya",
    "gn:country_code":"CL",
    "gn:dem":3658,
    "gn:feature_class":"P",
    "gn:feature_code":"PPL",
    "gn:name":"Caritaya",
    "gn:population":0,
    "gn:timezone":"America/Santiago",
    "iso:country":"CL",
    "name:spa_x_preferred":[
        "Caritaya"
    ],
    "name:und_x_variant":[
        "Reten Caritaya"
    ],
    "wof:name":"Caritaya",
    "wof:placetype":"locality"
},
  "geometry": {"coordinates":[-69.33881,-19.01533],"type":"Point"}
}