{
  "type": "Feature",
  "properties": {
    "gn:admin1_code":"15.0",
    "gn:admin2_code":"14.0",
    "gn:admin3_code":"1404.0",
    "gn:asciiname":"Guavina",
    "gn:country_code":"CL",
    "gn:dem":2398,
    "gn:feature_class":"P",
    "gn:feature_code":"PPL",
    "gn:name":"Guavi\u00f1a",
    "gn:population":0,
    "gn:timezone":"America/Santiago",
    "iso:country":"CL",
    "name:ceb_x_preferred":[
        "Guavina"
    ],
    "name:nld_x_preferred":[
        "Guavina"
    ],
    "name:spa_x_preferred":[
        "Guavina"
    ],
    "name:swe_x_preferred":[
        "Guavina"
    ],
    "name:und_x_variant":[
        "Huavi\u00f1a",
        "Guavi\u00f1a"
    ],
    "name:war_x_preferred":[
        "Guavina"
    ],
    "name:zho_x_preferred":[
        "\u74dc\u7ef4\u90a3\u5858\u9ce2\u5c5e"
    ],
    "wof:name":"Guavina",
    "wof:placetype":"locality"
},
  "geometry": {"coordinates":[-69.22338000000001,-19.79549],"type":"Point"}
}