{
  "type": "Feature",
  "properties": {
    "gn:country":"CL",
    "gn:fcode":"PPL",
    "gn:pop":0,
    "iso:country":"CL",
    "name:ceb_x_preferred":[
        "Choapa"
    ],
    "name:heb_x_preferred":[
        "\u05e6'\u05d5\u05d0\u05e4\u05d4"
    ],
    "name:ron_x_preferred":[
        "Choapa"
    ],
    "name:spa_x_preferred":[
        "Choapa"
    ],
    "name:swe_x_preferred":[
        "Choapa"
    ],
    "qs:name":"Choapa",
    "qs:name_adm0":"Chile",
    "qs:name_adm1":"Coquimbo",
    "qs:photos_9r":0,
    "qs:photos_sr":0,
    "qs:placetype":"Town",
    "qs:pop_sr":"0",
    "wd:wordcount":35,
    "wof:name":"Choapa",
    "wof:placetype":"locality",
    "wof:population":0
},
  "geometry": {"coordinates":[-71.20514,-31.73009],"type":"Point"}
}