{
  "type": "Feature",
  "properties": {
    "gn:admin1_code":"14.0",
    "gn:admin2_code":"101.0",
    "gn:admin3_code":"10109.0",
    "gn:asciiname":"Rio del Sur",
    "gn:cc2":"CL",
    "gn:country_code":"CL",
    "gn:dem":379,
    "gn:feature_class":"P",
    "gn:feature_code":"PPL",
    "gn:name":"R\u00edo del Sur",
    "gn:population":0,
    "gn:timezone":"America/Santiago",
    "iso:country":"CL",
    "name:und_x_variant":[
        "Colonia R\u00edo Sur",
        "R\u00edo del Sur"
    ],
    "wof:name":"Rio del Sur",
    "wof:placetype":"locality"
},
  "geometry": {"coordinates":[-72.71666999999999,-41.31667],"type":"Point"}
}