{
  "type": "Feature",
  "properties": {
    "gn:admin1_code":"8.0",
    "gn:admin2_code":"63.0",
    "gn:admin3_code":"6302.0",
    "gn:asciiname":"Auquinco",
    "gn:country_code":"CL",
    "gn:dem":229,
    "gn:feature_class":"P",
    "gn:feature_code":"PPL",
    "gn:name":"Auquinco",
    "gn:population":0,
    "gn:timezone":"America/Santiago",
    "iso:country":"CL",
    "wof:name":"Auquinco",
    "wof:placetype":"locality"
},
  "geometry": {"coordinates":[-71.19529,-34.765],"type":"Point"}
}