{
  "type": "Feature",
  "properties": {
    "gn:admin1_code":"16.0",
    "gn:admin2_code":"152.0",
    "gn:admin3_code":"15201.0",
    "gn:asciiname":"Misitune",
    "gn:country_code":"CL",
    "gn:dem":4310,
    "gn:feature_class":"P",
    "gn:feature_code":"PPL",
    "gn:name":"Misitune",
    "gn:population":0,
    "gn:timezone":"America/Santiago",
    "iso:country":"CL",
    "wof:name":"Misitune",
    "wof:placetype":"locality"
},
  "geometry": {"coordinates":[-69.36321,-18.37523],"type":"Point"}
}