{
  "type": "Feature",
  "properties": {
    "gn:admin1_code":"15.0",
    "gn:admin2_code":"14.0",
    "gn:admin3_code":"1401.0",
    "gn:asciiname":"El Chocal",
    "gn:country_code":"CL",
    "gn:dem":3588,
    "gn:feature_class":"P",
    "gn:feature_code":"PPL",
    "gn:name":"El Chocal",
    "gn:population":0,
    "gn:timezone":"America/Santiago",
    "iso:country":"CL",
    "wof:name":"El Chocal",
    "wof:placetype":"locality"
},
  "geometry": {"coordinates":[-68.88333,-21.25],"type":"Point"}
}