{
  "type": "Feature",
  "properties": {
    "gn:admin1_code":"6.0",
    "gn:admin2_code":"83.0",
    "gn:asciiname":"Casas Villucura",
    "gn:country_code":"CL",
    "gn:dem":717,
    "gn:feature_class":"P",
    "gn:feature_code":"PPL",
    "gn:name":"Casas Villucura",
    "gn:population":0,
    "gn:timezone":"America/Santiago",
    "iso:country":"CL",
    "name:spa_x_preferred":[
        "Las Centinelas"
    ],
    "wof:name":"Casas Villucura",
    "wof:placetype":"locality"
},
  "geometry": {"coordinates":[-71.41755999999999,-38.11422],"type":"Point"}
}