{
  "type": "Feature",
  "properties": {
    "gn:admin1_code":"8.0",
    "gn:admin2_code":"62.0",
    "gn:admin3_code":"6203.0",
    "gn:asciiname":"Ranquilco",
    "gn:country_code":"CL",
    "gn:dem":304,
    "gn:feature_class":"P",
    "gn:feature_code":"PPL",
    "gn:name":"Ranquilco",
    "gn:population":0,
    "gn:timezone":"America/Santiago",
    "iso:country":"CL",
    "name:und_x_variant":[
        "Panquilco",
        "Ranquilco"
    ],
    "wof:name":"Ranquilco",
    "wof:placetype":"locality"
},
  "geometry": {"coordinates":[-71.68092,-34.07398],"type":"Point"}
}