{
  "type": "Feature",
  "properties": {
    "gn:admin1_code":"5.0",
    "gn:admin2_code":"31.0",
    "gn:admin3_code":"3101.0",
    "gn:asciiname":"Mirador",
    "gn:country_code":"CL",
    "gn:dem":352,
    "gn:feature_class":"P",
    "gn:feature_code":"PPL",
    "gn:name":"Mirador",
    "gn:population":0,
    "gn:timezone":"America/Santiago",
    "iso:country":"CL",
    "name:ceb_x_preferred":[
        "Mirador"
    ],
    "name:deu_x_preferred":[
        "Mirador"
    ],
    "name:fra_x_preferred":[
        "Mirador"
    ],
    "name:ita_x_preferred":[
        "Mirador"
    ],
    "name:nld_x_preferred":[
        "Mirador"
    ],
    "name:nor_x_preferred":[
        "Mirador"
    ],
    "name:por_x_preferred":[
        "Mirador"
    ],
    "name:rus_x_preferred":[
        "\u041c\u0438\u0440\u0430\u0434\u043e\u0440"
    ],
    "name:spa_x_preferred":[
        "Mirador"
    ],
    "name:srp_x_preferred":[
        "\u041c\u0438\u0440\u0430\u0434\u043e\u0440"
    ],
    "name:swe_x_preferred":[
        "Mirador"
    ],
    "name:vie_x_preferred":[
        "Mirador"
    ],
    "name:vol_x_preferred":[
        "Mirador"
    ],
    "wof:name":"Mirador",
    "wof:placetype":"locality"
},
  "geometry": {"coordinates":[-70.36196,-27.34605],"type":"Point"}
}