{
  "type": "Feature",
  "properties": {
    "gn:admin1_code":"11.0",
    "gn:admin2_code":"71.0",
    "gn:admin3_code":"7102.0",
    "gn:asciiname":"Pichaman",
    "gn:country_code":"CL",
    "gn:dem":73,
    "gn:feature_class":"P",
    "gn:feature_code":"PPL",
    "gn:name":"Picham\u00e1n",
    "gn:population":0,
    "gn:timezone":"America/Santiago",
    "iso:country":"CL",
    "wof:name":"Pichaman",
    "wof:placetype":"locality"
},
  "geometry": {"coordinates":[-72.10457,-35.43347],"type":"Point"}
}