{
  "type": "Feature",
  "properties": {
    "gn:country":"CL",
    "gn:fcode":"ADM3",
    "gn:pop":0,
    "iso:country":"CL",
    "qs:name":"Vi\u00f1a del Mar",
    "qs:name_adm0":"Chile",
    "qs:name_adm1":"Valpara\u00edso",
    "qs:photos":7,
    "qs:photos_1k":1,
    "qs:photos_9k":103,
    "qs:photos_9r":21,
    "qs:photos_all":23319,
    "qs:photos_sr":1,
    "qs:placetype":"LocalAdmin",
    "qs:pop_sr":"0",
    "wd:elevation":2.0,
    "wd:population":324836,
    "wd:wordcount":3052,
    "wof:name":"Vi\u00f1a del Mar",
    "wof:placetype":"localadmin",
    "wof:population":324836
},
  "geometry": {"coordinates":[-71.51593,-33.02878],"type":"Point"}
}