{
  "type": "Feature",
  "properties": {
    "iso:country":"CL",
    "name:arn_x_preferred":[
        "Loncoche"
    ],
    "name:cat_x_preferred":[
        "Loncoche"
    ],
    "name:ceb_x_preferred":[
        "Loncoche"
    ],
    "name:deu_x_preferred":[
        "Loncoche"
    ],
    "name:eng_x_preferred":[
        "Loncoche"
    ],
    "name:eus_x_preferred":[
        "Loncoche"
    ],
    "name:fas_x_preferred":[
        "\u0644\u0648\u0646\u06a9\u0648\u0686\u0647"
    ],
    "name:fra_x_preferred":[
        "Loncoche"
    ],
    "name:ita_x_preferred":[
        "Loncoche"
    ],
    "name:jpn_x_preferred":[
        "\u30ed\u30f3\u30b3\u30c1\u30a7"
    ],
    "name:kor_x_preferred":[
        "\ub871\ucf54\uccb4"
    ],
    "name:nan_x_preferred":[
        "Loncoche"
    ],
    "name:nld_x_preferred":[
        "Loncoche"
    ],
    "name:oci_x_preferred":[
        "Loncoche"
    ],
    "name:por_x_preferred":[
        "Loncoche"
    ],
    "name:ron_x_preferred":[
        "Loncoche"
    ],
    "name:rus_x_preferred":[
        "\u041b\u043e\u043d\u043a\u043e\u0447\u0435"
    ],
    "name:spa_x_preferred":[
        "Loncoche"
    ],
    "name:swe_x_preferred":[
        "Loncoche"
    ],
    "name:zho_x_preferred":[
        "\u502b\u79d1\u5207"
    ],
    "qs:name":"Loncoche",
    "qs:name_adm0":"Chile",
    "qs:name_adm1":"Araucania",
    "qs:photos":2,
    "qs:photos_1k":1,
    "qs:photos_9k":1,
    "qs:photos_9r":3,
    "qs:photos_all":111,
    "qs:photos_sr":1,
    "qs:placetype":"LocalAdmin",
    "qs:pop_sr":"0",
    "wd:wordcount":274,
    "wof:name":"Loncoche",
    "wof:placetype":"localadmin"
},
  "geometry": {"coordinates":[-72.631344,-39.369813],"type":"Point"}
}