{
  "type": "Feature",
  "properties": {
    "iso:country":"CL",
    "qs:name":"Loncoche",
    "qs:name_adm0":"Chile",
    "qs:name_adm1":"Araucania",
    "qs:photos":2,
    "qs:photos_1k":1,
    "qs:photos_9k":1,
    "qs:photos_9r":3,
    "qs:photos_all":111,
    "qs:photos_sr":1,
    "qs:placetype":"LocalAdmin",
    "qs:pop_sr":"0",
    "wd:wordcount":274,
    "wof:name":"Loncoche",
    "wof:placetype":"localadmin"
},
  "geometry": {"coordinates":[-72.631344,-39.369813],"type":"Point"}
}