{
  "type": "Feature",
  "properties": {
    "gn:admin1_code":"16.0",
    "gn:admin2_code":"151.0",
    "gn:admin3_code":"15101.0",
    "gn:asciiname":"Taipimarca",
    "gn:country_code":"CL",
    "gn:dem":944,
    "gn:feature_class":"P",
    "gn:feature_code":"PPL",
    "gn:name":"Taipimarca",
    "gn:population":0,
    "gn:timezone":"America/Santiago",
    "iso:country":"CL",
    "wof:name":"Taipimarca",
    "wof:placetype":"locality"
},
  "geometry": {"coordinates":[-69.94996999999999,-18.38809],"type":"Point"}
}