{
  "type": "Feature",
  "properties": {
    "gn:admin1_code":"1.0",
    "gn:admin2_code":"58.0",
    "gn:admin3_code":"5803.0",
    "gn:asciiname":"Lo Narvaez",
    "gn:country_code":"CL",
    "gn:dem":150,
    "gn:feature_class":"P",
    "gn:feature_code":"PPL",
    "gn:name":"Lo Narv\u00e1ez",
    "gn:population":0,
    "gn:timezone":"America/Santiago",
    "iso:country":"CL",
    "wof:name":"Lo Narvaez",
    "wof:placetype":"locality"
},
  "geometry": {"coordinates":[-71.18333,-33.01667],"type":"Point"}
}