{
  "type": "Feature",
  "properties": {
    "gn:admin1_code":"15.0",
    "gn:admin2_code":"14.0",
    "gn:admin3_code":"1404.0",
    "gn:asciiname":"Suca Alto",
    "gn:country_code":"CL",
    "gn:dem":1039,
    "gn:feature_class":"P",
    "gn:feature_code":"PPL",
    "gn:name":"Suca Alto",
    "gn:population":0,
    "gn:timezone":"America/Santiago",
    "iso:country":"CL",
    "wof:name":"Suca Alto",
    "wof:placetype":"locality"
},
  "geometry": {"coordinates":[-69.78333000000001,-19.26667],"type":"Point"}
}