{
  "type": "Feature",
  "properties": {
    "gn:admin1_code":"7.0",
    "gn:admin2_code":"42.0",
    "gn:asciiname":"Las Canas",
    "gn:country_code":"CL",
    "gn:dem":377,
    "gn:feature_class":"P",
    "gn:feature_code":"PPL",
    "gn:name":"Las Ca\u00f1as",
    "gn:population":0,
    "gn:timezone":"America/Santiago",
    "iso:country":"CL",
    "name:spa_x_preferred":[
        "Las Ca\u00f1as"
    ],
    "wof:name":"Las Canas",
    "wof:placetype":"locality"
},
  "geometry": {"coordinates":[-71.21226999999998,-31.7421],"type":"Point"}
}