{
  "type": "Feature",
  "properties": {
    "gn:admin1_code":"7.0",
    "gn:admin2_code":"43.0",
    "gn:admin3_code":"4302.0",
    "gn:asciiname":"Manquegua",
    "gn:country_code":"CL",
    "gn:dem":614,
    "gn:feature_class":"P",
    "gn:feature_code":"PPL",
    "gn:name":"Manquegua",
    "gn:population":0,
    "gn:timezone":"America/Santiago",
    "iso:country":"CL",
    "wof:name":"Manquegua",
    "wof:placetype":"locality"
},
  "geometry": {"coordinates":[-71.18814,-30.94717],"type":"Point"}
}