{
  "type": "Feature",
  "properties": {
    "gn:admin1_code":"7.0",
    "gn:admin2_code":"43.0",
    "gn:admin3_code":"4301.0",
    "gn:asciiname":"Panulcillo",
    "gn:country_code":"CL",
    "gn:dem":516,
    "gn:feature_class":"P",
    "gn:feature_code":"PPL",
    "gn:name":"Panulcillo",
    "gn:population":0,
    "gn:timezone":"America/Santiago",
    "iso:country":"CL",
    "name:und_x_variant":[
        "Panucillo",
        "Panulcillo"
    ],
    "wof:name":"Panulcillo",
    "wof:placetype":"locality"
},
  "geometry": {"coordinates":[-71.22833,-30.45274],"type":"Point"}
}