{
  "type": "Feature",
  "properties": {
    "gn:admin1_code":"2.0",
    "gn:admin2_code":"111.0",
    "gn:admin3_code":"11101.0",
    "gn:asciiname":"Coihaique Alto",
    "gn:country_code":"CL",
    "gn:dem":729,
    "gn:feature_class":"P",
    "gn:feature_code":"PPL",
    "gn:name":"Coihaique Alto",
    "gn:population":0,
    "gn:timezone":"America/Santiago",
    "iso:country":"CL",
    "name:und_x_variant":[
        "Coyhaique Alto",
        "Coihaique Alto"
    ],
    "wof:name":"Coihaique Alto",
    "wof:placetype":"locality"
},
  "geometry": {"coordinates":[-71.60388,-45.4803],"type":"Point"}
}