{
  "type": "Feature",
  "properties": {
    "gn:admin1_code":"4.0",
    "gn:admin2_code":"92.0",
    "gn:admin3_code":"9208.0",
    "gn:asciiname":"Ipinco",
    "gn:country_code":"CL",
    "gn:dem":510,
    "gn:feature_class":"P",
    "gn:feature_code":"PPL",
    "gn:name":"Ipinco",
    "gn:population":0,
    "gn:timezone":"America/Santiago",
    "iso:country":"CL",
    "wof:name":"Ipinco",
    "wof:placetype":"locality"
},
  "geometry": {"coordinates":[-73.06801,-38.07537],"type":"Point"}
}