{
  "type": "Feature",
  "properties": {
    "gn:admin1_code":"6.0",
    "gn:admin2_code":"83.0",
    "gn:admin3_code":"8302.0",
    "gn:asciiname":"El Abanico",
    "gn:cc2":"CL",
    "gn:country_code":"CL",
    "gn:dem":1033,
    "gn:feature_class":"P",
    "gn:feature_code":"PPL",
    "gn:name":"El Abanico",
    "gn:population":0,
    "gn:timezone":"America/Santiago",
    "iso:country":"CL",
    "name:und_x_variant":[
        "Abanico",
        "El Abanico"
    ],
    "wof:name":"El Abanico",
    "wof:placetype":"locality"
},
  "geometry": {"coordinates":[-71.51666999999998,-37.33333],"type":"Point"}
}