{
  "type": "Feature",
  "properties": {
    "gn:country":"CL",
    "gn:fcode":"PPL",
    "gn:pop":0,
    "iso:country":"CL",
    "name:ara_x_preferred":[
        "\u0643\u0627\u0644\u064a\u0631\u0627 \u062f\u064a \u062a\u0627\u0646\u062c\u0648"
    ],
    "name:cat_x_preferred":[
        "Calera de Tango"
    ],
    "name:deu_x_preferred":[
        "Calera de Tango"
    ],
    "name:eng_x_preferred":[
        "Calera de Tango"
    ],
    "name:eus_x_preferred":[
        "Calera de Tango"
    ],
    "name:fas_x_preferred":[
        "\u06a9\u0627\u0644\u0631\u0627 \u062f \u062a\u0627\u0646\u06af\u0648"
    ],
    "name:fra_x_preferred":[
        "Calera de Tango"
    ],
    "name:ita_x_preferred":[
        "Calera de Tango"
    ],
    "name:kor_x_preferred":[
        "\uce7c\ub808\ub77c\ub370\ud0d5\uace0"
    ],
    "name:nan_x_preferred":[
        "Calera de Tango"
    ],
    "name:nld_x_preferred":[
        "Calera de Tango"
    ],
    "name:oci_x_preferred":[
        "Calera de Tango"
    ],
    "name:por_x_preferred":[
        "Calera de Tango"
    ],
    "name:ron_x_preferred":[
        "Calera de Tango"
    ],
    "name:rus_x_preferred":[
        "\u041a\u0430\u043b\u0435\u0440\u0430-\u0434\u0435-\u0422\u0430\u043d\u0433\u043e"
    ],
    "name:spa_x_preferred":[
        "Calera de Tango"
    ],
    "name:swe_x_preferred":[
        "Calera de Tango"
    ],
    "name:zho_x_preferred":[
        "\u5361\u840a\u62c9\u5fb7\u5766\u6208"
    ],
    "qs:name":"Calera de Tango",
    "qs:name_adm0":"Chile",
    "qs:name_adm1":"Santiago",
    "qs:photos_9k":1,
    "qs:photos_9r":1,
    "qs:photos_all":1,
    "qs:photos_sr":0,
    "qs:placetype":"Town",
    "qs:pop_sr":"0",
    "wd:wordcount":254,
    "wof:name":"Calera de Tango",
    "wof:placetype":"locality",
    "wof:population":0
},
  "geometry": {"coordinates":[-70.79912,-33.62238],"type":"Point"}
}