{
  "type": "Feature",
  "properties": {
    "gn:gn_country":"CL",
    "gn:gn_fcode":"ADM3",
    "gn:gn_pop":0,
    "iso:country":"CL",
    "name:ara_x_preferred":[
        "\u0643\u0627\u0633\u0627\u0628\u0644\u0627\u0646\u0643\u0627"
    ],
    "name:kor_x_preferred":[
        "\uce74\uc0ac\ube14\ub791\uce74"
    ],
    "name:rus_x_preferred":[
        "\u041a\u0430\u0441\u0430\u0431\u043b\u0430\u043d\u043a\u0430"
    ],
    "name:zho_x_preferred":[
        "\u5361\u85a9\u5e03\u862d\u5361"
    ],
    "qs_pg:aaroncc":"CL",
    "qs_pg:gn_country":"CL",
    "qs_pg:gn_fcode":"ADM3",
    "qs_pg:gn_pop":0,
    "qs_pg:name":"Casablanca",
    "qs_pg:name_adm0":"Chile",
    "qs_pg:name_adm1":"Valpara\u00edso",
    "qs_pg:photos_9k":6,
    "qs_pg:photos_9r":7,
    "qs_pg:photos_all":1326,
    "qs_pg:photos_sr":0,
    "qs_pg:pop_sr":0,
    "qs_pg:qs_pg_placetype":"localadmin",
    "qs_pg:qs_pg_placetype_gp":"LocalAdmin",
    "qs_pg:woe_adm0":23424782,
    "woe:adm0_id":23424782,
    "woe:name_adm0":"Chile",
    "woe:name_adm1":"Valpara\u00edso",
    "woe:placetype":"LocalAdmin",
    "wof:name":"Casablanca",
    "wof:placetype":"localadmin"
},
  "geometry": {"coordinates":[-71.43531,-33.3158],"type":"Point"}
}