{
  "type": "Feature",
  "properties": {
    "gn:admin1_code":"14.0",
    "gn:admin2_code":"102.0",
    "gn:asciiname":"Paildad",
    "gn:country_code":"CL",
    "gn:dem":6,
    "gn:feature_class":"P",
    "gn:feature_code":"PPL",
    "gn:name":"Paildad",
    "gn:population":0,
    "gn:timezone":"America/Santiago",
    "iso:country":"CL",
    "name:und_x_variant":[
        "Pailad",
        "Paildad"
    ],
    "wof:name":"Paildad",
    "wof:placetype":"locality"
},
  "geometry": {"coordinates":[-73.60580999999998,-42.85245],"type":"Point"}
}