{
  "type": "Feature",
  "properties": {
    "gn:admin1_code":"14.0",
    "gn:admin2_code":"101.0",
    "gn:admin3_code":"10103.0",
    "gn:asciiname":"El Arco",
    "gn:country_code":"CL",
    "gn:dem":725,
    "gn:feature_class":"P",
    "gn:feature_code":"PPL",
    "gn:name":"El Arco",
    "gn:population":0,
    "gn:timezone":"America/Santiago",
    "iso:country":"CL",
    "name:ceb_x_preferred":[
        "El Arco"
    ],
    "name:spa_x_preferred":[
        "El Arco"
    ],
    "name:swe_x_preferred":[
        "El Arco"
    ],
    "name:und_x_variant":[
        "Arco"
    ],
    "wof:name":"El Arco",
    "wof:placetype":"locality"
},
  "geometry": {"coordinates":[-72.04716999999999,-41.42371],"type":"Point"}
}