{
  "type": "Feature",
  "properties": {
    "gn:admin1_code":"11.0",
    "gn:admin2_code":"71.0",
    "gn:admin3_code":"7103.0",
    "gn:asciiname":"Huelon",
    "gn:country_code":"CL",
    "gn:dem":21,
    "gn:feature_class":"P",
    "gn:feature_code":"PPL",
    "gn:name":"Huel\u00f3n",
    "gn:population":0,
    "gn:timezone":"America/Santiago",
    "iso:country":"CL",
    "wof:name":"Huelon",
    "wof:placetype":"locality"
},
  "geometry": {"coordinates":[-72.05076,-35.081],"type":"Point"}
}