{
  "type": "Feature",
  "properties": {
    "gn:admin1_code":"15.0",
    "gn:admin2_code":"14.0",
    "gn:admin3_code":"1405.0",
    "gn:asciiname":"Collacollani",
    "gn:country_code":"CL",
    "gn:dem":3932,
    "gn:feature_class":"P",
    "gn:feature_code":"PPL",
    "gn:name":"Collacollani",
    "gn:population":0,
    "gn:timezone":"America/Santiago",
    "iso:country":"CL",
    "name:spa_x_preferred":[
        "Collacollani"
    ],
    "name:und_x_variant":[
        "Collacollane"
    ],
    "wof:name":"Collacollani",
    "wof:placetype":"locality"
},
  "geometry": {"coordinates":[-68.61891,-19.94867],"type":"Point"}
}