{
  "type": "Feature",
  "properties": {
    "gn:admin1_code":"14.0",
    "gn:admin2_code":"104.0",
    "gn:admin3_code":"10404.0",
    "gn:asciiname":"Las Maravillas",
    "gn:country_code":"CL",
    "gn:dem":424,
    "gn:feature_class":"P",
    "gn:feature_code":"PPL",
    "gn:name":"Las Maravillas",
    "gn:population":0,
    "gn:timezone":"America/Santiago",
    "iso:country":"CL",
    "wof:name":"Las Maravillas",
    "wof:placetype":"locality"
},
  "geometry": {"coordinates":[-71.83192,-43.77029],"type":"Point"}
}