{
  "type": "Feature",
  "properties": {
    "gn:admin1_code":"14.0",
    "gn:admin2_code":"102.0",
    "gn:admin3_code":"10203.0",
    "gn:asciiname":"Natri",
    "gn:country_code":"CL",
    "gn:dem":44,
    "gn:feature_class":"P",
    "gn:feature_code":"PPL",
    "gn:name":"Natri",
    "gn:population":0,
    "gn:timezone":"America/Santiago",
    "iso:country":"CL",
    "name:spa_x_preferred":[
        "Natri"
    ],
    "wof:name":"Natri",
    "wof:placetype":"locality"
},
  "geometry": {"coordinates":[-73.77674,-42.79897],"type":"Point"}
}