{
  "type": "Feature",
  "properties": {
    "gn:admin1_code":"7.0",
    "gn:admin2_code":"43.0",
    "gn:admin3_code":"4305.0",
    "gn:asciiname":"Quebraditas",
    "gn:country_code":"CL",
    "gn:dem":2152,
    "gn:feature_class":"P",
    "gn:feature_code":"PPL",
    "gn:name":"Quebraditas",
    "gn:population":0,
    "gn:timezone":"America/Santiago",
    "iso:country":"CL",
    "wof:name":"Quebraditas",
    "wof:placetype":"locality"
},
  "geometry": {"coordinates":[-70.51076,-30.46781],"type":"Point"}
}