{
  "type": "Feature",
  "properties": {
    "gn:admin1_code":"15.0",
    "gn:admin2_code":"14.0",
    "gn:admin3_code":"1401.0",
    "gn:asciiname":"Sagasca",
    "gn:country_code":"CL",
    "gn:dem":1835,
    "gn:feature_class":"P",
    "gn:feature_code":"PPL",
    "gn:name":"Sagasca",
    "gn:population":0,
    "gn:timezone":"America/Santiago",
    "iso:country":"CL",
    "name:spa_x_preferred":[
        "Sagasca"
    ],
    "wof:name":"Sagasca",
    "wof:placetype":"locality"
},
  "geometry": {"coordinates":[-69.33081,-20.19207],"type":"Point"}
}