{
  "type": "Feature",
  "properties": {
    "iso:country":"CL",
    "name:cat_x_preferred":[
        "Natales"
    ],
    "name:ceb_x_preferred":[
        "Natales"
    ],
    "name:eng_x_preferred":[
        "Natales"
    ],
    "name:eus_x_preferred":[
        "Natales"
    ],
    "name:fas_x_preferred":[
        "\u0646\u0627\u062a\u0627\u0644\u0633"
    ],
    "name:fra_x_preferred":[
        "Natales"
    ],
    "name:ita_x_preferred":[
        "Natales"
    ],
    "name:kor_x_preferred":[
        "\ub098\ud0c8\ub808\uc2a4"
    ],
    "name:nan_x_preferred":[
        "Natales"
    ],
    "name:nld_x_preferred":[
        "Natales"
    ],
    "name:oci_x_preferred":[
        "Natales"
    ],
    "name:pol_x_preferred":[
        "Natales"
    ],
    "name:por_x_preferred":[
        "Natales"
    ],
    "name:ron_x_preferred":[
        "Natales"
    ],
    "name:rus_x_preferred":[
        "\u041d\u0430\u0442\u0430\u043b\u0435\u0441"
    ],
    "name:spa_x_preferred":[
        "Natales"
    ],
    "name:swe_x_preferred":[
        "Natales"
    ],
    "name:ukr_x_preferred":[
        "\u041d\u0430\u0442\u0430\u043b\u0435\u0441"
    ],
    "name:zho_x_preferred":[
        "\u7d0d\u5854\u840a\u65af"
    ],
    "qs:name":"Natales",
    "qs:name_adm0":"Chile",
    "qs:name_adm1":"Magallanes y Antartica Chilena",
    "qs:photos":2,
    "qs:photos_1k":1,
    "qs:photos_9k":15,
    "qs:photos_9r":11,
    "qs:photos_all":3473,
    "qs:photos_sr":1,
    "qs:placetype":"LocalAdmin",
    "qs:pop_sr":"0",
    "wd:wordcount":407,
    "wof:name":"Natales",
    "wof:placetype":"localadmin"
},
  "geometry": {"coordinates":[-72.507289,-51.727878],"type":"Point"}
}