{
  "type": "Feature",
  "properties": {
    "iso:country":"CL",
    "qs:name":"Natales",
    "qs:name_adm0":"Chile",
    "qs:name_adm1":"Magallanes y Antartica Chilena",
    "qs:photos":2,
    "qs:photos_1k":1,
    "qs:photos_9k":15,
    "qs:photos_9r":11,
    "qs:photos_all":3473,
    "qs:photos_sr":1,
    "qs:placetype":"LocalAdmin",
    "qs:pop_sr":"0",
    "wd:wordcount":407,
    "wof:name":"Natales",
    "wof:placetype":"localadmin"
},
  "geometry": {"coordinates":[-72.507289,-51.727878],"type":"Point"}
}