{
  "type": "Feature",
  "properties": {
    "gn:admin1_code":"11.0",
    "gn:admin2_code":"73.0",
    "gn:admin3_code":"7306.0",
    "gn:asciiname":"Los Quenes",
    "gn:country_code":"CL",
    "gn:dem":665,
    "gn:feature_class":"P",
    "gn:feature_code":"PPL",
    "gn:name":"Los Que\u00f1es",
    "gn:population":0,
    "gn:timezone":"America/Santiago",
    "iso:country":"CL",
    "wof:name":"Los Quenes",
    "wof:placetype":"locality"
},
  "geometry": {"coordinates":[-70.81639,-34.99856],"type":"Point"}
}