{
  "type": "Feature",
  "properties": {
    "gn:admin1_code":"14.0",
    "gn:admin2_code":"104.0",
    "gn:admin3_code":"10402.0",
    "gn:asciiname":"Espolon",
    "gn:country_code":"CL",
    "gn:dem":433,
    "gn:feature_class":"P",
    "gn:feature_code":"PPL",
    "gn:name":"Espol\u00f3n",
    "gn:population":0,
    "gn:timezone":"America/Argentina/Catamarca",
    "iso:country":"CL",
    "name:und_x_variant":[
        "Espol\u00f3n",
        "El Espol\u00f3n"
    ],
    "wof:name":"Espolon",
    "wof:placetype":"locality"
},
  "geometry": {"coordinates":[-72.02294999999999,-43.09404],"type":"Point"}
}