{
  "type": "Feature",
  "properties": {
    "gn:gn_country":"CL",
    "gn:gn_fcode":"ADM3",
    "gn:gn_pop":0,
    "iso:country":"CL",
    "name:bak_x_preferred":[
        "\u041f\u043b\u0430\u0441\u0438\u043b\u044c\u044f"
    ],
    "name:ceb_x_preferred":[
        "Placilla"
    ],
    "name:eus_x_preferred":[
        "Placilla"
    ],
    "name:fas_x_preferred":[
        "\u067e\u0644\u0627\u062b\u06cc\u0627"
    ],
    "name:fra_x_preferred":[
        "Placilla"
    ],
    "name:ita_x_preferred":[
        "Placilla"
    ],
    "name:kor_x_preferred":[
        "\ud50c\ub77c\uc2dc\uc57c"
    ],
    "name:nld_x_preferred":[
        "Placilla"
    ],
    "name:por_x_preferred":[
        "Placilla"
    ],
    "name:ron_x_preferred":[
        "Placilla"
    ],
    "name:rus_x_preferred":[
        "\u041f\u043b\u0430\u0441\u0438\u043b\u044c\u044f"
    ],
    "name:sco_x_preferred":[
        "Placilla"
    ],
    "name:spa_x_preferred":[
        "Placilla"
    ],
    "name:swe_x_preferred":[
        "Placilla"
    ],
    "name:zho_x_preferred":[
        "\u666e\u62c9\u897f\u4e9e"
    ],
    "qs_pg:aaroncc":"CL",
    "qs_pg:gn_country":"CL",
    "qs_pg:gn_fcode":"ADM3",
    "qs_pg:gn_pop":0,
    "qs_pg:name":"Placilla",
    "qs_pg:photos_9r":0,
    "qs_pg:photos_sr":0,
    "qs_pg:pop_sr":0,
    "qs_pg:qs_pg_placetype":"localadmin",
    "wof:name":"Placilla",
    "wof:placetype":"localadmin"
},
  "geometry": {"coordinates":[-71.08623,-34.61921],"type":"Point"}
}