{
  "type": "Feature",
  "properties": {
    "gn:admin1_code":"7.0",
    "gn:admin2_code":"43.0",
    "gn:admin3_code":"4303.0",
    "gn:asciiname":"Mialqui",
    "gn:country_code":"CL",
    "gn:dem":547,
    "gn:feature_class":"P",
    "gn:feature_code":"PPL",
    "gn:name":"Mialqui",
    "gn:population":0,
    "gn:timezone":"America/Santiago",
    "iso:country":"CL",
    "name:und_x_variant":[
        "Miaqui",
        "Mialqui"
    ],
    "wof:name":"Mialqui",
    "wof:placetype":"locality"
},
  "geometry": {"coordinates":[-70.85911,-30.75039],"type":"Point"}
}