{
  "type": "Feature",
  "properties": {
    "gn:admin1_code":"5.0",
    "gn:admin2_code":"32.0",
    "gn:admin3_code":"3202.0",
    "gn:asciiname":"Mostazal",
    "gn:country_code":"CL",
    "gn:dem":2616,
    "gn:feature_class":"P",
    "gn:feature_code":"PPL",
    "gn:name":"Mostazal",
    "gn:population":0,
    "gn:timezone":"America/Santiago",
    "iso:country":"CL",
    "name:bak_x_preferred":[
        "\u041c\u043e\u0441\u0442\u0430\u0441\u0430\u043b\u044c"
    ],
    "name:ceb_x_preferred":[
        "Mostazal"
    ],
    "name:eus_x_preferred":[
        "Mostazal"
    ],
    "name:fas_x_preferred":[
        "\u0645\u0648\u0633\u062a\u062b\u0644"
    ],
    "name:fra_x_preferred":[
        "Mostazal"
    ],
    "name:ita_x_preferred":[
        "Mostazal"
    ],
    "name:kor_x_preferred":[
        "\ubaa8\uc2a4\ud0c0\uc0b4"
    ],
    "name:nld_x_preferred":[
        "Mostazal"
    ],
    "name:por_x_preferred":[
        "Mostazal"
    ],
    "name:ron_x_preferred":[
        "Mostazal"
    ],
    "name:rus_x_preferred":[
        "\u041c\u043e\u0441\u0442\u0430\u0441\u0430\u043b\u044c"
    ],
    "name:sco_x_preferred":[
        "Mostazal"
    ],
    "name:spa_x_preferred":[
        "Mostazal"
    ],
    "name:swe_x_preferred":[
        "Mostazal"
    ],
    "name:zho_x_preferred":[
        "\u83ab\u65af\u5854\u85a9\u723e"
    ],
    "wof:name":"Mostazal",
    "wof:placetype":"locality"
},
  "geometry": {"coordinates":[-69.58201,-26.68818],"type":"Point"}
}