{
  "type": "Feature",
  "properties": {
    "gn:admin1_code":"5.0",
    "gn:admin2_code":"32.0",
    "gn:admin3_code":"3202.0",
    "gn:asciiname":"Mostazal",
    "gn:country_code":"CL",
    "gn:dem":2616,
    "gn:feature_class":"P",
    "gn:feature_code":"PPL",
    "gn:name":"Mostazal",
    "gn:population":0,
    "gn:timezone":"America/Santiago",
    "iso:country":"CL",
    "wof:name":"Mostazal",
    "wof:placetype":"locality"
},
  "geometry": {"coordinates":[-69.58201,-26.68818],"type":"Point"}
}