{
  "type": "Feature",
  "properties": {
    "iso:country":"CL",
    "name:cat_x_preferred":[
        "Perquenco"
    ],
    "name:ceb_x_preferred":[
        "Perquenco"
    ],
    "name:deu_x_preferred":[
        "Perquenco"
    ],
    "name:eng_x_preferred":[
        "Perquenco"
    ],
    "name:eus_x_preferred":[
        "Perquenco"
    ],
    "name:fas_x_preferred":[
        "\u067e\u0631\u06a9\u0646\u06a9\u0648"
    ],
    "name:fra_x_preferred":[
        "Perquenco"
    ],
    "name:ita_x_preferred":[
        "Perquenco"
    ],
    "name:kor_x_preferred":[
        "\ud398\ub974\ucf15\ucf54"
    ],
    "name:nan_x_preferred":[
        "Perquenco"
    ],
    "name:nld_x_preferred":[
        "Perquenco"
    ],
    "name:oci_x_preferred":[
        "Perquenco"
    ],
    "name:por_x_preferred":[
        "Perquenco"
    ],
    "name:ron_x_preferred":[
        "Perquenco"
    ],
    "name:rus_x_preferred":[
        "\u041f\u0435\u0440\u043a\u0435\u043d\u043a\u043e"
    ],
    "name:spa_x_preferred":[
        "Perquenco"
    ],
    "name:swe_x_preferred":[
        "Perquenco"
    ],
    "name:zho_x_preferred":[
        "\u4f69\u723e\u7434\u79d1"
    ],
    "qs:name":"Perquenco",
    "qs:name_adm0":"Chile",
    "qs:name_adm1":"Araucania",
    "qs:photos":1,
    "qs:photos_1k":1,
    "qs:photos_9k":1,
    "qs:photos_9r":2,
    "qs:photos_all":33,
    "qs:photos_sr":1,
    "qs:placetype":"LocalAdmin",
    "qs:pop_sr":"0",
    "wd:wordcount":261,
    "wof:name":"Perquenco",
    "wof:placetype":"localadmin"
},
  "geometry": {"coordinates":[-72.383079,-38.4412195],"type":"Point"}
}