{
  "type": "Feature",
  "properties": {
    "iso:country":"CL",
    "qs:name":"Perquenco",
    "qs:name_adm0":"Chile",
    "qs:name_adm1":"Araucania",
    "qs:photos":1,
    "qs:photos_1k":1,
    "qs:photos_9k":1,
    "qs:photos_9r":2,
    "qs:photos_all":33,
    "qs:photos_sr":1,
    "qs:placetype":"LocalAdmin",
    "qs:pop_sr":"0",
    "wd:wordcount":261,
    "wof:name":"Perquenco",
    "wof:placetype":"localadmin"
},
  "geometry": {"coordinates":[-72.383079,-38.4412195],"type":"Point"}
}