{
  "type": "Feature",
  "properties": {
    "iso:country":"CL",
    "name:cat_x_preferred":[
        "Huara"
    ],
    "name:ceb_x_preferred":[
        "Huara"
    ],
    "name:deu_x_preferred":[
        "Huara"
    ],
    "name:eng_x_preferred":[
        "Huara"
    ],
    "name:eus_x_preferred":[
        "Huara"
    ],
    "name:fas_x_preferred":[
        "\u0648\u0648\u0622\u0631\u0627"
    ],
    "name:fin_x_preferred":[
        "Huara"
    ],
    "name:fra_x_preferred":[
        "Huara"
    ],
    "name:ita_x_preferred":[
        "Huara"
    ],
    "name:kor_x_preferred":[
        "\uc6b0\uc544\ub77c"
    ],
    "name:nan_x_preferred":[
        "Huara"
    ],
    "name:nld_x_preferred":[
        "Huara"
    ],
    "name:oci_x_preferred":[
        "Huara"
    ],
    "name:por_x_preferred":[
        "Huara"
    ],
    "name:que_x_preferred":[
        "Wara munisipyu"
    ],
    "name:roh_x_preferred":[
        "Huara"
    ],
    "name:ron_x_preferred":[
        "Huara"
    ],
    "name:rus_x_preferred":[
        "\u0423\u0430\u0440\u0430"
    ],
    "name:spa_x_preferred":[
        "Huara"
    ],
    "name:swe_x_preferred":[
        "Huara"
    ],
    "name:zho_x_preferred":[
        "\u74e6\u62c9"
    ],
    "qs:name":"Huara",
    "qs:name_adm0":"Chile",
    "qs:name_adm1":"Tarapaca",
    "qs:photos":2,
    "qs:photos_1k":1,
    "qs:photos_9k":1,
    "qs:photos_9r":4,
    "qs:photos_all":223,
    "qs:photos_sr":1,
    "qs:placetype":"LocalAdmin",
    "qs:pop_sr":"0",
    "wd:wordcount":284,
    "wof:name":"Huara",
    "wof:placetype":"localadmin"
},
  "geometry": {"coordinates":[-70.20993199999999,-19.5961],"type":"Point"}
}