{
  "type": "Feature",
  "properties": {
    "iso:country":"CL",
    "qs:name":"Huara",
    "qs:name_adm0":"Chile",
    "qs:name_adm1":"Tarapaca",
    "qs:photos":2,
    "qs:photos_1k":1,
    "qs:photos_9k":1,
    "qs:photos_9r":4,
    "qs:photos_all":223,
    "qs:photos_sr":1,
    "qs:placetype":"LocalAdmin",
    "qs:pop_sr":"0",
    "wd:wordcount":284,
    "wof:name":"Huara",
    "wof:placetype":"localadmin"
},
  "geometry": {"coordinates":[-70.20993199999999,-19.5961],"type":"Point"}
}