{
  "type": "Feature",
  "properties": {
    "gn:gn_country":"CL",
    "gn:gn_fcode":"PPL",
    "gn:gn_pop":0,
    "iso:country":"CL",
    "name:eng_x_preferred":[
        "Llif\u00e9n"
    ],
    "name:jpn_x_preferred":[
        "\u30ea\u30d5\u30a7\u30f3"
    ],
    "name:nld_x_preferred":[
        "Llif\u00e9n"
    ],
    "name:spa_x_preferred":[
        "Llif\u00e9n"
    ],
    "qs_pg:aaroncc":"CL",
    "qs_pg:gn_country":"CL",
    "qs_pg:gn_fcode":"PPL",
    "qs_pg:gn_pop":0,
    "qs_pg:name":"Llifen",
    "qs_pg:name_adm0":"Chile",
    "qs_pg:name_adm1":"Los Rios",
    "qs_pg:photos":57,
    "qs_pg:photos_1k":12,
    "qs_pg:photos_9k":1,
    "qs_pg:photos_9r":2,
    "qs_pg:photos_all":57,
    "qs_pg:photos_sr":2,
    "qs_pg:pop_sr":0,
    "qs_pg:qs_pg_placetype":"locality",
    "qs_pg:qs_pg_placetype_gp":"Town",
    "qs_pg:woe_adm0":23424782,
    "woe:adm0_id":23424782,
    "woe:name_adm0":"Chile",
    "woe:name_adm1":"Los Rios",
    "woe:placetype":"Town",
    "wof:name":"Llifen",
    "wof:placetype":"locality"
},
  "geometry": {"coordinates":[-72.26497999999999,-40.20379],"type":"Point"}
}