{
  "type": "Feature",
  "properties": {
    "gn:admin1_code":"6.0",
    "gn:admin2_code":"84.0",
    "gn:admin3_code":"8416.0",
    "gn:asciiname":"Pomuyeto",
    "gn:country_code":"CL",
    "gn:dem":197,
    "gn:feature_class":"P",
    "gn:feature_code":"PPL",
    "gn:name":"Pomuyeto",
    "gn:population":0,
    "gn:timezone":"America/Santiago",
    "iso:country":"CL",
    "wof:name":"Pomuyeto",
    "wof:placetype":"locality"
},
  "geometry": {"coordinates":[-71.92424,-36.44364],"type":"Point"}
}