{
  "type": "Feature",
  "properties": {
    "gn:admin1_code":"10.0",
    "gn:admin2_code":"123.0",
    "gn:admin3_code":"12303.0",
    "gn:asciiname":"Puerto Arturo",
    "gn:country_code":"CL",
    "gn:dem":17,
    "gn:feature_class":"P",
    "gn:feature_code":"PPL",
    "gn:name":"Puerto Arturo",
    "gn:population":0,
    "gn:timezone":"America/Punta_Arenas",
    "iso:country":"CL",
    "name:spa_x_preferred":[
        "Puerto Arturo"
    ],
    "wof:name":"Puerto Arturo",
    "wof:placetype":"locality"
},
  "geometry": {"coordinates":[-70.04288000000001,-54.06391],"type":"Point"}
}