{
  "type": "Feature",
  "properties": {
    "iso:country":"CL",
    "qs:name":"Hualaihue",
    "qs:name_adm0":"Chile",
    "qs:name_adm1":"Los Lagos",
    "qs:photos":29,
    "qs:photos_1k":6,
    "qs:photos_9k":1,
    "qs:photos_9r":4,
    "qs:photos_all":265,
    "qs:photos_sr":2,
    "qs:placetype":"LocalAdmin",
    "qs:pop_sr":"0",
    "wd:wordcount":245,
    "wof:name":"Hualaihue",
    "wof:placetype":"localadmin"
},
  "geometry": {"coordinates":[-72.469768,-41.968297],"type":"Point"}
}