{
  "type": "Feature",
  "properties": {
    "iso:country":"CL",
    "name:bul_x_preferred":[
        "\u0425\u0443\u0430\u0438\u043b\u0430\u0438\u0445\u0443\u0435"
    ],
    "name:cat_x_preferred":[
        "Hualaihu\u00e9"
    ],
    "name:ceb_x_preferred":[
        "Huailaihue"
    ],
    "name:ces_x_preferred":[
        "Hualaihu\u00e9"
    ],
    "name:deu_x_preferred":[
        "Hualaihu\u00e9"
    ],
    "name:ell_x_preferred":[
        "\u039f\u03c5\u03b1\u03bb\u03b1\u03ca\u03bf\u03c5\u03ad"
    ],
    "name:eng_x_preferred":[
        "Hualaihu\u00e9"
    ],
    "name:eus_x_preferred":[
        "Hualaihu\u00e9"
    ],
    "name:fra_x_preferred":[
        "Hualaihu\u00e9"
    ],
    "name:ita_x_preferred":[
        "Hualaihu\u00e9"
    ],
    "name:jpn_x_preferred":[
        "\u30a6\u30a2\u30e9\u30a4\u30a6\u30a8"
    ],
    "name:kor_x_preferred":[
        "\uc6b0\uc54c\ub77c\uc774\uc6b0\uc5d0"
    ],
    "name:nan_x_preferred":[
        "Hualaihu\u00e9"
    ],
    "name:nld_x_preferred":[
        "Hualaihu\u00e9"
    ],
    "name:oci_x_preferred":[
        "Hualaihu\u00e9"
    ],
    "name:por_x_preferred":[
        "Hualaihu\u00e9"
    ],
    "name:ron_x_preferred":[
        "Hualaihu\u00e9"
    ],
    "name:rus_x_preferred":[
        "\u0423\u0430\u043b\u0430\u0439\u0443\u044d"
    ],
    "name:slk_x_preferred":[
        "Hualaihu\u00e9"
    ],
    "name:spa_x_preferred":[
        "Hualaihu\u00e9"
    ],
    "name:swe_x_preferred":[
        "Huailaihue"
    ],
    "name:ukr_x_preferred":[
        "\u0423\u0430\u043b\u0430\u044e\u0435"
    ],
    "name:zho_x_preferred":[
        "\u74e6\u840a\u97cb"
    ],
    "qs:name":"Hualaihue",
    "qs:name_adm0":"Chile",
    "qs:name_adm1":"Los Lagos",
    "qs:photos":29,
    "qs:photos_1k":6,
    "qs:photos_9k":1,
    "qs:photos_9r":4,
    "qs:photos_all":265,
    "qs:photos_sr":2,
    "qs:placetype":"LocalAdmin",
    "qs:pop_sr":"0",
    "wd:wordcount":245,
    "wof:name":"Hualaihue",
    "wof:placetype":"localadmin"
},
  "geometry": {"coordinates":[-72.469768,-41.968297],"type":"Point"}
}