{
  "type": "Feature",
  "properties": {
    "gn:admin1_code":"15.0",
    "gn:admin2_code":"14.0",
    "gn:admin3_code":"1403.0",
    "gn:asciiname":"Cuchuguano",
    "gn:country_code":"CL",
    "gn:dem":3958,
    "gn:feature_class":"P",
    "gn:feature_code":"PPL",
    "gn:name":"Cuchuguano",
    "gn:population":0,
    "gn:timezone":"America/Santiago",
    "iso:country":"CL",
    "name:und_x_variant":[
        "Chuchuguana",
        "Cuchugano",
        "Cuchuguano"
    ],
    "wof:name":"Cuchuguano",
    "wof:placetype":"locality"
},
  "geometry": {"coordinates":[-68.57095,-19.59156],"type":"Point"}
}