{
  "type": "Feature",
  "properties": {
    "gn:admin1_code":"7.0",
    "gn:admin2_code":"43.0",
    "gn:admin3_code":"4305.0",
    "gn:asciiname":"El Castillo",
    "gn:country_code":"CL",
    "gn:dem":1268,
    "gn:feature_class":"P",
    "gn:feature_code":"PPL",
    "gn:name":"El Castillo",
    "gn:population":0,
    "gn:timezone":"America/Santiago",
    "iso:country":"CL",
    "wof:name":"El Castillo",
    "wof:placetype":"locality"
},
  "geometry": {"coordinates":[-70.64386999999998,-30.28387],"type":"Point"}
}