{
  "type": "Feature",
  "properties": {
    "gn:country":"CL",
    "gn:fcode":"PPL",
    "gn:population":0,
    "iso:country":"CL",
    "name:eng_x_preferred":[
        "El Guape"
    ],
    "name:spa_x_preferred":[
        "El Guape"
    ],
    "name:und_x_variant":[
        "Huape"
    ],
    "qs_pg:aaroncc":"CL",
    "qs_pg:gn_country":"CL",
    "qs_pg:gn_fcode":"PPL",
    "qs_pg:gn_pop":0,
    "qs_pg:name":"El Guape",
    "qs_pg:name_adm0":"Chile",
    "qs_pg:name_adm1":"Biobio",
    "qs_pg:photos_9r":0,
    "qs_pg:photos_sr":0,
    "qs_pg:pop_sr":0,
    "qs_pg:qs_pg_placetype":"locality",
    "qs_pg:qs_pg_placetype_gp":"Town",
    "qs_pg:woe_adm0":23424782,
    "woe:adm0_id":23424782,
    "woe:name_adm0":"Chile",
    "woe:name_adm1":"Biobio",
    "woe:placetype":"Town",
    "wof:name":"El Guape",
    "wof:placetype":"locality"
},
  "geometry": {"coordinates":[-72.24366000000001,-36.60928],"type":"Point"}
}