{
  "type": "Feature",
  "properties": {
    "gn:admin1_code":"14.0",
    "gn:admin2_code":"102.0",
    "gn:admin3_code":"10203.0",
    "gn:asciiname":"Quitripulli",
    "gn:country_code":"CL",
    "gn:dem":172,
    "gn:feature_class":"P",
    "gn:feature_code":"PPL",
    "gn:name":"Quitripulli",
    "gn:population":0,
    "gn:timezone":"America/Santiago",
    "iso:country":"CL",
    "name:spa_x_preferred":[
        "Quitripulli"
    ],
    "wof:name":"Quitripulli",
    "wof:placetype":"locality"
},
  "geometry": {"coordinates":[-73.70959000000001,-42.69223],"type":"Point"}
}