{
  "type": "Feature",
  "properties": {
    "iso:country":"CL",
    "qs:name":"Hualqui",
    "qs:name_adm0":"Chile",
    "qs:name_adm1":"Biobio",
    "qs:photos":1,
    "qs:photos_1k":1,
    "qs:photos_9k":1,
    "qs:photos_9r":4,
    "qs:photos_all":262,
    "qs:photos_sr":1,
    "qs:placetype":"LocalAdmin",
    "qs:pop_sr":"0",
    "wd:wordcount":374,
    "wof:name":"Hualqui",
    "wof:placetype":"localadmin"
},
  "geometry": {"coordinates":[-72.937427,-36.980066],"type":"Point"}
}