{
  "type": "Feature",
  "properties": {
    "iso:country":"CL",
    "name:afr_x_preferred":[
        "Hualqui"
    ],
    "name:arg_x_preferred":[
        "Hualqui"
    ],
    "name:ast_x_preferred":[
        "Hualqui"
    ],
    "name:aym_x_preferred":[
        "Hualqui"
    ],
    "name:aze_x_preferred":[
        "Hualqui"
    ],
    "name:cat_x_preferred":[
        "Hualqui"
    ],
    "name:ceb_x_preferred":[
        "Hualqui"
    ],
    "name:deu_x_preferred":[
        "Hualqui"
    ],
    "name:eng_x_preferred":[
        "Hualqui"
    ],
    "name:eus_x_preferred":[
        "Hualqui"
    ],
    "name:fas_x_preferred":[
        "\u0648\u0648\u0622\u0644\u06a9\u06cc"
    ],
    "name:fra_x_preferred":[
        "Hualqui"
    ],
    "name:glg_x_preferred":[
        "Hualqui"
    ],
    "name:hat_x_preferred":[
        "Hualqui"
    ],
    "name:hun_x_preferred":[
        "Hualqui"
    ],
    "name:ina_x_preferred":[
        "Hualqui"
    ],
    "name:ita_x_preferred":[
        "Hualqui"
    ],
    "name:kal_x_preferred":[
        "Hualqui"
    ],
    "name:kon_x_preferred":[
        "Hualqui"
    ],
    "name:kor_x_preferred":[
        "\uc6b0\uc54c\ud0a4"
    ],
    "name:lad_x_preferred":[
        "Ualki"
    ],
    "name:nah_x_preferred":[
        "Hualqui"
    ],
    "name:nan_x_preferred":[
        "Hualqui"
    ],
    "name:nld_x_preferred":[
        "Hualqui"
    ],
    "name:oci_x_preferred":[
        "Hualqui"
    ],
    "name:pap_x_preferred":[
        "Hualqui"
    ],
    "name:pms_x_preferred":[
        "Hualqui"
    ],
    "name:pol_x_preferred":[
        "Hualqui"
    ],
    "name:por_x_preferred":[
        "Hualqui"
    ],
    "name:ron_x_preferred":[
        "Hualqui"
    ],
    "name:rus_x_preferred":[
        "\u0423\u0430\u043b\u044c\u043a\u0438"
    ],
    "name:spa_x_preferred":[
        "Hualqui"
    ],
    "name:srp_x_preferred":[
        "\u0412\u0430\u043b\u043a\u0438"
    ],
    "name:swe_x_preferred":[
        "Hualqui"
    ],
    "name:vol_x_preferred":[
        "Hualqui"
    ],
    "name:war_x_preferred":[
        "Hualqui"
    ],
    "name:zho_x_preferred":[
        "\u74e6\u723e\u57fa"
    ],
    "qs:name":"Hualqui",
    "qs:name_adm0":"Chile",
    "qs:name_adm1":"Biobio",
    "qs:photos":1,
    "qs:photos_1k":1,
    "qs:photos_9k":1,
    "qs:photos_9r":4,
    "qs:photos_all":262,
    "qs:photos_sr":1,
    "qs:placetype":"LocalAdmin",
    "qs:pop_sr":"0",
    "wd:wordcount":374,
    "wof:name":"Hualqui",
    "wof:placetype":"localadmin"
},
  "geometry": {"coordinates":[-72.937427,-36.980066],"type":"Point"}
}