{
  "type": "Feature",
  "properties": {
    "gn:admin1_code":"14.0",
    "gn:admin2_code":"104.0",
    "gn:admin3_code":"10401.0",
    "gn:asciiname":"Termas del Amarillo",
    "gn:country_code":"CL",
    "gn:dem":542,
    "gn:feature_class":"P",
    "gn:feature_code":"PPL",
    "gn:name":"Termas del Amarillo",
    "gn:population":0,
    "gn:timezone":"America/Santiago",
    "iso:country":"CL",
    "wof:name":"Termas del Amarillo",
    "wof:placetype":"locality"
},
  "geometry": {"coordinates":[-72.35639,-42.88083],"type":"Point"}
}