{
  "type": "Feature",
  "properties": {
    "gn:admin1_code":"14.0",
    "gn:admin2_code":"104.0",
    "gn:admin3_code":"10401.0",
    "gn:asciiname":"Talcan",
    "gn:country_code":"CL",
    "gn:dem":11,
    "gn:feature_class":"P",
    "gn:feature_code":"PPL",
    "gn:name":"Talc\u00e1n",
    "gn:population":0,
    "gn:timezone":"America/Santiago",
    "iso:country":"CL",
    "name:spa_x_preferred":[
        "Talc\u00e1n"
    ],
    "wof:name":"Talcan",
    "wof:placetype":"locality"
},
  "geometry": {"coordinates":[-73.02452,-42.72059],"type":"Point"}
}