{
  "type": "Feature",
  "properties": {
    "gn:admin1_code":"6.0",
    "gn:admin2_code":"84.0",
    "gn:admin3_code":"8418.0",
    "gn:asciiname":"Tricao",
    "gn:country_code":"CL",
    "gn:dem":241,
    "gn:feature_class":"P",
    "gn:feature_code":"PPL",
    "gn:name":"Tricao",
    "gn:population":0,
    "gn:timezone":"America/Santiago",
    "iso:country":"CL",
    "wof:name":"Tricao",
    "wof:placetype":"locality"
},
  "geometry": {"coordinates":[-72.02419999999999,-36.81647],"type":"Point"}
}