{
  "type": "Feature",
  "properties": {
    "gn:admin1_code":"15.0",
    "gn:admin2_code":"14.0",
    "gn:admin3_code":"1405.0",
    "gn:asciiname":"El Algarrobal",
    "gn:country_code":"CL",
    "gn:dem":1661,
    "gn:feature_class":"P",
    "gn:feature_code":"PPL",
    "gn:name":"El Algarrobal",
    "gn:population":0,
    "gn:timezone":"America/Santiago",
    "iso:country":"CL",
    "name:spa_x_preferred":[
        "El Algarrobal"
    ],
    "wof:name":"El Algarrobal",
    "wof:placetype":"locality"
},
  "geometry": {"coordinates":[-69.20985,-20.71917],"type":"Point"}
}