{
  "type": "Feature",
  "properties": {
    "gn:admin1_code":"11.0",
    "gn:admin2_code":"72.0",
    "gn:admin3_code":"7201.0",
    "gn:asciiname":"Las Rosas",
    "gn:country_code":"CL",
    "gn:dem":186,
    "gn:feature_class":"P",
    "gn:feature_code":"PPL",
    "gn:name":"Las Rosas",
    "gn:population":0,
    "gn:timezone":"America/Santiago",
    "iso:country":"CL",
    "wof:name":"Las Rosas",
    "wof:placetype":"locality"
},
  "geometry": {"coordinates":[-72.34658,-36.08264000000001],"type":"Point"}
}