{
  "type": "Feature",
  "properties": {
    "gn:admin1_code":"3.0",
    "gn:admin2_code":"23.0",
    "gn:admin3_code":"2301.0",
    "gn:asciiname":"Ojeda",
    "gn:country_code":"CL",
    "gn:dem":1500,
    "gn:feature_class":"P",
    "gn:feature_code":"PPL",
    "gn:name":"Ojeda",
    "gn:population":0,
    "gn:timezone":"America/Santiago",
    "iso:country":"CL",
    "name:deu_x_preferred":[
        "Ojeda"
    ],
    "name:fra_x_preferred":[
        "Ojeda"
    ],
    "name:jpn_x_preferred":[
        "\u30aa\u30d8\u30c0"
    ],
    "name:rus_x_preferred":[
        "\u041e\u0445\u0435\u0434\u0430"
    ],
    "name:spa_x_preferred":[
        "Ojeda"
    ],
    "name:swe_x_preferred":[
        "Ojeda"
    ],
    "wof:name":"Ojeda",
    "wof:placetype":"locality"
},
  "geometry": {"coordinates":[-69.88114,-22.11578],"type":"Point"}
}