{
  "type": "Feature",
  "properties": {
    "iso:country":"CL",
    "name:ceb_x_preferred":[
        "Buin"
    ],
    "name:deu_x_preferred":[
        "Buin"
    ],
    "name:fas_x_preferred":[
        "\u0628\u0648\u0626\u06cc\u0646"
    ],
    "name:ita_x_preferred":[
        "Buin"
    ],
    "name:jpn_x_preferred":[
        "\u30d6\u30a4\u30f3"
    ],
    "name:kor_x_preferred":[
        "\ubd80\uc778"
    ],
    "name:spa_x_preferred":[
        "Buin"
    ],
    "name:swe_x_preferred":[
        "Buin"
    ],
    "qs:name":"Buin",
    "qs:name_adm0":"Chile",
    "qs:name_adm1":"Santiago",
    "qs:photos":3,
    "qs:photos_1k":1,
    "qs:photos_9k":5,
    "qs:photos_9r":7,
    "qs:photos_all":1121,
    "qs:photos_sr":1,
    "qs:placetype":"LocalAdmin",
    "qs:pop_sr":"0",
    "wd:wordcount":16,
    "wof:name":"Buin",
    "wof:placetype":"localadmin"
},
  "geometry": {"coordinates":[-70.734832,-33.731335],"type":"Point"}
}