{
  "type": "Feature",
  "properties": {
    "gn:gn_country":"CL",
    "gn:gn_fcode":"PPL",
    "gn:gn_pop":4065,
    "gn:population":4065,
    "iso:country":"CL",
    "name:ara_x_preferred":[
        "\u0634\u0627\u064a\u062a\u0646"
    ],
    "name:cat_x_preferred":[
        "Chait\u00e9n"
    ],
    "name:ces_x_preferred":[
        "Chait\u00e9n"
    ],
    "name:deu_x_preferred":[
        "Chait\u00e9n"
    ],
    "name:eng_x_preferred":[
        "Chait\u00e9n"
    ],
    "name:eus_x_preferred":[
        "Chait\u00e9n"
    ],
    "name:fas_x_preferred":[
        "\u0686\u0627\u06cc\u062a\u0646\u060c \u0634\u06cc\u0644\u06cc"
    ],
    "name:fra_x_preferred":[
        "Chait\u00e9n"
    ],
    "name:ita_x_preferred":[
        "Chait\u00e9n"
    ],
    "name:jpn_x_preferred":[
        "\u30c1\u30e3\u30a4\u30c6\u30f3"
    ],
    "name:kor_x_preferred":[
        "\ucc28\uc774\ud150"
    ],
    "name:ksh_x_preferred":[
        "Chait\u00e9n"
    ],
    "name:lit_x_preferred":[
        "\u010caitenas"
    ],
    "name:nan_x_preferred":[
        "Chait\u00e9n"
    ],
    "name:nld_x_preferred":[
        "Chait\u00e9n"
    ],
    "name:nob_x_preferred":[
        "Chait\u00e9n"
    ],
    "name:oci_x_preferred":[
        "Chait\u00e9n"
    ],
    "name:pol_x_preferred":[
        "Chait\u00e9n"
    ],
    "name:por_x_preferred":[
        "Chait\u00e9n"
    ],
    "name:ron_x_preferred":[
        "Chait\u00e9n"
    ],
    "name:rus_x_preferred":[
        "\u0427\u0430\u0439\u0442\u0435\u043d"
    ],
    "name:spa_x_preferred":[
        "Chait\u00e9n"
    ],
    "name:swe_x_preferred":[
        "Chait\u00e9n"
    ],
    "name:ukr_x_preferred":[
        "\u0427\u0430\u0439\u0442\u0435\u043d"
    ],
    "name:war_x_preferred":[
        "Chait\u00e9n"
    ],
    "name:zho_x_preferred":[
        "\u67f4\u6ed5"
    ],
    "qs_pg:aaroncc":"CL",
    "qs_pg:gn_country":"CL",
    "qs_pg:gn_fcode":"PPL",
    "qs_pg:gn_pop":4065,
    "qs_pg:name":"Chait\u00e9n",
    "qs_pg:name_adm0":"Chile",
    "qs_pg:name_adm1":"Los Lagos",
    "qs_pg:photos":642,
    "qs_pg:photos_1k":130,
    "qs_pg:photos_9k":3,
    "qs_pg:photos_9r":5,
    "qs_pg:photos_all":642,
    "qs_pg:photos_sr":8,
    "qs_pg:pop_sr":6,
    "qs_pg:qs_pg_placetype":"locality",
    "qs_pg:qs_pg_placetype_gp":"Town",
    "qs_pg:woe_adm0":23424782,
    "woe:adm0_id":23424782,
    "woe:name_adm0":"Chile",
    "woe:name_adm1":"Los Lagos",
    "woe:placetype":"Town",
    "wof:name":"Chait\u00e9n",
    "wof:placetype":"locality",
    "wof:population":4065
},
  "geometry": {"coordinates":[-72.70632000000001,-42.91596],"type":"Point"}
}