{
  "type": "Feature",
  "properties": {
    "gn:admin1_code":"14.0",
    "gn:admin2_code":"102.0",
    "gn:admin3_code":"10209.0",
    "gn:asciiname":"Aucar",
    "gn:country_code":"CL",
    "gn:dem":34,
    "gn:feature_class":"P",
    "gn:feature_code":"PPL",
    "gn:name":"Aucar",
    "gn:population":0,
    "gn:timezone":"America/Santiago",
    "iso:country":"CL",
    "name:und_x_variant":[
        "Escuela Aucar",
        "Aucar"
    ],
    "wof:name":"Aucar",
    "wof:placetype":"locality"
},
  "geometry": {"coordinates":[-73.48737,-42.16689],"type":"Point"}
}