{
  "type": "Feature",
  "properties": {
    "gn:admin1_code":"12.0",
    "gn:admin2_code":"132.0",
    "gn:admin3_code":"13203.0",
    "gn:asciiname":"El Melocoton",
    "gn:country_code":"CL",
    "gn:dem":1025,
    "gn:feature_class":"P",
    "gn:feature_code":"PPL",
    "gn:name":"El Melocot\u00f3n",
    "gn:population":0,
    "gn:timezone":"America/Santiago",
    "iso:country":"CL",
    "name:und_x_variant":[
        "El Melocot\u00f3n",
        "Melocot\u00f3n"
    ],
    "wof:name":"El Melocoton",
    "wof:placetype":"locality"
},
  "geometry": {"coordinates":[-70.33476999999999,-33.69471],"type":"Point"}
}