{
  "type": "Feature",
  "properties": {
    "gn:admin1_code":"1.0",
    "gn:admin2_code":"55.0",
    "gn:admin3_code":"5506.0",
    "gn:asciiname":"Artificio",
    "gn:country_code":"CL",
    "gn:dem":217,
    "gn:feature_class":"P",
    "gn:feature_code":"PPL",
    "gn:name":"Artificio",
    "gn:population":0,
    "gn:timezone":"America/Santiago",
    "iso:country":"CL",
    "wof:name":"Artificio",
    "wof:placetype":"locality"
},
  "geometry": {"coordinates":[-71.19396999999999,-32.75578],"type":"Point"}
}