{
  "type": "Feature",
  "properties": {
    "gn:admin1_code":"14.0",
    "gn:admin2_code":"104.0",
    "gn:admin3_code":"10403.0",
    "gn:asciiname":"Rolecha",
    "gn:country_code":"CL",
    "gn:dem":8,
    "gn:feature_class":"P",
    "gn:feature_code":"PPL",
    "gn:name":"Rolecha",
    "gn:population":0,
    "gn:timezone":"America/Santiago",
    "iso:country":"CL",
    "name:und_x_variant":[
        "Ensenada Rolecha",
        "Rolecha"
    ],
    "wof:name":"Rolecha",
    "wof:placetype":"locality"
},
  "geometry": {"coordinates":[-72.84317,-41.92099],"type":"Point"}
}