{
  "type": "Feature",
  "properties": {
    "gn:admin1_code":"15.0",
    "gn:admin2_code":"14.0",
    "gn:admin3_code":"1403.0",
    "gn:asciiname":"Challuma",
    "gn:country_code":"CL",
    "gn:dem":3683,
    "gn:feature_class":"P",
    "gn:feature_code":"PPL",
    "gn:name":"Challuma",
    "gn:population":0,
    "gn:timezone":"America/Santiago",
    "iso:country":"CL",
    "name:spa_x_preferred":[
        "Challuma"
    ],
    "name:zho_x_preferred":[
        "\u67e5\u67f3\u99ac\u5c71"
    ],
    "wof:name":"Challuma",
    "wof:placetype":"locality"
},
  "geometry": {"coordinates":[-68.4851,-19.41514],"type":"Point"}
}