{
  "type": "Feature",
  "properties": {
    "gn:admin1_code":"17.0",
    "gn:admin2_code":"141.0",
    "gn:asciiname":"Maiquillahue",
    "gn:country_code":"CL",
    "gn:dem":22,
    "gn:feature_class":"P",
    "gn:feature_code":"PPL",
    "gn:name":"Maiquillahue",
    "gn:population":0,
    "gn:timezone":"America/Santiago",
    "iso:country":"CL",
    "wof:name":"Maiquillahue",
    "wof:placetype":"locality"
},
  "geometry": {"coordinates":[-73.25237,-39.46694],"type":"Point"}
}