{
  "type": "Feature",
  "properties": {
    "gn:admin1_code":"7.0",
    "gn:admin2_code":"43.0",
    "gn:admin3_code":"4301.0",
    "gn:asciiname":"Camarico",
    "gn:country_code":"CL",
    "gn:dem":237,
    "gn:feature_class":"P",
    "gn:feature_code":"PPL",
    "gn:name":"Camarico",
    "gn:population":0,
    "gn:timezone":"America/Santiago",
    "iso:country":"CL",
    "wof:name":"Camarico",
    "wof:placetype":"locality"
},
  "geometry": {"coordinates":[-71.33618,-30.73878],"type":"Point"}
}