{
  "type": "Feature",
  "properties": {
    "gn:admin1_code":"8.0",
    "gn:admin2_code":"62.0",
    "gn:admin3_code":"6201.0",
    "gn:asciiname":"El Maqui",
    "gn:country_code":"CL",
    "gn:dem":26,
    "gn:feature_class":"P",
    "gn:feature_code":"PPL",
    "gn:name":"El Maqui",
    "gn:population":0,
    "gn:timezone":"America/Santiago",
    "iso:country":"CL",
    "name:fas_x_preferred":[
        "\u0627\u0644 \u0645\u0627\u06a9\u06cc"
    ],
    "wof:name":"El Maqui",
    "wof:placetype":"locality"
},
  "geometry": {"coordinates":[-71.93048,-34.53954],"type":"Point"}
}