{
  "type": "Feature",
  "properties": {
    "gn:admin1_code":"5.0",
    "gn:admin2_code":"33.0",
    "gn:admin3_code":"3301.0",
    "gn:asciiname":"Vallenar",
    "gn:country_code":"CL",
    "gn:dem":1990,
    "gn:feature_class":"P",
    "gn:feature_code":"PPLA3",
    "gn:name":"Vallenar",
    "gn:population":0,
    "gn:timezone":"America/Santiago",
    "iso:country":"CL",
    "name:aka_x_preferred":[
        "Vallenar"
    ],
    "name:ara_x_preferred":[
        "\u0641\u0627\u0644\u064a\u0646\u0627\u0631"
    ],
    "name:bak_x_preferred":[
        "\u0412\u0430\u043b\u0435\u043d\u0430\u0440"
    ],
    "name:ceb_x_preferred":[
        "Vallenar"
    ],
    "name:deu_x_preferred":[
        "Vallenar"
    ],
    "name:ell_x_preferred":[
        "\u0392\u03b1\u03b3\u03b9\u03b5\u03bd\u03ac\u03c1"
    ],
    "name:eus_x_preferred":[
        "Vallenar"
    ],
    "name:fas_x_preferred":[
        "\u0648\u0627\u06cc\u0646\u0627\u0631"
    ],
    "name:fra_x_preferred":[
        "Vallenar"
    ],
    "name:ita_x_preferred":[
        "Vallenar"
    ],
    "name:kor_x_preferred":[
        "\ubc14\uc608\ub098\ub974"
    ],
    "name:lit_x_preferred":[
        "Valjenaras"
    ],
    "name:nld_x_preferred":[
        "Vallenar"
    ],
    "name:pol_x_preferred":[
        "Vallenar"
    ],
    "name:por_x_preferred":[
        "Vallenar"
    ],
    "name:ron_x_preferred":[
        "Vallenar"
    ],
    "name:rus_x_preferred":[
        "\u0412\u0430\u043b\u044c\u0435\u043d\u0430\u0440"
    ],
    "name:spa_x_preferred":[
        "Vallenar"
    ],
    "name:srp_x_preferred":[
        "\u0412\u0430\u0459\u0435\u043d\u0430\u0440"
    ],
    "name:swe_x_preferred":[
        "Vallenar"
    ],
    "name:war_x_preferred":[
        "Vallenar"
    ],
    "name:zho_x_preferred":[
        "\u5df4\u8036\u7d0d\u723e"
    ],
    "wof:name":"Vallenar",
    "wof:placetype":"locality"
},
  "geometry": {"coordinates":[-70.25551,-28.51576],"type":"Point"}
}