{
  "type": "Feature",
  "properties": {
    "gn:admin1_code":"17.0",
    "gn:admin2_code":"142.0",
    "gn:admin3_code":"14202.0",
    "gn:asciiname":"Caunao",
    "gn:country_code":"CL",
    "gn:dem":160,
    "gn:feature_class":"P",
    "gn:feature_code":"PPL",
    "gn:name":"Caunao",
    "gn:population":0,
    "gn:timezone":"America/Santiago",
    "iso:country":"CL",
    "name:und_x_variant":[
        "Caunahue",
        "Caunao"
    ],
    "wof:name":"Caunao",
    "wof:placetype":"locality"
},
  "geometry": {"coordinates":[-72.24766,-40.13944],"type":"Point"}
}