{
  "type": "Feature",
  "properties": {
    "gn:admin1_code":"8.0",
    "gn:admin2_code":"62.0",
    "gn:admin3_code":"6205.0",
    "gn:asciiname":"Los Manzanos",
    "gn:country_code":"CL",
    "gn:dem":284,
    "gn:feature_class":"P",
    "gn:feature_code":"PPL",
    "gn:name":"Los Manzanos",
    "gn:population":0,
    "gn:timezone":"America/Santiago",
    "iso:country":"CL",
    "name:und_x_variant":[
        "El Manzano",
        "Los Manzanos"
    ],
    "wof:name":"Los Manzanos",
    "wof:placetype":"locality"
},
  "geometry": {"coordinates":[-71.8309,-34.08953],"type":"Point"}
}