{
  "type": "Feature",
  "properties": {
    "gn:admin1_code":"1.0",
    "gn:admin2_code":"56.0",
    "gn:admin3_code":"5603.0",
    "gn:asciiname":"Lo Zarate",
    "gn:country_code":"CL",
    "gn:dem":46,
    "gn:feature_class":"P",
    "gn:feature_code":"PPL",
    "gn:name":"Lo Z\u00e1rate",
    "gn:population":0,
    "gn:timezone":"America/Santiago",
    "iso:country":"CL",
    "wof:name":"Lo Zarate",
    "wof:placetype":"locality"
},
  "geometry": {"coordinates":[-71.52894000000001,-33.53368],"type":"Point"}
}