{
  "type": "Feature",
  "properties": {
    "gn:admin1_code":"8.0",
    "gn:admin2_code":"63.0",
    "gn:admin3_code":"6303.0",
    "gn:asciiname":"Convento El Molino",
    "gn:country_code":"CL",
    "gn:dem":250,
    "gn:feature_class":"P",
    "gn:feature_code":"PPL",
    "gn:name":"Convento El Molino",
    "gn:population":0,
    "gn:timezone":"America/Santiago",
    "iso:country":"CL",
    "name:und_x_variant":[
        "El Molino",
        "Convento",
        "Convento El Molino"
    ],
    "wof:name":"Convento El Molino",
    "wof:placetype":"locality"
},
  "geometry": {"coordinates":[-71.13202,-34.76284],"type":"Point"}
}