{
  "type": "Feature",
  "properties": {
    "gn:admin1_code":"8.0",
    "gn:admin2_code":"62.0",
    "gn:admin3_code":"6204.0",
    "gn:asciiname":"La Quebrada",
    "gn:country_code":"CL",
    "gn:dem":168,
    "gn:feature_class":"P",
    "gn:feature_code":"PPL",
    "gn:name":"La Quebrada",
    "gn:population":0,
    "gn:timezone":"America/Santiago",
    "iso:country":"CL",
    "name:ceb_x_preferred":[
        "La Quebrada"
    ],
    "name:swe_x_preferred":[
        "La Quebrada"
    ],
    "wof:name":"La Quebrada",
    "wof:placetype":"locality"
},
  "geometry": {"coordinates":[-71.70389,-34.47638],"type":"Point"}
}