{
  "type": "Feature",
  "properties": {
    "gn:admin1_code":"15.0",
    "gn:admin2_code":"14.0",
    "gn:admin3_code":"1401.0",
    "gn:asciiname":"Guatacondo",
    "gn:country_code":"CL",
    "gn:dem":2284,
    "gn:feature_class":"P",
    "gn:feature_code":"PPL",
    "gn:name":"Guatacondo",
    "gn:population":0,
    "gn:timezone":"America/Santiago",
    "iso:country":"CL",
    "name:und_x_variant":[
        "Huatacondo",
        "Guatacondo"
    ],
    "wof:name":"Guatacondo",
    "wof:placetype":"locality"
},
  "geometry": {"coordinates":[-69.05570999999999,-20.92755],"type":"Point"}
}