{
  "type": "Feature",
  "properties": {
    "iso:country":"CL",
    "name:spa_x_colloquial":[
        "Baron"
    ],
    "name:spa_x_preferred":[
        "Bar\u00f3n",
        "Jorge Bar\u00f3n"
    ],
    "name:spa_x_variant":[
        "El Baron"
    ],
    "name:unk_x_variant":[
        "El Baron",
        "Bar\u00f3n"
    ],
    "qs:gn_adm0_cc":"CL",
    "qs:gn_fcode":"PPLX",
    "qs:gn_local":0,
    "qs:gn_namadm1":"01",
    "qs:gn_name":"Bar\u00f3n",
    "qs:local_max":14219,
    "qs:local_sum":41999,
    "qs:localhoods":9,
    "qs:name":"Bar\u00f3n",
    "qs:name_adm0":"Chile",
    "qs:name_adm1":"Valpara\u00edso",
    "qs:name_adm2":"Valparaiso",
    "qs:name_lau":"Valparaiso",
    "qs:name_local":"Valpara\u00edso",
    "qs:photo_max":1331,
    "qs:photo_sum":8632,
    "qs:placetype":"Suburb",
    "qs:quad_count":133,
    "qs:woe_adm0":23424782,
    "qs:woe_adm1":2345018,
    "qs:woe_adm2":26794022,
    "qs:woe_lau":26794357,
    "qs:woe_local":349861,
    "qs:woe_ver":"7.10.0",
    "wof:lang":[
        "spa"
    ],
    "wof:name":"Bar\u00f3n",
    "wof:placetype":"neighbourhood"
},
  "geometry": {"coordinates":[-71.615565,-33.044833],"type":"Point"}
}