{
  "type": "Feature",
  "properties": {
    "gn:admin1_code":"5.0",
    "gn:admin2_code":"32.0",
    "gn:admin3_code":"3202.0",
    "gn:asciiname":"Mineral El Salvador",
    "gn:country_code":"CL",
    "gn:dem":2313,
    "gn:feature_class":"P",
    "gn:feature_code":"PPL",
    "gn:name":"Mineral El Salvador",
    "gn:population":0,
    "gn:timezone":"America/Santiago",
    "iso:country":"CL",
    "wof:name":"Mineral El Salvador",
    "wof:placetype":"locality"
},
  "geometry": {"coordinates":[-69.59999999999999,-26.21667],"type":"Point"}
}