{
  "type": "Feature",
  "properties": {
    "gn:admin1_code":"5.0",
    "gn:admin2_code":"31.0",
    "gn:asciiname":"Cerro Iman",
    "gn:country_code":"CL",
    "gn:dem":432,
    "gn:feature_class":"P",
    "gn:feature_code":"PPL",
    "gn:name":"Cerro Im\u00e1n",
    "gn:population":0,
    "gn:timezone":"America/Santiago",
    "iso:country":"CL",
    "name:spa_x_preferred":[
        "Cerro Im\u00e1n"
    ],
    "wof:name":"Cerro Iman",
    "wof:placetype":"locality"
},
  "geometry": {"coordinates":[-70.38682,-27.25628],"type":"Point"}
}