{
  "type": "Feature",
  "properties": {
    "gn:country":"CL",
    "gn:fcode":"PPL",
    "gn:pop":0,
    "iso:country":"CL",
    "qs:name":"Puerto Puyuguapi",
    "qs:name_adm0":"Chile",
    "qs:name_adm1":"Aisen del General Carlos Ibanez Del Campo",
    "qs:photos":107,
    "qs:photos_1k":22,
    "qs:photos_9k":1,
    "qs:photos_9r":3,
    "qs:photos_all":107,
    "qs:photos_sr":3,
    "qs:placetype":"Town",
    "qs:pop_sr":"5",
    "wof:name":"Puerto Puyuguapi",
    "wof:placetype":"locality",
    "wof:population":0
},
  "geometry": {"coordinates":[-72.55859,-44.32488],"type":"Point"}
}