{
  "type": "Feature",
  "properties": {
    "gn:admin1_code":"15.0",
    "gn:admin2_code":"14.0",
    "gn:admin3_code":"1403.0",
    "gn:asciiname":"Arabilla",
    "gn:country_code":"CL",
    "gn:dem":3996,
    "gn:feature_class":"P",
    "gn:feature_code":"PPL",
    "gn:name":"Arabilla",
    "gn:population":0,
    "gn:timezone":"America/Santiago",
    "iso:country":"CL",
    "name:und_x_variant":[
        "Aravilla",
        "Arabilla"
    ],
    "wof:name":"Arabilla",
    "wof:placetype":"locality"
},
  "geometry": {"coordinates":[-68.8601,-19.22087],"type":"Point"}
}