{
  "type": "Feature",
  "properties": {
    "gn:admin1_code":"11.0",
    "gn:admin2_code":"73.0",
    "gn:admin3_code":"7307.0",
    "gn:asciiname":"San Javier",
    "gn:country_code":"CL",
    "gn:dem":125,
    "gn:feature_class":"P",
    "gn:feature_code":"PPL",
    "gn:name":"San Javier",
    "gn:population":0,
    "gn:timezone":"America/Santiago",
    "iso:country":"CL",
    "name:ceb_x_preferred":[
        "San Javier"
    ],
    "name:deu_x_preferred":[
        "San Javier"
    ],
    "name:fra_x_preferred":[
        "San Javier"
    ],
    "name:ita_x_preferred":[
        "San Javier"
    ],
    "name:mlg_x_preferred":[
        "San Javier"
    ],
    "name:nld_x_preferred":[
        "San Javier"
    ],
    "name:pol_x_preferred":[
        "San Javier"
    ],
    "name:por_x_preferred":[
        "San Javier"
    ],
    "name:ron_x_preferred":[
        "San Javier"
    ],
    "name:rus_x_preferred":[
        "\u0421\u0430\u043d-\u0425\u0430\u0432\u044c\u0435\u0440"
    ],
    "name:sco_x_preferred":[
        "San Javier"
    ],
    "name:spa_x_preferred":[
        "San Javier"
    ],
    "name:swe_x_preferred":[
        "San Javier"
    ],
    "wof:name":"San Javier",
    "wof:placetype":"locality"
},
  "geometry": {"coordinates":[-71.47780999999998,-35.05247],"type":"Point"}
}