{
  "type": "Feature",
  "properties": {
    "gn:admin1_code":"14.0",
    "gn:admin2_code":"101.0",
    "gn:asciiname":"Colegual",
    "gn:country_code":"CL",
    "gn:dem":193,
    "gn:feature_class":"P",
    "gn:feature_code":"PPL",
    "gn:name":"Colegual",
    "gn:population":0,
    "gn:timezone":"America/Santiago",
    "iso:country":"CL",
    "name:spa_x_preferred":[
        "Colegual"
    ],
    "wof:name":"Colegual",
    "wof:placetype":"locality"
},
  "geometry": {"coordinates":[-73.22154,-41.22276],"type":"Point"}
}