{
  "type": "Feature",
  "properties": {
    "gn:admin1_code":"16.0",
    "gn:admin2_code":"152.0",
    "gn:admin3_code":"15202.0",
    "gn:asciiname":"Pamputa",
    "gn:country_code":"CL",
    "gn:dem":4111,
    "gn:feature_class":"P",
    "gn:feature_code":"PPL",
    "gn:name":"Pamputa",
    "gn:population":0,
    "gn:timezone":"America/Santiago",
    "iso:country":"CL",
    "name:und_x_variant":[
        "Pamputa Uyunasi",
        "Pamputa"
    ],
    "wof:name":"Pamputa",
    "wof:placetype":"locality"
},
  "geometry": {"coordinates":[-69.71493000000001,-17.75261],"type":"Point"}
}