{
  "type": "Feature",
  "properties": {
    "gn:admin1_code":"6.0",
    "gn:admin2_code":"81.0",
    "gn:admin3_code":"8109.0",
    "gn:asciiname":"Colico",
    "gn:country_code":"CL",
    "gn:dem":126,
    "gn:feature_class":"P",
    "gn:feature_code":"PPL",
    "gn:name":"Colico",
    "gn:population":0,
    "gn:timezone":"America/Santiago",
    "iso:country":"CL",
    "wof:name":"Colico",
    "wof:placetype":"locality"
},
  "geometry": {"coordinates":[-72.87279000000002,-37.27573],"type":"Point"}
}