{
  "type": "Feature",
  "properties": {
    "gn:admin1_code":"7.0",
    "gn:admin2_code":"41.0",
    "gn:admin3_code":"4106.0",
    "gn:asciiname":"La Troya",
    "gn:country_code":"CL",
    "gn:dem":3176,
    "gn:feature_class":"P",
    "gn:feature_code":"PPL",
    "gn:name":"La Troya",
    "gn:population":0,
    "gn:timezone":"America/Santiago",
    "iso:country":"CL",
    "name:und_x_variant":[
        "La Toroya"
    ],
    "wof:name":"La Troya",
    "wof:placetype":"locality"
},
  "geometry": {"coordinates":[-70.03413,-29.94195],"type":"Point"}
}