{
  "type": "Feature",
  "properties": {
    "gn:admin1_code":"11.0",
    "gn:admin2_code":"71.0",
    "gn:admin3_code":"7102.0",
    "gn:asciiname":"Trapiche",
    "gn:country_code":"CL",
    "gn:dem":53,
    "gn:feature_class":"P",
    "gn:feature_code":"PPL",
    "gn:name":"Trapiche",
    "gn:population":0,
    "gn:timezone":"America/Santiago",
    "iso:country":"CL",
    "name:cat_x_preferred":[
        "Trapig"
    ],
    "name:fra_x_preferred":[
        "Trapiche"
    ],
    "name:por_x_preferred":[
        "Trapiche"
    ],
    "name:spa_x_preferred":[
        "Trapiche"
    ],
    "wof:name":"Trapiche",
    "wof:placetype":"locality"
},
  "geometry": {"coordinates":[-72.05792,-35.29379],"type":"Point"}
}