{
  "type": "Feature",
  "properties": {
    "gn:admin1_code":"12.0",
    "gn:admin2_code":"134.0",
    "gn:admin3_code":"13402.0",
    "gn:asciiname":"Viluco",
    "gn:country_code":"CL",
    "gn:dem":410,
    "gn:feature_class":"P",
    "gn:feature_code":"PPL",
    "gn:name":"Viluco",
    "gn:population":0,
    "gn:timezone":"America/Santiago",
    "iso:country":"CL",
    "wof:name":"Viluco",
    "wof:placetype":"locality"
},
  "geometry": {"coordinates":[-70.79527,-33.77825],"type":"Point"}
}