{
  "type": "Feature",
  "properties": {
    "gn:admin1_code":"1.0",
    "gn:admin2_code":"53.0",
    "gn:admin3_code":"5303.0",
    "gn:asciiname":"Los Ranchillos",
    "gn:country_code":"CL",
    "gn:dem":1271,
    "gn:feature_class":"P",
    "gn:feature_code":"PPL",
    "gn:name":"Los Ranchillos",
    "gn:population":0,
    "gn:timezone":"America/Santiago",
    "iso:country":"CL",
    "wof:name":"Los Ranchillos",
    "wof:placetype":"locality"
},
  "geometry": {"coordinates":[-70.70786,-32.93668],"type":"Point"}
}