{
  "type": "Feature",
  "properties": {
    "gn:admin1_code":"4.0",
    "gn:admin2_code":"92.0",
    "gn:admin3_code":"9205.0",
    "gn:asciiname":"Icalma",
    "gn:country_code":"CL",
    "gn:dem":1155,
    "gn:feature_class":"P",
    "gn:feature_code":"PPL",
    "gn:name":"Icalma",
    "gn:population":0,
    "gn:timezone":"America/Santiago",
    "iso:country":"CL",
    "name:spa_x_preferred":[
        "Icalma"
    ],
    "wof:name":"Icalma",
    "wof:placetype":"locality"
},
  "geometry": {"coordinates":[-71.28437,-38.81117],"type":"Point"}
}