{
  "type": "Feature",
  "properties": {
    "gn:admin1_code":"11.0",
    "gn:admin2_code":"72.0",
    "gn:admin3_code":"7201.0",
    "gn:asciiname":"El Cielo",
    "gn:country_code":"CL",
    "gn:dem":194,
    "gn:feature_class":"P",
    "gn:feature_code":"PPL",
    "gn:name":"El Cielo",
    "gn:population":0,
    "gn:timezone":"America/Santiago",
    "iso:country":"CL",
    "name:und_x_variant":[
        "Cielo",
        "El Cielo"
    ],
    "wof:name":"El Cielo",
    "wof:placetype":"locality"
},
  "geometry": {"coordinates":[-72.31184,-35.91337],"type":"Point"}
}