{
  "type": "Feature",
  "properties": {
    "gn:admin1_code":"14.0",
    "gn:admin2_code":"102.0",
    "gn:asciiname":"Villa Quenac",
    "gn:country_code":"CL",
    "gn:dem":-9999,
    "gn:feature_class":"P",
    "gn:feature_code":"PPL",
    "gn:name":"Villa Quenac",
    "gn:population":0,
    "gn:timezone":"America/Santiago",
    "iso:country":"CL",
    "wof:name":"Villa Quenac",
    "wof:placetype":"locality"
},
  "geometry": {"coordinates":[-73.32639,-42.44972],"type":"Point"}
}