{
  "type": "Feature",
  "properties": {
    "gn:admin1_code":"5.0",
    "gn:admin2_code":"32.0",
    "gn:admin3_code":"3202.0",
    "gn:asciiname":"Corrales del Juncalito",
    "gn:country_code":"CL",
    "gn:dem":3984,
    "gn:feature_class":"P",
    "gn:feature_code":"PPL",
    "gn:name":"Corrales del Juncalito",
    "gn:population":0,
    "gn:timezone":"America/Santiago",
    "iso:country":"CL",
    "wof:name":"Corrales del Juncalito",
    "wof:placetype":"locality"
},
  "geometry": {"coordinates":[-68.86493,-26.51051],"type":"Point"}
}