{
  "type": "Feature",
  "properties": {
    "gn:admin1_code":"10.0",
    "gn:admin2_code":"124.0",
    "gn:asciiname":"Dorotea",
    "gn:country_code":"CL",
    "gn:dem":400,
    "gn:feature_class":"P",
    "gn:feature_code":"PPL",
    "gn:name":"Dorotea",
    "gn:population":0,
    "gn:timezone":"America/Punta_Arenas",
    "iso:country":"CL",
    "name:bul_x_preferred":[
        "\u0414\u0443\u0440\u0443\u0442\u0435\u0430"
    ],
    "name:ceb_x_preferred":[
        "Dorotea"
    ],
    "name:dan_x_preferred":[
        "Dorotea"
    ],
    "name:deu_x_preferred":[
        "Dorotea"
    ],
    "name:est_x_preferred":[
        "Dorotea"
    ],
    "name:fao_x_preferred":[
        "Dorotea"
    ],
    "name:fas_x_preferred":[
        "\u062f\u0648\u0631\u0648\u062a\u06cc\u0627"
    ],
    "name:fin_x_preferred":[
        "Dorotea"
    ],
    "name:fra_x_preferred":[
        "Dorotea"
    ],
    "name:isl_x_preferred":[
        "Dorotea"
    ],
    "name:ita_x_preferred":[
        "Dorotea"
    ],
    "name:kor_x_preferred":[
        "\ub3c4\ub85c\ud14c\uc544"
    ],
    "name:nld_x_preferred":[
        "Dorotea"
    ],
    "name:nno_x_preferred":[
        "Tettstaden Dorotea"
    ],
    "name:nor_x_preferred":[
        "Dorotea"
    ],
    "name:por_x_preferred":[
        "Dorotea"
    ],
    "name:ron_x_preferred":[
        "Dorotea"
    ],
    "name:spa_x_preferred":[
        "Dorotea"
    ],
    "name:swe_x_preferred":[
        "Dorotea"
    ],
    "name:ukr_x_preferred":[
        "\u0414\u043e\u0440\u043e\u0442\u0435\u0430"
    ],
    "name:und_x_variant":[
        "Mina Dorotea",
        "Cerro Dorotea"
    ],
    "wof:name":"Dorotea",
    "wof:placetype":"locality"
},
  "geometry": {"coordinates":[-72.33329000000001,-51.61334],"type":"Point"}
}