{
  "type": "Feature",
  "properties": {
    "gn:admin1_code":"10.0",
    "gn:admin2_code":"124.0",
    "gn:asciiname":"Dorotea",
    "gn:country_code":"CL",
    "gn:dem":400,
    "gn:feature_class":"P",
    "gn:feature_code":"PPL",
    "gn:name":"Dorotea",
    "gn:population":0,
    "gn:timezone":"America/Punta_Arenas",
    "iso:country":"CL",
    "name:spa_x_preferred":[
        "Dorotea"
    ],
    "name:und_x_variant":[
        "Mina Dorotea",
        "Cerro Dorotea"
    ],
    "wof:name":"Dorotea",
    "wof:placetype":"locality"
},
  "geometry": {"coordinates":[-72.33329000000001,-51.61334],"type":"Point"}
}