{
  "type": "Feature",
  "properties": {
    "gn:admin1_code":"15.0",
    "gn:admin2_code":"11.0",
    "gn:asciiname":"Salina Pampa Nevada",
    "gn:country_code":"CL",
    "gn:dem":673,
    "gn:feature_class":"P",
    "gn:feature_code":"PPL",
    "gn:name":"Salina Pampa Nevada",
    "gn:population":0,
    "gn:timezone":"America/Santiago",
    "iso:country":"CL",
    "name:spa_x_preferred":[
        "Salina Pampa Nevada"
    ],
    "wof:name":"Salina Pampa Nevada",
    "wof:placetype":"locality"
},
  "geometry": {"coordinates":[-70.01608,-20.93586],"type":"Point"}
}