{
  "type": "Feature",
  "properties": {
    "gn:admin1_code":"6.0",
    "gn:admin2_code":"81.0",
    "gn:admin3_code":"8103.0",
    "gn:asciiname":"Fresia",
    "gn:country_code":"CL",
    "gn:dem":248,
    "gn:feature_class":"P",
    "gn:feature_code":"PPL",
    "gn:name":"Fresia",
    "gn:population":0,
    "gn:timezone":"America/Santiago",
    "iso:country":"CL",
    "name:und_x_variant":[
        "Paradero Fresia",
        "Fresia"
    ],
    "wof:name":"Fresia",
    "wof:placetype":"locality"
},
  "geometry": {"coordinates":[-73.01536,-36.8868],"type":"Point"}
}