{
  "type": "Feature",
  "properties": {
    "gn:admin1_code":"7.0",
    "gn:admin2_code":"43.0",
    "gn:admin3_code":"4305.0",
    "gn:asciiname":"El Puerto",
    "gn:country_code":"CL",
    "gn:dem":815,
    "gn:feature_class":"P",
    "gn:feature_code":"PPL",
    "gn:name":"El Puerto",
    "gn:population":0,
    "gn:timezone":"America/Santiago",
    "iso:country":"CL",
    "name:ast_x_preferred":[
        "El Puertu"
    ],
    "name:ceb_x_preferred":[
        "El Puerto"
    ],
    "name:deu_x_preferred":[
        "El Puerto"
    ],
    "name:spa_x_preferred":[
        "El Puerto"
    ],
    "name:srp_x_preferred":[
        "\u0415\u043b \u041f\u0443\u0435\u0440\u0442\u043e"
    ],
    "name:swe_x_preferred":[
        "El Puerto"
    ],
    "wof:name":"El Puerto",
    "wof:placetype":"locality"
},
  "geometry": {"coordinates":[-70.81910000000001,-30.37928],"type":"Point"}
}