{
  "type": "Feature",
  "properties": {
    "gn:admin1_code":"5.0",
    "gn:admin2_code":"31.0",
    "gn:admin3_code":"3101.0",
    "gn:asciiname":"Carrizo",
    "gn:country_code":"CL",
    "gn:dem":1719,
    "gn:feature_class":"P",
    "gn:feature_code":"PPL",
    "gn:name":"Carrizo",
    "gn:population":0,
    "gn:timezone":"America/Santiago",
    "iso:country":"CL",
    "name:ceb_x_preferred":[
        "Carrizo"
    ],
    "name:deu_x_preferred":[
        "Carrizo"
    ],
    "name:glg_x_preferred":[
        "Carrizo"
    ],
    "name:ita_x_preferred":[
        "Carrizo"
    ],
    "name:jpn_x_preferred":[
        "\u30ab\u30ea\u30fc\u30bd"
    ],
    "name:nld_x_preferred":[
        "Carrizo"
    ],
    "name:por_x_preferred":[
        "Carrizo"
    ],
    "name:spa_x_preferred":[
        "Carrizo"
    ],
    "name:swe_x_preferred":[
        "Carrizo"
    ],
    "wof:name":"Carrizo",
    "wof:placetype":"locality"
},
  "geometry": {"coordinates":[-70.16540000000001,-28.12294],"type":"Point"}
}