{
  "type": "Feature",
  "properties": {
    "gn:admin1_code":"15.0",
    "gn:admin2_code":"14.0",
    "gn:admin3_code":"1403.0",
    "gn:asciiname":"Casiri",
    "gn:country_code":"CL",
    "gn:dem":3736,
    "gn:feature_class":"P",
    "gn:feature_code":"PPL",
    "gn:name":"Casiri",
    "gn:population":0,
    "gn:timezone":"America/Santiago",
    "iso:country":"CL",
    "name:spa_x_preferred":[
        "Casiri"
    ],
    "wof:name":"Casiri",
    "wof:placetype":"locality"
},
  "geometry": {"coordinates":[-68.63394,-19.39254],"type":"Point"}
}