{
  "type": "Feature",
  "properties": {
    "gn:admin1_code":"4.0",
    "gn:admin2_code":"91.0",
    "gn:admin3_code":"9102.0",
    "gn:asciiname":"Huenaliben",
    "gn:country_code":"CL",
    "gn:dem":225,
    "gn:feature_class":"P",
    "gn:feature_code":"PPL",
    "gn:name":"Huenaliben",
    "gn:population":0,
    "gn:timezone":"America/Santiago",
    "iso:country":"CL",
    "name:und_x_variant":[
        "Hue\u00f1alihuen",
        "Huenaliben"
    ],
    "wof:name":"Huenaliben",
    "wof:placetype":"locality"
},
  "geometry": {"coordinates":[-73.48166999999999,-38.50739],"type":"Point"}
}