{
  "type": "Feature",
  "properties": {
    "gn:admin1_code":"6.0",
    "gn:admin2_code":"84.0",
    "gn:admin3_code":"8401.0",
    "gn:asciiname":"Las Minas",
    "gn:country_code":"CL",
    "gn:dem":229,
    "gn:feature_class":"P",
    "gn:feature_code":"PPL",
    "gn:name":"Las Minas",
    "gn:population":0,
    "gn:timezone":"America/Santiago",
    "iso:country":"CL",
    "name:ceb_x_preferred":[
        "Las Minas"
    ],
    "name:deu_x_preferred":[
        "Las Minas"
    ],
    "name:spa_x_preferred":[
        "Las Minas"
    ],
    "name:swe_x_preferred":[
        "Las Minas"
    ],
    "wof:name":"Las Minas",
    "wof:placetype":"locality"
},
  "geometry": {"coordinates":[-72.0089,-36.73559],"type":"Point"}
}