{
  "type": "Feature",
  "properties": {
    "iso:country":"CL",
    "qs:name":"Corral",
    "qs:name_adm0":"Chile",
    "qs:name_adm1":"Los Rios",
    "qs:photos":14,
    "qs:photos_1k":3,
    "qs:photos_9k":5,
    "qs:photos_9r":7,
    "qs:photos_all":1182,
    "qs:photos_sr":1,
    "qs:placetype":"LocalAdmin",
    "qs:pop_sr":"0",
    "wof:name":"Corral",
    "wof:placetype":"localadmin"
},
  "geometry": {"coordinates":[-73.41959900000001,-39.882338],"type":"Point"}
}