{
  "type": "Feature",
  "properties": {
    "gn:admin1_code":"8.0",
    "gn:admin2_code":"62.0",
    "gn:admin3_code":"6204.0",
    "gn:asciiname":"Tunel del Arbol",
    "gn:country_code":"CL",
    "gn:dem":496,
    "gn:feature_class":"P",
    "gn:feature_code":"PPL",
    "gn:name":"T\u00fanel del \u00c1rbol",
    "gn:population":0,
    "gn:timezone":"America/Santiago",
    "iso:country":"CL",
    "name:und_x_variant":[
        "El Arbol",
        "T\u00fanel del \u00c1rbol"
    ],
    "wof:name":"Tunel del Arbol",
    "wof:placetype":"locality"
},
  "geometry": {"coordinates":[-71.81638000000002,-34.44178],"type":"Point"}
}