{
  "type": "Feature",
  "properties": {
    "gn:admin1_code":"6.0",
    "gn:admin2_code":"84.0",
    "gn:admin3_code":"8413.0",
    "gn:asciiname":"Chillancito",
    "gn:country_code":"CL",
    "gn:dem":64,
    "gn:feature_class":"P",
    "gn:feature_code":"PPL",
    "gn:name":"Chillancito",
    "gn:population":0,
    "gn:timezone":"America/Santiago",
    "iso:country":"CL",
    "wof:name":"Chillancito",
    "wof:placetype":"locality"
},
  "geometry": {"coordinates":[-72.43011,-36.78585],"type":"Point"}
}