{
  "type": "Feature",
  "properties": {
    "gn:admin1_code":"6.0",
    "gn:admin2_code":"84.0",
    "gn:admin3_code":"8415.0",
    "gn:asciiname":"Ranquil",
    "gn:country_code":"CL",
    "gn:dem":336,
    "gn:feature_class":"P",
    "gn:feature_code":"PPL",
    "gn:name":"R\u00e1nquil",
    "gn:population":0,
    "gn:timezone":"America/Santiago",
    "iso:country":"CL",
    "name:ceb_x_preferred":[
        "Ranquil"
    ],
    "name:eus_x_preferred":[
        "R\u00e1nquil"
    ],
    "name:fra_x_preferred":[
        "R\u00e1nquil"
    ],
    "name:ita_x_preferred":[
        "R\u00e1nquil"
    ],
    "name:nld_x_preferred":[
        "R\u00e1nquil"
    ],
    "name:oci_x_preferred":[
        "R\u00e1nquil"
    ],
    "name:por_x_preferred":[
        "R\u00e1nquil"
    ],
    "name:ron_x_preferred":[
        "R\u00e1nquil"
    ],
    "name:rus_x_preferred":[
        "\u0420\u0430\u043d\u043a\u0438\u043b\u044c"
    ],
    "name:spa_x_preferred":[
        "R\u00e1nquil"
    ],
    "name:swe_x_preferred":[
        "Ranquil"
    ],
    "name:und_x_variant":[
        "R\u00e1nquil"
    ],
    "name:zho_x_preferred":[
        "\u862d\u57fa\u723e"
    ],
    "wof:name":"Ranquil",
    "wof:placetype":"locality"
},
  "geometry": {"coordinates":[-72.56041999999999,-36.65381],"type":"Point"}
}