{
  "type": "Feature",
  "properties": {
    "gn:admin1_code":"6.0",
    "gn:admin2_code":"84.0",
    "gn:admin3_code":"8415.0",
    "gn:asciiname":"Ranquil",
    "gn:country_code":"CL",
    "gn:dem":336,
    "gn:feature_class":"P",
    "gn:feature_code":"PPL",
    "gn:name":"R\u00e1nquil",
    "gn:population":0,
    "gn:timezone":"America/Santiago",
    "iso:country":"CL",
    "name:und_x_variant":[
        "R\u00e1nquil"
    ],
    "wof:name":"Ranquil",
    "wof:placetype":"locality"
},
  "geometry": {"coordinates":[-72.56041999999999,-36.65381],"type":"Point"}
}