{
  "type": "Feature",
  "properties": {
    "gn:country":"CL",
    "gn:fcode":"PPL",
    "gn:pop":0,
    "iso:country":"CL",
    "name:eng_x_preferred":[
        "Tinguiririca"
    ],
    "name:nld_x_preferred":[
        "Tinguiririca"
    ],
    "qs:name":"Tinguiririca",
    "qs:name_adm0":"Chile",
    "qs:name_adm1":"Libertador General Bernardo O'Higgins",
    "qs:photos_9r":0,
    "qs:photos_sr":0,
    "qs:placetype":"Town",
    "qs:pop_sr":"0",
    "wd:wordcount":19,
    "wof:name":"Tinguiririca",
    "wof:placetype":"locality",
    "wof:population":0
},
  "geometry": {"coordinates":[-70.97027,-34.65308],"type":"Point"}
}