{
  "type": "Feature",
  "properties": {
    "gn:admin1_code":"8.0",
    "gn:admin2_code":"61.0",
    "gn:admin3_code":"6109.0",
    "gn:asciiname":"Uva Blanca",
    "gn:country_code":"CL",
    "gn:dem":242,
    "gn:feature_class":"P",
    "gn:feature_code":"PPL",
    "gn:name":"Uva Blanca",
    "gn:population":0,
    "gn:timezone":"America/Santiago",
    "iso:country":"CL",
    "wof:name":"Uva Blanca",
    "wof:placetype":"locality"
},
  "geometry": {"coordinates":[-71.02837,-34.38122],"type":"Point"}
}