{
  "type": "Feature",
  "properties": {
    "gn:admin1_code":"16.0",
    "gn:admin2_code":"152.0",
    "gn:admin3_code":"15202.0",
    "gn:asciiname":"Angostura",
    "gn:country_code":"CL",
    "gn:dem":4122,
    "gn:feature_class":"P",
    "gn:feature_code":"PPL",
    "gn:name":"Angostura",
    "gn:population":0,
    "gn:timezone":"America/Santiago",
    "iso:country":"CL",
    "wof:name":"Angostura",
    "wof:placetype":"locality"
},
  "geometry": {"coordinates":[-69.41667,-17.71667],"type":"Point"}
}