{
  "type": "Feature",
  "properties": {
    "gn:admin1_code":"8.0",
    "gn:admin2_code":"63.0",
    "gn:admin3_code":"6301.0",
    "gn:asciiname":"Las Arboledas",
    "gn:country_code":"CL",
    "gn:dem":358,
    "gn:feature_class":"P",
    "gn:feature_code":"PPL",
    "gn:name":"Las Arboledas",
    "gn:population":0,
    "gn:timezone":"America/Santiago",
    "iso:country":"CL",
    "name:und_x_variant":[
        "Arboledas",
        "Arboledas de Pedehue",
        "Las Arboledas"
    ],
    "wof:name":"Las Arboledas",
    "wof:placetype":"locality"
},
  "geometry": {"coordinates":[-70.97067,-34.59799],"type":"Point"}
}