{
  "type": "Feature",
  "properties": {
    "gn:admin1_code":"6.0",
    "gn:admin2_code":"81.0",
    "gn:asciiname":"Puchoco",
    "gn:country_code":"CL",
    "gn:dem":13,
    "gn:feature_class":"P",
    "gn:feature_code":"PPL",
    "gn:name":"Puchoco",
    "gn:population":0,
    "gn:timezone":"America/Santiago",
    "iso:country":"CL",
    "wof:name":"Puchoco",
    "wof:placetype":"locality"
},
  "geometry": {"coordinates":[-73.17914,-37.01665],"type":"Point"}
}