{
  "type": "Feature",
  "properties": {
    "gn:admin1_code":"1.0",
    "gn:admin2_code":"57.0",
    "gn:admin3_code":"5702.0",
    "gn:asciiname":"Los Mantos",
    "gn:country_code":"CL",
    "gn:dem":1127,
    "gn:feature_class":"P",
    "gn:feature_code":"PPL",
    "gn:name":"Los Mantos",
    "gn:population":0,
    "gn:timezone":"America/Santiago",
    "iso:country":"CL",
    "name:und_x_variant":[
        "Mantos",
        "Los Mantos"
    ],
    "wof:name":"Los Mantos",
    "wof:placetype":"locality"
},
  "geometry": {"coordinates":[-70.89335,-32.6735],"type":"Point"}
}