{
  "type": "Feature",
  "properties": {
    "gn:admin1_code":"7.0",
    "gn:admin2_code":"43.0",
    "gn:admin3_code":"4303.0",
    "gn:asciiname":"Rapel",
    "gn:country_code":"CL",
    "gn:dem":862,
    "gn:feature_class":"P",
    "gn:feature_code":"PPL",
    "gn:name":"Rapel",
    "gn:population":0,
    "gn:timezone":"America/Santiago",
    "iso:country":"CL",
    "wof:name":"Rapel",
    "wof:placetype":"locality"
},
  "geometry": {"coordinates":[-70.77176999999998,-30.72295],"type":"Point"}
}