{
  "type": "Feature",
  "properties": {
    "gn:admin1_code":"4.0",
    "gn:admin2_code":"91.0",
    "gn:admin3_code":"9102.0",
    "gn:asciiname":"Yupehue",
    "gn:country_code":"CL",
    "gn:dem":141,
    "gn:feature_class":"P",
    "gn:feature_code":"PPL",
    "gn:name":"Yupehue",
    "gn:population":0,
    "gn:timezone":"America/Santiago",
    "iso:country":"CL",
    "name:spa_x_preferred":[
        "Reducci\u00f3n Yupehue"
    ],
    "wof:name":"Yupehue",
    "wof:placetype":"locality"
},
  "geometry": {"coordinates":[-73.48680999999998,-38.55438],"type":"Point"}
}