{
  "type": "Feature",
  "properties": {
    "gn:admin1_code":"15.0",
    "gn:admin2_code":"14.0",
    "gn:asciiname":"Chinchillani",
    "gn:country_code":"CL",
    "gn:dem":4241,
    "gn:feature_class":"P",
    "gn:feature_code":"PPL",
    "gn:name":"Chinchillani",
    "gn:population":0,
    "gn:timezone":"America/Santiago",
    "iso:country":"CL",
    "name:ceb_x_preferred":[
        "Cerro Chinchillani"
    ],
    "name:spa_x_preferred":[
        "Chinchillani"
    ],
    "name:swe_x_preferred":[
        "Cerro Chinchillani"
    ],
    "wof:name":"Chinchillani",
    "wof:placetype":"locality"
},
  "geometry": {"coordinates":[-68.86941,-19.07385],"type":"Point"}
}