{
  "type": "Feature",
  "properties": {
    "iso:country":"CL",
    "qs:name":"Pedro de Valdivia",
    "qs:name_adm0":"Chile",
    "qs:name_adm1":"Antofagasta",
    "qs:photos":98,
    "qs:photos_1k":20,
    "qs:photos_9k":1,
    "qs:photos_9r":3,
    "qs:photos_all":98,
    "qs:photos_sr":3,
    "qs:placetype":"Town",
    "qs:pop_sr":"0",
    "wd:wordcount":4150,
    "wof:name":"Pedro de Valdivia",
    "wof:placetype":"locality"
},
  "geometry": {"coordinates":[-69.662933,-22.561073],"type":"Point"}
}