{
  "type": "Feature",
  "properties": {
    "iso:country":"CL",
    "name:ara_x_preferred":[
        "\u0628\u064a\u062f\u0631\u0648 \u062f\u064a \u0641\u0627\u0644\u062f\u064a\u0641\u064a\u0627"
    ],
    "name:bel_x_preferred":[
        "\u041f\u0435\u0434\u0440\u0430 \u0434\u044d \u0412\u0430\u043b\u044c\u0434\u044b\u0432\u0456\u044f"
    ],
    "name:bul_x_preferred":[
        "\u041f\u0435\u0434\u0440\u043e \u0434\u0435 \u0412\u0430\u043b\u0434\u0438\u0432\u0438\u044f"
    ],
    "name:ell_x_preferred":[
        "\u03a0\u03ad\u03b4\u03c1\u03bf \u03bd\u03c4\u03b5 \u0392\u03b1\u03bb\u03b4\u03af\u03b2\u03b9\u03b1"
    ],
    "name:fas_x_preferred":[
        "\u067e\u062f\u0631\u0648 \u062f\u0647 \u0648\u0627\u0644\u062f\u06cc\u0648\u06cc\u0627"
    ],
    "name:heb_x_preferred":[
        "\u05e4\u05d3\u05e8\u05d5 \u05d3\u05d4 \u05d5\u05d0\u05dc\u05d3\u05d9\u05d1\u05d9\u05d4"
    ],
    "name:jpn_x_preferred":[
        "\u30da\u30c9\u30ed\u30fb\u30c7\u30fb\u30d0\u30eb\u30c7\u30a3\u30d3\u30a2"
    ],
    "name:kat_x_preferred":[
        "\u10de\u10d4\u10d3\u10e0\u10dd \u10d3\u10d4 \u10d5\u10d0\u10da\u10d3\u10d8\u10d5\u10d8\u10d0"
    ],
    "name:kor_x_preferred":[
        "\ud398\ub4dc\ub85c \ub370 \ubc1c\ub514\ube44\uc544"
    ],
    "name:krc_x_preferred":[
        "\u0412\u0430\u043b\u044c\u0434\u0438\u0432\u0438\u044f"
    ],
    "name:rus_x_preferred":[
        "\u041f\u0435\u0434\u0440\u043e \u0434\u0435 \u0412\u0430\u043b\u044c\u0434\u0438\u0432\u0438\u044f"
    ],
    "name:srp_x_preferred":[
        "\u041f\u0435\u0434\u0440\u043e \u0434\u0435 \u0412\u0430\u043b\u0434\u0438\u0432\u0438\u0458\u0430"
    ],
    "name:ukr_x_preferred":[
        "\u041f\u0435\u0434\u0440\u043e \u0434\u0435 \u0412\u0430\u043b\u044c\u0434\u0456\u0432\u0456\u044f"
    ],
    "name:zho_x_preferred":[
        "\u4f69\u5fb7\u7f85\u00b7\u5fb7\u00b7\u5df4\u723e\u8fea\u7dad\u4e9e"
    ],
    "qs:name":"Pedro de Valdivia",
    "qs:name_adm0":"Chile",
    "qs:name_adm1":"Antofagasta",
    "qs:photos":98,
    "qs:photos_1k":20,
    "qs:photos_9k":1,
    "qs:photos_9r":3,
    "qs:photos_all":98,
    "qs:photos_sr":3,
    "qs:placetype":"Town",
    "qs:pop_sr":"0",
    "wd:wordcount":4150,
    "wof:name":"Pedro de Valdivia",
    "wof:placetype":"locality"
},
  "geometry": {"coordinates":[-69.662933,-22.561073],"type":"Point"}
}