{
  "type": "Feature",
  "properties": {
    "gn:admin1_code":"14.0",
    "gn:admin2_code":"103.0",
    "gn:admin3_code":"10306.0",
    "gn:asciiname":"El Manzanito",
    "gn:cc2":"CL",
    "gn:country_code":"CL",
    "gn:dem":114,
    "gn:feature_class":"P",
    "gn:feature_code":"PPL",
    "gn:name":"El Manzanito",
    "gn:population":0,
    "gn:timezone":"America/Santiago",
    "iso:country":"CL",
    "name:und_x_variant":[
        "El Manzano"
    ],
    "wof:name":"El Manzanito",
    "wof:placetype":"locality"
},
  "geometry": {"coordinates":[-73.63655,-40.29236],"type":"Point"}
}