{
  "type": "Feature",
  "properties": {
    "gn:admin1_code":"8.0",
    "gn:admin2_code":"63.0",
    "gn:admin3_code":"6308.0",
    "gn:asciiname":"Taulemu",
    "gn:country_code":"CL",
    "gn:dem":272,
    "gn:feature_class":"P",
    "gn:feature_code":"PPL",
    "gn:name":"Taulemu",
    "gn:population":0,
    "gn:timezone":"America/Santiago",
    "iso:country":"CL",
    "wof:name":"Taulemu",
    "wof:placetype":"locality"
},
  "geometry": {"coordinates":[-71.09073000000002,-34.61754000000001],"type":"Point"}
}