{
  "type": "Feature",
  "properties": {
    "gn:admin1_code":"3.0",
    "gn:admin2_code":"22.0",
    "gn:admin3_code":"2203.0",
    "gn:asciiname":"Lagunita",
    "gn:country_code":"CL",
    "gn:dem":4158,
    "gn:feature_class":"P",
    "gn:feature_code":"PPL",
    "gn:name":"Lagunita",
    "gn:population":0,
    "gn:timezone":"America/Santiago",
    "iso:country":"CL",
    "name:nld_x_preferred":[
        "Lagunita"
    ],
    "name:spa_x_preferred":[
        "Lagunita"
    ],
    "name:swe_x_preferred":[
        "Lagunita"
    ],
    "wof:name":"Lagunita",
    "wof:placetype":"locality"
},
  "geometry": {"coordinates":[-68.10104,-22.55299],"type":"Point"}
}