{
  "type": "Feature",
  "properties": {
    "gn:admin1_code":"1.0",
    "gn:admin2_code":"56.0",
    "gn:admin3_code":"5603.0",
    "gn:asciiname":"Paso del Rosario",
    "gn:country_code":"CL",
    "gn:dem":210,
    "gn:feature_class":"P",
    "gn:feature_code":"PPL",
    "gn:name":"Paso del Rosario",
    "gn:population":0,
    "gn:timezone":"America/Santiago",
    "iso:country":"CL",
    "name:und_x_variant":[
        "Paso Rosario",
        "Paso del Rosario"
    ],
    "wof:name":"Paso del Rosario",
    "wof:placetype":"locality"
},
  "geometry": {"coordinates":[-71.48333000000002,-33.48333],"type":"Point"}
}