{
  "type": "Feature",
  "properties": {
    "gn:admin1_code":"16.0",
    "gn:admin2_code":"152.0",
    "gn:admin3_code":"15201.0",
    "gn:asciiname":"Timalchaca",
    "gn:country_code":"CL",
    "gn:dem":3908,
    "gn:feature_class":"P",
    "gn:feature_code":"PPL",
    "gn:name":"Timalchaca",
    "gn:population":0,
    "gn:timezone":"America/Santiago",
    "iso:country":"CL",
    "name:spa_x_preferred":[
        "Timalchaca"
    ],
    "wof:name":"Timalchaca",
    "wof:placetype":"locality"
},
  "geometry": {"coordinates":[-69.41415000000001,-18.68232],"type":"Point"}
}