{
  "type": "Feature",
  "properties": {
    "gn:admin1_code":"12.0",
    "gn:admin2_code":"136.0",
    "gn:admin3_code":"13601.0",
    "gn:asciiname":"Los Olmos",
    "gn:country_code":"CL",
    "gn:dem":391,
    "gn:feature_class":"P",
    "gn:feature_code":"PPL",
    "gn:name":"Los Olmos",
    "gn:population":0,
    "gn:timezone":"America/Santiago",
    "iso:country":"CL",
    "wof:name":"Los Olmos",
    "wof:placetype":"locality"
},
  "geometry": {"coordinates":[-70.86667,-33.66667],"type":"Point"}
}