{
  "type": "Feature",
  "properties": {
    "gn:admin1_code":"7.0",
    "gn:admin2_code":"41.0",
    "gn:admin3_code":"4102.0",
    "gn:asciiname":"Tongoicillo",
    "gn:country_code":"CL",
    "gn:dem":271,
    "gn:feature_class":"P",
    "gn:feature_code":"PPL",
    "gn:name":"Tongoicillo",
    "gn:population":0,
    "gn:timezone":"America/Santiago",
    "iso:country":"CL",
    "wof:name":"Tongoicillo",
    "wof:placetype":"locality"
},
  "geometry": {"coordinates":[-71.30580999999999,-30.17811],"type":"Point"}
}