{
  "type": "Feature",
  "properties": {
    "gn:admin1_code":"2.0",
    "gn:admin2_code":"113.0",
    "gn:asciiname":"Entrada Mayer",
    "gn:country_code":"CL",
    "gn:dem":443,
    "gn:feature_class":"P",
    "gn:feature_code":"PPL",
    "gn:name":"Entrada Mayer",
    "gn:population":0,
    "gn:timezone":"America/Santiago",
    "iso:country":"CL",
    "name:spa_x_preferred":[
        "Entrada Mayer"
    ],
    "wof:name":"Entrada Mayer",
    "wof:placetype":"locality"
},
  "geometry": {"coordinates":[-72.32285999999998,-48.20942],"type":"Point"}
}