{
  "type": "Feature",
  "properties": {
    "gn:admin1_code":"7.0",
    "gn:admin2_code":"41.0",
    "gn:asciiname":"El Empalme",
    "gn:country_code":"CL",
    "gn:dem":2407,
    "gn:feature_class":"P",
    "gn:feature_code":"PPL",
    "gn:name":"El Empalme",
    "gn:population":0,
    "gn:timezone":"America/Santiago",
    "iso:country":"CL",
    "name:ceb_x_preferred":[
        "El Empalme"
    ],
    "name:glg_x_preferred":[
        "O Empalme"
    ],
    "name:spa_x_preferred":[
        "El Empalme"
    ],
    "name:swe_x_preferred":[
        "El Empalme"
    ],
    "wof:name":"El Empalme",
    "wof:placetype":"locality"
},
  "geometry": {"coordinates":[-70.06599,-29.92487],"type":"Point"}
}