{
  "type": "Feature",
  "properties": {
    "gn:admin1_code":"16.0",
    "gn:admin2_code":"152.0",
    "gn:admin3_code":"15202.0",
    "gn:asciiname":"Pahuta",
    "gn:country_code":"CL",
    "gn:dem":4106,
    "gn:feature_class":"P",
    "gn:feature_code":"PPL",
    "gn:name":"Pahuta",
    "gn:population":0,
    "gn:timezone":"America/Santiago",
    "iso:country":"CL",
    "name:spa_x_preferred":[
        "Pahuta"
    ],
    "wof:name":"Pahuta",
    "wof:placetype":"locality"
},
  "geometry": {"coordinates":[-69.58129,-17.86921],"type":"Point"}
}