{
  "type": "Feature",
  "properties": {
    "gn:admin1_code":"2.0",
    "gn:admin2_code":"113.0",
    "gn:asciiname":"Fundo El Mirador",
    "gn:country_code":"CL",
    "gn:dem":456,
    "gn:feature_class":"P",
    "gn:feature_code":"PPL",
    "gn:name":"Fundo El Mirador",
    "gn:population":0,
    "gn:timezone":"America/Santiago",
    "iso:country":"CL",
    "name:spa_x_preferred":[
        "Fundo El Mirador"
    ],
    "wof:name":"Fundo El Mirador",
    "wof:placetype":"locality"
},
  "geometry": {"coordinates":[-72.34336,-48.21153],"type":"Point"}
}