{
  "type": "Feature",
  "properties": {
    "gn:admin1_code":"4.0",
    "gn:admin2_code":"91.0",
    "gn:admin3_code":"9120.0",
    "gn:asciiname":"Liumalla",
    "gn:country_code":"CL",
    "gn:dem":353,
    "gn:feature_class":"P",
    "gn:feature_code":"PPL",
    "gn:name":"Liumalla",
    "gn:population":0,
    "gn:timezone":"America/Santiago",
    "iso:country":"CL",
    "name:und_x_variant":[
        "Lumalla",
        "Liumalla"
    ],
    "wof:name":"Liumalla",
    "wof:placetype":"locality"
},
  "geometry": {"coordinates":[-72.2714,-39.38561],"type":"Point"}
}