{
  "type": "Feature",
  "properties": {
    "gn:admin1_code":"14.0",
    "gn:admin2_code":"102.0",
    "gn:admin3_code":"10203.0",
    "gn:asciiname":"Huicha",
    "gn:country_code":"CL",
    "gn:dem":46,
    "gn:feature_class":"P",
    "gn:feature_code":"PPL",
    "gn:name":"Huicha",
    "gn:population":0,
    "gn:timezone":"America/Santiago",
    "iso:country":"CL",
    "wof:name":"Huicha",
    "wof:placetype":"locality"
},
  "geometry": {"coordinates":[-73.74775,-42.64605],"type":"Point"}
}