{
  "type": "Feature",
  "properties": {
    "iso:country":"CL",
    "qs:name":"Tom\u00e9",
    "qs:name_adm0":"Chile",
    "qs:name_adm1":"Biobio",
    "qs:photos":1,
    "qs:photos_1k":1,
    "qs:photos_9k":10,
    "qs:photos_9r":10,
    "qs:photos_all":2342,
    "qs:photos_sr":1,
    "qs:placetype":"LocalAdmin",
    "qs:pop_sr":"0",
    "wd:wordcount":265,
    "wof:name":"Tom\u00e9",
    "wof:placetype":"localadmin"
},
  "geometry": {"coordinates":[-72.958145,-36.604504],"type":"Point"}
}