{
  "type": "Feature",
  "properties": {
    "gn:admin1_code":"7.0",
    "gn:admin2_code":"43.0",
    "gn:admin3_code":"4305.0",
    "gn:asciiname":"Guampulla",
    "gn:country_code":"CL",
    "gn:dem":548,
    "gn:feature_class":"P",
    "gn:feature_code":"PPL",
    "gn:name":"Guampulla",
    "gn:population":0,
    "gn:timezone":"America/Santiago",
    "iso:country":"CL",
    "name:und_x_variant":[
        "Huampulla",
        "Guampulla"
    ],
    "wof:name":"Guampulla",
    "wof:placetype":"locality"
},
  "geometry": {"coordinates":[-70.98156999999998,-30.42841],"type":"Point"}
}