{
  "type": "Feature",
  "properties": {
    "gn:admin1_code":"11.0",
    "gn:admin2_code":"72.0",
    "gn:admin3_code":"7201.0",
    "gn:asciiname":"Quella",
    "gn:country_code":"CL",
    "gn:dem":134,
    "gn:feature_class":"P",
    "gn:feature_code":"PPL",
    "gn:name":"Quella",
    "gn:population":0,
    "gn:timezone":"America/Santiago",
    "iso:country":"CL",
    "name:arg_x_preferred":[
        "Quella"
    ],
    "wof:name":"Quella",
    "wof:placetype":"locality"
},
  "geometry": {"coordinates":[-72.08568000000002,-36.0545],"type":"Point"}
}