{
  "type": "Feature",
  "properties": {
    "gn:country":"CL",
    "gn:fcode":"PPL",
    "gn:pop":1500,
    "iso:country":"CL",
    "qs:name":"Las Gaviotas",
    "qs:photos_9r":0,
    "qs:photos_sr":0,
    "qs:pop_sr":"3",
    "wof:name":"Las Gaviotas",
    "wof:placetype":"locality",
    "wof:population":1500
},
  "geometry": {"coordinates":[-73.18834,-39.86653],"type":"Point"}
}