{
  "type": "Feature",
  "properties": {
    "gn:admin1_code":"3.0",
    "gn:admin2_code":"23.0",
    "gn:admin3_code":"2302.0",
    "gn:asciiname":"Jose Francisco Vergara",
    "gn:country_code":"CL",
    "gn:dem":1298,
    "gn:feature_class":"P",
    "gn:feature_code":"PPL",
    "gn:name":"Jos\u00e9 Francisco Vergara",
    "gn:population":0,
    "gn:timezone":"America/Santiago",
    "iso:country":"CL",
    "wof:name":"Jose Francisco Vergara",
    "wof:placetype":"locality"
},
  "geometry": {"coordinates":[-69.62141,-22.46019],"type":"Point"}
}