{
  "type": "Feature",
  "properties": {
    "gn:admin1_code":"11.0",
    "gn:admin2_code":"71.0",
    "gn:admin3_code":"7102.0",
    "gn:asciiname":"Aguas Buenas",
    "gn:country_code":"CL",
    "gn:dem":516,
    "gn:feature_class":"P",
    "gn:feature_code":"PPL",
    "gn:name":"Aguas Buenas",
    "gn:population":0,
    "gn:timezone":"America/Santiago",
    "iso:country":"CL",
    "name:und_x_variant":[
        "Agua Buena",
        "Aguas Buenas"
    ],
    "wof:name":"Aguas Buenas",
    "wof:placetype":"locality"
},
  "geometry": {"coordinates":[-72.15679,-35.28226],"type":"Point"}
}