{
  "type": "Feature",
  "properties": {
    "gn:admin1_code":"5.0",
    "gn:admin2_code":"33.0",
    "gn:admin3_code":"3304.0",
    "gn:asciiname":"Chanar Quemado",
    "gn:country_code":"CL",
    "gn:dem":769,
    "gn:feature_class":"P",
    "gn:feature_code":"PPL",
    "gn:name":"Cha\u00f1ar Quemado",
    "gn:population":0,
    "gn:timezone":"America/Santiago",
    "iso:country":"CL",
    "name:spa_x_preferred":[
        "Cha\u00f1ar Quemado"
    ],
    "wof:name":"Chanar Quemado",
    "wof:placetype":"locality"
},
  "geometry": {"coordinates":[-70.85221999999997,-28.3836],"type":"Point"}
}