{
  "type": "Feature",
  "properties": {
    "gn:admin1_code":"14.0",
    "gn:admin2_code":"101.0",
    "gn:asciiname":"Rio Gato",
    "gn:country_code":"CL",
    "gn:dem":34,
    "gn:feature_class":"P",
    "gn:feature_code":"PPLL",
    "gn:name":"R\u00edo Gato",
    "gn:population":0,
    "gn:timezone":"America/Santiago",
    "iso:country":"CL",
    "name:spa_x_preferred":[
        "R\u00edo Gato"
    ],
    "wof:name":"Rio Gato",
    "wof:placetype":"locality"
},
  "geometry": {"coordinates":[-73.24124999999999,-41.47853],"type":"Point"}
}