{
  "type": "Feature",
  "properties": {
    "gn:admin1_code":"8.0",
    "gn:admin2_code":"62.0",
    "gn:admin3_code":"6205.0",
    "gn:asciiname":"Boca Pupuya",
    "gn:country_code":"CL",
    "gn:dem":17,
    "gn:feature_class":"P",
    "gn:feature_code":"PPL",
    "gn:name":"Boca Pupuya",
    "gn:population":0,
    "gn:timezone":"America/Santiago",
    "iso:country":"CL",
    "name:und_x_variant":[
        "Boca",
        "Boca de Pupuya",
        "Boca Pupuya"
    ],
    "wof:name":"Boca Pupuya",
    "wof:placetype":"locality"
},
  "geometry": {"coordinates":[-71.87971999999998,-33.98818],"type":"Point"}
}