{
  "type": "Feature",
  "properties": {
    "gn:admin1_code":"12.0",
    "gn:admin2_code":"136.0",
    "gn:admin3_code":"13605.0",
    "gn:asciiname":"Casas de El Retiro",
    "gn:country_code":"CL",
    "gn:dem":435,
    "gn:feature_class":"P",
    "gn:feature_code":"PPL",
    "gn:name":"Casas de El Retiro",
    "gn:population":0,
    "gn:timezone":"America/Santiago",
    "iso:country":"CL",
    "wof:name":"Casas de El Retiro",
    "wof:placetype":"locality"
},
  "geometry": {"coordinates":[-70.83333,-33.61667],"type":"Point"}
}