{
  "type": "Feature",
  "properties": {
    "gn:admin1_code":"14.0",
    "gn:admin2_code":"102.0",
    "gn:admin3_code":"10208.0",
    "gn:asciiname":"San Antonio de Chadmo",
    "gn:country_code":"CL",
    "gn:dem":32,
    "gn:feature_class":"P",
    "gn:feature_code":"PPL",
    "gn:name":"San Antonio de Chadmo",
    "gn:population":0,
    "gn:timezone":"America/Santiago",
    "iso:country":"CL",
    "name:spa_x_preferred":[
        "San Antonio de Chadmo"
    ],
    "wof:name":"San Antonio de Chadmo",
    "wof:placetype":"locality"
},
  "geometry": {"coordinates":[-73.68446,-42.92078],"type":"Point"}
}