{
  "type": "Feature",
  "properties": {
    "iso:country":"CL",
    "qs:name":"Castro",
    "qs:name_adm0":"Chile",
    "qs:name_adm1":"Los Lagos",
    "qs:photos":4,
    "qs:photos_1k":1,
    "qs:photos_9k":15,
    "qs:photos_9r":11,
    "qs:photos_all":3442,
    "qs:photos_sr":1,
    "qs:placetype":"LocalAdmin",
    "qs:pop_sr":"0",
    "wd:wordcount":377,
    "wof:name":"Castro",
    "wof:placetype":"localadmin"
},
  "geometry": {"coordinates":[-73.7677,-42.482288],"type":"Point"}
}