{
  "type": "Feature",
  "properties": {
    "iso:country":"CL",
    "name:bel_x_preferred":[
        "\u041a\u0430\u0441\u0442\u0440\u0430"
    ],
    "name:bre_x_preferred":[
        "Castro"
    ],
    "name:bul_x_preferred":[
        "\u041a\u0430\u0441\u0442\u0440\u043e"
    ],
    "name:cat_x_preferred":[
        "Castro"
    ],
    "name:ceb_x_preferred":[
        "Castro"
    ],
    "name:ces_x_preferred":[
        "Castro"
    ],
    "name:cym_x_preferred":[
        "Castro"
    ],
    "name:deu_x_preferred":[
        "Castro"
    ],
    "name:epo_x_preferred":[
        "Castro"
    ],
    "name:eus_x_preferred":[
        "Castro"
    ],
    "name:fas_x_preferred":[
        "\u06a9\u0627\u0633\u062a\u0631\u0648"
    ],
    "name:fin_x_preferred":[
        "Castro"
    ],
    "name:fra_x_preferred":[
        "Castro"
    ],
    "name:glg_x_preferred":[
        "Castro"
    ],
    "name:heb_x_preferred":[
        "\u05e7\u05e1\u05d8\u05e8\u05d5"
    ],
    "name:hye_x_preferred":[
        "\u053f\u0561\u057d\u057f\u0580\u0578"
    ],
    "name:isl_x_preferred":[
        "Castro"
    ],
    "name:ita_x_preferred":[
        "Castro"
    ],
    "name:jpn_x_preferred":[
        "\u30ab\u30b9\u30c8\u30ed"
    ],
    "name:kor_x_preferred":[
        "\uce74\uc2a4\ud2b8\ub85c"
    ],
    "name:lit_x_preferred":[
        "Castro"
    ],
    "name:nld_x_preferred":[
        "Castro"
    ],
    "name:nor_x_preferred":[
        "Castro"
    ],
    "name:pms_x_preferred":[
        "Castro"
    ],
    "name:pol_x_preferred":[
        "Castro"
    ],
    "name:por_x_preferred":[
        "Castro"
    ],
    "name:ron_x_preferred":[
        "Castro"
    ],
    "name:rus_x_preferred":[
        "\u041a\u0430\u0441\u0442\u0440\u043e"
    ],
    "name:slk_x_preferred":[
        "Castro"
    ],
    "name:slv_x_preferred":[
        "Castro"
    ],
    "name:spa_x_preferred":[
        "Castro"
    ],
    "name:srp_x_preferred":[
        "\u041a\u0430\u0441\u0442\u0440\u043e"
    ],
    "name:swe_x_preferred":[
        "Castro"
    ],
    "name:tur_x_preferred":[
        "Castro"
    ],
    "name:ukr_x_preferred":[
        "\u041a\u0430\u0441\u0442\u0440\u043e"
    ],
    "name:vol_x_preferred":[
        "Castro"
    ],
    "name:zho_x_preferred":[
        "\u5361\u65af\u7279\u7f57"
    ],
    "qs:name":"Castro",
    "qs:name_adm0":"Chile",
    "qs:name_adm1":"Los Lagos",
    "qs:photos":4,
    "qs:photos_1k":1,
    "qs:photos_9k":15,
    "qs:photos_9r":11,
    "qs:photos_all":3442,
    "qs:photos_sr":1,
    "qs:placetype":"LocalAdmin",
    "qs:pop_sr":"0",
    "wd:wordcount":377,
    "wof:name":"Castro",
    "wof:placetype":"localadmin"
},
  "geometry": {"coordinates":[-73.7677,-42.482288],"type":"Point"}
}