{
  "type": "Feature",
  "properties": {
    "gn:admin1_code":"7.0",
    "gn:admin2_code":"41.0",
    "gn:admin3_code":"4104.0",
    "gn:asciiname":"Los Corrales",
    "gn:country_code":"CL",
    "gn:dem":1935,
    "gn:feature_class":"P",
    "gn:feature_code":"PPL",
    "gn:name":"Los Corrales",
    "gn:population":0,
    "gn:timezone":"America/Santiago",
    "iso:country":"CL",
    "name:arg_x_preferred":[
        "Los Corrales"
    ],
    "name:ast_x_preferred":[
        "Los Corrales"
    ],
    "name:cat_x_preferred":[
        "Los Corrales"
    ],
    "name:ceb_x_preferred":[
        "Los Corrales"
    ],
    "name:epo_x_preferred":[
        "Los Corrales"
    ],
    "name:eus_x_preferred":[
        "Los Corrales"
    ],
    "name:fra_x_preferred":[
        "Los Corrales"
    ],
    "name:hun_x_preferred":[
        "Los Corrales"
    ],
    "name:hye_x_preferred":[
        "\u053c\u0578\u057d \u053f\u0578\u057c\u0561\u056c\u0565\u057d"
    ],
    "name:ind_x_preferred":[
        "Los Corrales"
    ],
    "name:ita_x_preferred":[
        "Los Corrales"
    ],
    "name:kaz_x_preferred":[
        "\u041b\u043e\u0441-\u041a\u043e\u0440\u0440\u0430\u043b\u0435\u0441"
    ],
    "name:msa_x_preferred":[
        "Los Corrales"
    ],
    "name:nld_x_preferred":[
        "Los Corrales"
    ],
    "name:oci_x_preferred":[
        "Los Corrales"
    ],
    "name:pol_x_preferred":[
        "Los Corrales"
    ],
    "name:por_x_preferred":[
        "Los Corrales"
    ],
    "name:ron_x_preferred":[
        "Los Corrales"
    ],
    "name:rus_x_preferred":[
        "\u041b\u043e\u0441-\u041a\u043e\u0440\u0440\u0430\u043b\u0435\u0441"
    ],
    "name:spa_x_preferred":[
        "Los Corrales"
    ],
    "name:tur_x_preferred":[
        "Los Corrales"
    ],
    "name:ukr_x_preferred":[
        "\u041b\u043e\u0441-\u041a\u043e\u0440\u0440\u0430\u043b\u0435\u0441"
    ],
    "name:uzb_x_preferred":[
        "Los Corrales"
    ],
    "name:vie_x_preferred":[
        "Los Corrales"
    ],
    "name:war_x_preferred":[
        "Los Corrales"
    ],
    "name:zho_x_preferred":[
        "\u6d1b\u65af\u79d1\u62c9\u83b1\u65af"
    ],
    "wof:name":"Los Corrales",
    "wof:placetype":"locality"
},
  "geometry": {"coordinates":[-70.63406999999999,-29.46419],"type":"Point"}
}