{
  "type": "Feature",
  "properties": {
    "gn:admin1_code":"7.0",
    "gn:admin2_code":"41.0",
    "gn:admin3_code":"4104.0",
    "gn:asciiname":"Los Corrales",
    "gn:country_code":"CL",
    "gn:dem":1935,
    "gn:feature_class":"P",
    "gn:feature_code":"PPL",
    "gn:name":"Los Corrales",
    "gn:population":0,
    "gn:timezone":"America/Santiago",
    "iso:country":"CL",
    "name:spa_x_preferred":[
        "Los Corrales"
    ],
    "wof:name":"Los Corrales",
    "wof:placetype":"locality"
},
  "geometry": {"coordinates":[-70.63406999999999,-29.46419],"type":"Point"}
}