{
  "type": "Feature",
  "properties": {
    "gn:admin1_code":"11.0",
    "gn:admin2_code":"73.0",
    "gn:admin3_code":"7301.0",
    "gn:asciiname":"Upeo",
    "gn:country_code":"CL",
    "gn:dem":534,
    "gn:feature_class":"P",
    "gn:feature_code":"PPL",
    "gn:name":"Upeo",
    "gn:population":0,
    "gn:timezone":"America/Santiago",
    "iso:country":"CL",
    "wof:name":"Upeo",
    "wof:placetype":"locality"
},
  "geometry": {"coordinates":[-71.03855,-35.12487],"type":"Point"}
}