{
  "type": "Feature",
  "properties": {
    "gn:admin1_code":"16.0",
    "gn:admin2_code":"152.0",
    "gn:admin3_code":"15202.0",
    "gn:asciiname":"Ancocalani",
    "gn:country_code":"CL",
    "gn:dem":4031,
    "gn:feature_class":"P",
    "gn:feature_code":"PPL",
    "gn:name":"Ancocalani",
    "gn:population":0,
    "gn:timezone":"America/Santiago",
    "iso:country":"CL",
    "name:und_x_variant":[
        "Ancocatani",
        "Anocalani",
        "Ancolacane",
        "Ancocalani"
    ],
    "wof:name":"Ancocalani",
    "wof:placetype":"locality"
},
  "geometry": {"coordinates":[-69.60613000000001,-17.85419],"type":"Point"}
}