{
  "type": "Feature",
  "properties": {
    "gn:admin1_code":"14.0",
    "gn:admin2_code":"102.0",
    "gn:admin3_code":"10203.0",
    "gn:asciiname":"Nahuitad",
    "gn:country_code":"CL",
    "gn:dem":134,
    "gn:feature_class":"P",
    "gn:feature_code":"PPL",
    "gn:name":"Nahuitad",
    "gn:population":0,
    "gn:timezone":"America/Santiago",
    "iso:country":"CL",
    "wof:name":"Nahuitad",
    "wof:placetype":"locality"
},
  "geometry": {"coordinates":[-73.81458000000001,-42.5439],"type":"Point"}
}