{
  "type": "Feature",
  "properties": {
    "gn:admin1_code":"14.0",
    "gn:admin2_code":"102.0",
    "gn:admin3_code":"10209.0",
    "gn:asciiname":"Montemar",
    "gn:country_code":"CL",
    "gn:dem":1,
    "gn:feature_class":"P",
    "gn:feature_code":"PPL",
    "gn:name":"Montemar",
    "gn:population":0,
    "gn:timezone":"America/Santiago",
    "iso:country":"CL",
    "name:spa_x_preferred":[
        "Montemar"
    ],
    "wof:name":"Montemar",
    "wof:placetype":"locality"
},
  "geometry": {"coordinates":[-73.42135999999998,-42.22998],"type":"Point"}
}