{
  "type": "Feature",
  "properties": {
    "gn:admin1_code":"1.0",
    "gn:admin2_code":"57.0",
    "gn:admin3_code":"5704.0",
    "gn:asciiname":"Lo Campo",
    "gn:country_code":"CL",
    "gn:dem":456,
    "gn:feature_class":"P",
    "gn:feature_code":"PPL",
    "gn:name":"Lo Campo",
    "gn:population":0,
    "gn:timezone":"America/Santiago",
    "iso:country":"CL",
    "name:und_x_variant":[
        "Ocampo",
        "Lo Campo"
    ],
    "wof:name":"Lo Campo",
    "wof:placetype":"locality"
},
  "geometry": {"coordinates":[-70.91937,-32.81077],"type":"Point"}
}