{
  "type": "Feature",
  "properties": {
    "gn:admin1_code":"10.0",
    "gn:admin2_code":"123.0",
    "gn:asciiname":"Victoria Norte",
    "gn:country_code":"CL",
    "gn:dem":49,
    "gn:feature_class":"P",
    "gn:feature_code":"PPL",
    "gn:name":"Victoria Norte",
    "gn:population":0,
    "gn:timezone":"America/Punta_Arenas",
    "iso:country":"CL",
    "name:spa_x_preferred":[
        "Victoria Norte"
    ],
    "wof:name":"Victoria Norte",
    "wof:placetype":"locality"
},
  "geometry": {"coordinates":[-69.34583000000001,-52.75814],"type":"Point"}
}