{
  "type": "Feature",
  "properties": {
    "gn:admin1_code":"8.0",
    "gn:admin2_code":"61.0",
    "gn:admin3_code":"6108.0",
    "gn:asciiname":"Banos",
    "gn:country_code":"CL",
    "gn:dem":757,
    "gn:feature_class":"P",
    "gn:feature_code":"PPL",
    "gn:name":"Ba\u00f1os",
    "gn:population":0,
    "gn:timezone":"America/Santiago",
    "iso:country":"CL",
    "wof:name":"Banos",
    "wof:placetype":"locality"
},
  "geometry": {"coordinates":[-70.55393000000002,-34.24362],"type":"Point"}
}