{
  "type": "Feature",
  "properties": {
    "iso:country":"CL",
    "qs:name":"San Carlos",
    "qs:name_adm0":"Chile",
    "qs:name_adm1":"Biobio",
    "qs:photos":8,
    "qs:photos_1k":2,
    "qs:photos_9k":1,
    "qs:photos_9r":4,
    "qs:photos_all":290,
    "qs:photos_sr":1,
    "qs:placetype":"LocalAdmin",
    "qs:pop_sr":"0",
    "wd:wordcount":508,
    "wof:name":"San Carlos",
    "wof:placetype":"localadmin"
},
  "geometry": {"coordinates":[-71.955657,-36.423768],"type":"Point"}
}