{
  "type": "Feature",
  "properties": {
    "gn:admin1_code":"4.0",
    "gn:admin2_code":"92.0",
    "gn:admin3_code":"9206.0",
    "gn:asciiname":"Quilquen",
    "gn:country_code":"CL",
    "gn:dem":148,
    "gn:feature_class":"P",
    "gn:feature_code":"PPL",
    "gn:name":"Quilqu\u00e9n",
    "gn:population":0,
    "gn:timezone":"America/Santiago",
    "iso:country":"CL",
    "name:spa_x_preferred":[
        "Quilqu\u00e9n"
    ],
    "wof:name":"Quilquen",
    "wof:placetype":"locality"
},
  "geometry": {"coordinates":[-72.70869999999999,-38.10995],"type":"Point"}
}