{
  "type": "Feature",
  "properties": {
    "gn:admin1_code":"10.0",
    "gn:admin2_code":"121.0",
    "gn:asciiname":"Delgada Este",
    "gn:country_code":"CL",
    "gn:dem":14,
    "gn:feature_class":"P",
    "gn:feature_code":"PPL",
    "gn:name":"Delgada Este",
    "gn:population":0,
    "gn:timezone":"America/Punta_Arenas",
    "iso:country":"CL",
    "name:spa_x_preferred":[
        "Delgada Este"
    ],
    "wof:name":"Delgada Este",
    "wof:placetype":"locality"
},
  "geometry": {"coordinates":[-69.52814000000001,-52.36706],"type":"Point"}
}