{
  "type": "Feature",
  "properties": {
    "gn:admin1_code":"15.0",
    "gn:admin2_code":"14.0",
    "gn:admin3_code":"1401.0",
    "gn:asciiname":"Huaca",
    "gn:country_code":"CL",
    "gn:dem":2838,
    "gn:feature_class":"P",
    "gn:feature_code":"PPL",
    "gn:name":"Huaca",
    "gn:population":0,
    "gn:timezone":"America/Santiago",
    "iso:country":"CL",
    "wof:name":"Huaca",
    "wof:placetype":"locality"
},
  "geometry": {"coordinates":[-69.12971999999999,-20.20422],"type":"Point"}
}