{
  "type": "Feature",
  "properties": {
    "gn:admin1_code":"15.0",
    "gn:admin2_code":"14.0",
    "gn:admin3_code":"1401.0",
    "gn:asciiname":"Huaca",
    "gn:country_code":"CL",
    "gn:dem":2838,
    "gn:feature_class":"P",
    "gn:feature_code":"PPL",
    "gn:name":"Huaca",
    "gn:population":0,
    "gn:timezone":"America/Santiago",
    "iso:country":"CL",
    "name:cat_x_preferred":[
        "Huaca"
    ],
    "name:deu_x_preferred":[
        "Wak'a"
    ],
    "name:eus_x_preferred":[
        "Huaca"
    ],
    "name:fin_x_preferred":[
        "Huaca"
    ],
    "name:heb_x_preferred":[
        "\u05d5\u05d0\u05e7\u05d4"
    ],
    "name:ita_x_preferred":[
        "Huaca"
    ],
    "name:kat_x_preferred":[
        "\u10e3\u10d0\u10d9\u10d0"
    ],
    "name:mkd_x_preferred":[
        "\u0423\u0430\u043a\u0430"
    ],
    "name:pol_x_preferred":[
        "Huaca"
    ],
    "name:por_x_preferred":[
        "Huaca"
    ],
    "name:que_x_preferred":[
        "Wak'a"
    ],
    "name:rus_x_preferred":[
        "\u0423\u0430\u043a\u0430"
    ],
    "name:spa_x_preferred":[
        "Huaca"
    ],
    "name:swe_x_preferred":[
        "Huacas"
    ],
    "name:tha_x_preferred":[
        "\u0e2e\u0e31\u0e27\u0e04\u0e32"
    ],
    "name:ukr_x_preferred":[
        "\u0423\u0430\u043a\u0430"
    ],
    "wof:name":"Huaca",
    "wof:placetype":"locality"
},
  "geometry": {"coordinates":[-69.12971999999999,-20.20422],"type":"Point"}
}