{
  "type": "Feature",
  "properties": {
    "gn:admin1_code":"6.0",
    "gn:admin2_code":"84.0",
    "gn:admin3_code":"8410.0",
    "gn:asciiname":"El Saltillo",
    "gn:country_code":"CL",
    "gn:dem":310,
    "gn:feature_class":"P",
    "gn:feature_code":"PPL",
    "gn:name":"El Saltillo",
    "gn:population":0,
    "gn:timezone":"America/Santiago",
    "iso:country":"CL",
    "name:spa_x_preferred":[
        "Santa Lidia"
    ],
    "wof:name":"El Saltillo",
    "wof:placetype":"locality"
},
  "geometry": {"coordinates":[-71.99861,-37.01094000000001],"type":"Point"}
}