{
  "type": "Feature",
  "properties": {
    "gn:admin1_code":"16.0",
    "gn:admin2_code":"152.0",
    "gn:admin3_code":"15202.0",
    "gn:asciiname":"Aguas Calientes",
    "gn:country_code":"CL",
    "gn:dem":4512,
    "gn:feature_class":"P",
    "gn:feature_code":"PPL",
    "gn:name":"Aguas Calientes",
    "gn:population":0,
    "gn:timezone":"America/Santiago",
    "iso:country":"CL",
    "name:spa_x_preferred":[
        "Aguas Calientes"
    ],
    "wof:name":"Aguas Calientes",
    "wof:placetype":"locality"
},
  "geometry": {"coordinates":[-69.81939,-17.72239],"type":"Point"}
}