{
  "type": "Feature",
  "properties": {
    "gn:admin1_code":"1.0",
    "gn:admin2_code":"51.0",
    "gn:admin3_code":"5107.0",
    "gn:asciiname":"Loncura",
    "gn:country_code":"CL",
    "gn:dem":28,
    "gn:feature_class":"P",
    "gn:feature_code":"PPL",
    "gn:name":"Loncura",
    "gn:population":0,
    "gn:timezone":"America/Santiago",
    "iso:country":"CL",
    "wof:name":"Loncura",
    "wof:placetype":"locality"
},
  "geometry": {"coordinates":[-71.50556,-32.78778],"type":"Point"}
}