{
  "type": "Feature",
  "properties": {
    "gn:admin1_code":"7.0",
    "gn:admin2_code":"43.0",
    "gn:admin3_code":"4303.0",
    "gn:asciiname":"Caren",
    "gn:country_code":"CL",
    "gn:dem":712,
    "gn:feature_class":"P",
    "gn:feature_code":"PPL",
    "gn:name":"Car\u00e9n",
    "gn:population":0,
    "gn:timezone":"America/Santiago",
    "iso:country":"CL",
    "wof:name":"Caren",
    "wof:placetype":"locality"
},
  "geometry": {"coordinates":[-70.77063000000003,-30.85022],"type":"Point"}
}