{
  "type": "Feature",
  "properties": {
    "gn:admin1_code":"1.0",
    "gn:admin2_code":"51.0",
    "gn:admin3_code":"5103.0",
    "gn:asciiname":"Montemar",
    "gn:country_code":"CL",
    "gn:dem":159,
    "gn:feature_class":"P",
    "gn:feature_code":"PPL",
    "gn:name":"Montemar",
    "gn:population":0,
    "gn:timezone":"America/Santiago",
    "iso:country":"CL",
    "wof:name":"Montemar",
    "wof:placetype":"locality"
},
  "geometry": {"coordinates":[-71.48333000000002,-32.96667],"type":"Point"}
}