{
  "type": "Feature",
  "properties": {
    "iso:country":"CL",
    "qs:name":"Cabildo",
    "qs:name_adm0":"Chile",
    "qs:name_adm1":"Valpara\u00edso",
    "qs:photos":7,
    "qs:photos_1k":1,
    "qs:photos_9k":1,
    "qs:photos_9r":3,
    "qs:photos_all":121,
    "qs:photos_sr":1,
    "qs:placetype":"LocalAdmin",
    "qs:pop_sr":"0",
    "wd:wordcount":74,
    "wof:name":"Cabildo",
    "wof:placetype":"localadmin"
},
  "geometry": {"coordinates":[-71.0683805,-32.427599],"type":"Point"}
}