{
  "type": "Feature",
  "properties": {
    "iso:country":"CL",
    "name:cat_x_preferred":[
        "Cabildo"
    ],
    "name:deu_x_preferred":[
        "Cabildo"
    ],
    "name:fra_x_preferred":[
        "Cabildo"
    ],
    "name:ita_x_preferred":[
        "Cabildo"
    ],
    "name:por_x_preferred":[
        "Cabildo"
    ],
    "name:rus_x_preferred":[
        "\u041a\u0430\u0431\u0438\u043b\u044c\u0434\u043e"
    ],
    "name:spa_x_preferred":[
        "Cabildo"
    ],
    "qs:name":"Cabildo",
    "qs:name_adm0":"Chile",
    "qs:name_adm1":"Valpara\u00edso",
    "qs:photos":7,
    "qs:photos_1k":1,
    "qs:photos_9k":1,
    "qs:photos_9r":3,
    "qs:photos_all":121,
    "qs:photos_sr":1,
    "qs:placetype":"LocalAdmin",
    "qs:pop_sr":"0",
    "wd:wordcount":74,
    "wof:name":"Cabildo",
    "wof:placetype":"localadmin"
},
  "geometry": {"coordinates":[-71.0683805,-32.427599],"type":"Point"}
}