{
  "type": "Feature",
  "properties": {
    "gn:admin1_code":"11.0",
    "gn:admin2_code":"74.0",
    "gn:admin3_code":"7405.0",
    "gn:asciiname":"Campanacura",
    "gn:country_code":"CL",
    "gn:dem":136,
    "gn:feature_class":"P",
    "gn:feature_code":"PPL",
    "gn:name":"Campanacura",
    "gn:population":0,
    "gn:timezone":"America/Santiago",
    "iso:country":"CL",
    "wof:name":"Campanacura",
    "wof:placetype":"locality"
},
  "geometry": {"coordinates":[-71.98586,-35.98349],"type":"Point"}
}