{
  "type": "Feature",
  "properties": {
    "gn:admin1_code":"1.0",
    "gn:admin2_code":"51.0",
    "gn:admin3_code":"5105.0",
    "gn:asciiname":"Campiche",
    "gn:country_code":"CL",
    "gn:dem":55,
    "gn:feature_class":"P",
    "gn:feature_code":"PPL",
    "gn:name":"Campiche",
    "gn:population":0,
    "gn:timezone":"America/Santiago",
    "iso:country":"CL",
    "wof:name":"Campiche",
    "wof:placetype":"locality"
},
  "geometry": {"coordinates":[-71.4575,-32.73985],"type":"Point"}
}