{
  "type": "Feature",
  "properties": {
    "gn:country":"CL",
    "gn:fcode":"PPLL",
    "gn:pop":50,
    "iso:country":"CL",
    "qs:name":"El Cadillal",
    "qs:photos_9r":0,
    "qs:photos_sr":0,
    "qs:pop_sr":"1",
    "wof:name":"El Cadillal",
    "wof:placetype":"locality",
    "wof:population":50
},
  "geometry": {"coordinates":[-73.57886999999999,-39.93251],"type":"Point"}
}