{
  "type": "Feature",
  "properties": {
    "gn:admin1_code":"8.0",
    "gn:admin2_code":"61.0",
    "gn:admin3_code":"6117.0",
    "gn:asciiname":"La Vinilla",
    "gn:country_code":"CL",
    "gn:dem":237,
    "gn:feature_class":"P",
    "gn:feature_code":"PPL",
    "gn:name":"La Vi\u00f1illa",
    "gn:population":0,
    "gn:timezone":"America/Santiago",
    "iso:country":"CL",
    "wof:name":"La Vinilla",
    "wof:placetype":"locality"
},
  "geometry": {"coordinates":[-71.05677,-34.38462],"type":"Point"}
}