{
  "type": "Feature",
  "properties": {
    "gn:admin1_code":"7.0",
    "gn:admin2_code":"41.0",
    "gn:admin3_code":"4103.0",
    "gn:asciiname":"La Chupalla",
    "gn:country_code":"CL",
    "gn:dem":486,
    "gn:feature_class":"P",
    "gn:feature_code":"PPL",
    "gn:name":"La Chupalla",
    "gn:population":0,
    "gn:timezone":"America/Santiago",
    "iso:country":"CL",
    "wof:name":"La Chupalla",
    "wof:placetype":"locality"
},
  "geometry": {"coordinates":[-71.11667,-30.38333],"type":"Point"}
}