{
  "type": "Feature",
  "properties": {
    "gn:admin1_code":"1.0",
    "gn:admin2_code":"53.0",
    "gn:admin3_code":"5301.0",
    "gn:asciiname":"El Juncal",
    "gn:country_code":"CL",
    "gn:dem":2221,
    "gn:feature_class":"P",
    "gn:feature_code":"PPL",
    "gn:name":"El Juncal",
    "gn:population":0,
    "gn:timezone":"America/Santiago",
    "iso:country":"CL",
    "wof:name":"El Juncal",
    "wof:placetype":"locality"
},
  "geometry": {"coordinates":[-70.15047,-32.86748],"type":"Point"}
}