{
  "type": "Feature",
  "properties": {
    "gn:country":"CL",
    "gn:fcode":"ADM3",
    "gn:pop":0,
    "iso:country":"CL",
    "qs:name":"Cauquenes",
    "qs:name_adm0":"Chile",
    "qs:name_adm1":"Maule",
    "qs:photos":2,
    "qs:photos_1k":1,
    "qs:photos_9k":1,
    "qs:photos_9r":4,
    "qs:photos_all":259,
    "qs:photos_sr":1,
    "qs:placetype":"LocalAdmin",
    "qs:pop_sr":"0",
    "wd:wordcount":576,
    "wof:name":"Cauquenes",
    "wof:placetype":"localadmin",
    "wof:population":0
},
  "geometry": {"coordinates":[-72.27997999999999,-35.97135],"type":"Point"}
}