{
  "type": "Feature",
  "properties": {
    "gn:admin1_code":"5.0",
    "gn:admin2_code":"31.0",
    "gn:asciiname":"Alianza",
    "gn:country_code":"CL",
    "gn:dem":601,
    "gn:feature_class":"P",
    "gn:feature_code":"PPL",
    "gn:name":"Alianza",
    "gn:population":0,
    "gn:timezone":"America/Santiago",
    "iso:country":"CL",
    "name:ceb_x_preferred":[
        "Alianza"
    ],
    "name:por_x_preferred":[
        "Alianza"
    ],
    "name:spa_x_preferred":[
        "Alianza"
    ],
    "name:swe_x_preferred":[
        "Alianza"
    ],
    "wof:name":"Alianza",
    "wof:placetype":"locality"
},
  "geometry": {"coordinates":[-70.24811,-27.57701],"type":"Point"}
}