{
  "type": "Feature",
  "properties": {
    "gn:admin1_code":"6.0",
    "gn:admin2_code":"84.0",
    "gn:admin3_code":"8420.0",
    "gn:asciiname":"Pachagua",
    "gn:country_code":"CL",
    "gn:dem":139,
    "gn:feature_class":"P",
    "gn:feature_code":"PPL",
    "gn:name":"Pachagua",
    "gn:population":0,
    "gn:timezone":"America/Santiago",
    "iso:country":"CL",
    "wof:name":"Pachagua",
    "wof:placetype":"locality"
},
  "geometry": {"coordinates":[-72.56692,-36.44603],"type":"Point"}
}