{
  "type": "Feature",
  "properties": {
    "gn:admin1_code":"8.0",
    "gn:admin2_code":"62.0",
    "gn:admin3_code":"6205.0",
    "gn:asciiname":"El Arco",
    "gn:country_code":"CL",
    "gn:dem":312,
    "gn:feature_class":"P",
    "gn:feature_code":"PPL",
    "gn:name":"El Arco",
    "gn:population":0,
    "gn:timezone":"America/Santiago",
    "iso:country":"CL",
    "name:ceb_x_preferred":[
        "El Arco"
    ],
    "name:spa_x_preferred":[
        "El Arco"
    ],
    "name:swe_x_preferred":[
        "El Arco"
    ],
    "wof:name":"El Arco",
    "wof:placetype":"locality"
},
  "geometry": {"coordinates":[-71.80234,-34.07943],"type":"Point"}
}