{
  "type": "Feature",
  "properties": {
    "gn:admin1_code":"11.0",
    "gn:admin2_code":"72.0",
    "gn:admin3_code":"7202.0",
    "gn:asciiname":"Coihueco",
    "gn:country_code":"CL",
    "gn:dem":446,
    "gn:feature_class":"P",
    "gn:feature_code":"PPL",
    "gn:name":"Coihueco",
    "gn:population":0,
    "gn:timezone":"America/Santiago",
    "iso:country":"CL",
    "wof:name":"Coihueco",
    "wof:placetype":"locality"
},
  "geometry": {"coordinates":[-72.43181,-35.782],"type":"Point"}
}