{
  "type": "Feature",
  "properties": {
    "gn:admin1_code":"7.0",
    "gn:admin2_code":"43.0",
    "gn:admin3_code":"4305.0",
    "gn:asciiname":"Majada",
    "gn:country_code":"CL",
    "gn:dem":1661,
    "gn:feature_class":"P",
    "gn:feature_code":"PPL",
    "gn:name":"Majada",
    "gn:population":0,
    "gn:timezone":"America/Santiago",
    "iso:country":"CL",
    "wof:name":"Majada",
    "wof:placetype":"locality"
},
  "geometry": {"coordinates":[-70.84788,-30.29277],"type":"Point"}
}