{
  "type": "Feature",
  "properties": {
    "gn:admin1_code":"5.0",
    "gn:admin2_code":"33.0",
    "gn:admin3_code":"3301.0",
    "gn:asciiname":"Milla Quince",
    "gn:country_code":"CL",
    "gn:dem":357,
    "gn:feature_class":"P",
    "gn:feature_code":"PPL",
    "gn:name":"Milla Quince",
    "gn:population":0,
    "gn:timezone":"America/Santiago",
    "iso:country":"CL",
    "name:spa_x_preferred":[
        "Milla Quince"
    ],
    "wof:name":"Milla Quince",
    "wof:placetype":"locality"
},
  "geometry": {"coordinates":[-70.69275,-28.07329],"type":"Point"}
}