{
  "type": "Feature",
  "properties": {
    "gn:admin1_code":"14.0",
    "gn:admin2_code":"104.0",
    "gn:admin3_code":"10402.0",
    "gn:asciiname":"San Ramon",
    "gn:country_code":"CL",
    "gn:dem":503,
    "gn:feature_class":"P",
    "gn:feature_code":"PPL",
    "gn:name":"San Ram\u00f3n",
    "gn:population":0,
    "gn:timezone":"America/Santiago",
    "iso:country":"CL",
    "name:spa_x_preferred":[
        "San Ram\u00f3n"
    ],
    "wof:name":"San Ramon",
    "wof:placetype":"locality"
},
  "geometry": {"coordinates":[-72.07330999999998,-43.01834],"type":"Point"}
}