{
  "type": "Feature",
  "properties": {
    "gn:admin1_code":"16.0",
    "gn:admin2_code":"152.0",
    "gn:admin3_code":"15201.0",
    "gn:asciiname":"Jaillabe",
    "gn:country_code":"CL",
    "gn:dem":4575,
    "gn:feature_class":"P",
    "gn:feature_code":"PPL",
    "gn:name":"Jaillabe",
    "gn:population":0,
    "gn:timezone":"America/Santiago",
    "iso:country":"CL",
    "name:spa_x_preferred":[
        "Jaillabe"
    ],
    "wof:name":"Jaillabe",
    "wof:placetype":"locality"
},
  "geometry": {"coordinates":[-69.33653000000001,-18.05113],"type":"Point"}
}