{
  "type": "Feature",
  "properties": {
    "gn:admin1_code":"15.0",
    "gn:admin2_code":"14.0",
    "gn:admin3_code":"1404.0",
    "gn:asciiname":"Saya",
    "gn:country_code":"CL",
    "gn:dem":445,
    "gn:feature_class":"P",
    "gn:feature_code":"PPL",
    "gn:name":"Saya",
    "gn:population":0,
    "gn:timezone":"America/Santiago",
    "iso:country":"CL",
    "name:ceb_x_preferred":[
        "Saya"
    ],
    "name:deu_x_preferred":[
        "Saya"
    ],
    "name:fra_x_preferred":[
        "Saya"
    ],
    "name:ind_x_preferred":[
        "Saya"
    ],
    "name:spa_x_preferred":[
        "Saya"
    ],
    "name:swe_x_preferred":[
        "Saya"
    ],
    "wof:name":"Saya",
    "wof:placetype":"locality"
},
  "geometry": {"coordinates":[-70.11667,-19.51667],"type":"Point"}
}