{
  "type": "Feature",
  "properties": {
    "gn:admin1_code":"7.0",
    "gn:admin2_code":"41.0",
    "gn:asciiname":"La Herradura",
    "gn:country_code":"CL",
    "gn:dem":16,
    "gn:feature_class":"P",
    "gn:feature_code":"PPL",
    "gn:name":"La Herradura",
    "gn:population":0,
    "gn:timezone":"America/Santiago",
    "iso:country":"CL",
    "name:und_x_variant":[
        "Herradura"
    ],
    "wof:name":"La Herradura",
    "wof:placetype":"locality"
},
  "geometry": {"coordinates":[-71.36301,-29.98541],"type":"Point"}
}