{
  "type": "Feature",
  "properties": {
    "gn:admin1_code":"11.0",
    "gn:admin2_code":"71.0",
    "gn:admin3_code":"7108.0",
    "gn:asciiname":"Los Padres",
    "gn:country_code":"CL",
    "gn:dem":319,
    "gn:feature_class":"P",
    "gn:feature_code":"PPL",
    "gn:name":"Los Padres",
    "gn:population":0,
    "gn:timezone":"America/Santiago",
    "iso:country":"CL",
    "wof:name":"Los Padres",
    "wof:placetype":"locality"
},
  "geometry": {"coordinates":[-71.25865999999998,-35.25537],"type":"Point"}
}