{
  "type": "Feature",
  "properties": {
    "gn:admin1_code":"5.0",
    "gn:admin2_code":"32.0",
    "gn:admin3_code":"3202.0",
    "gn:asciiname":"Ines Chica",
    "gn:country_code":"CL",
    "gn:dem":3474,
    "gn:feature_class":"P",
    "gn:feature_code":"PPL",
    "gn:name":"In\u00e9s Chica",
    "gn:population":0,
    "gn:timezone":"America/Santiago",
    "iso:country":"CL",
    "wof:name":"Ines Chica",
    "wof:placetype":"locality"
},
  "geometry": {"coordinates":[-69.36667,-26.15],"type":"Point"}
}