{
  "type": "Feature",
  "properties": {
    "gn:admin1_code":"5.0",
    "gn:admin2_code":"33.0",
    "gn:admin3_code":"3301.0",
    "gn:asciiname":"El Bronce",
    "gn:country_code":"CL",
    "gn:dem":1973,
    "gn:feature_class":"P",
    "gn:feature_code":"PPL",
    "gn:name":"El Bronce",
    "gn:population":0,
    "gn:timezone":"America/Santiago",
    "iso:country":"CL",
    "wof:name":"El Bronce",
    "wof:placetype":"locality"
},
  "geometry": {"coordinates":[-70.30298000000001,-28.43544],"type":"Point"}
}