{
  "type": "Feature",
  "properties": {
    "gn:admin1_code":"16.0",
    "gn:admin2_code":"152.0",
    "gn:admin3_code":"15202.0",
    "gn:asciiname":"Chapuma",
    "gn:country_code":"CL",
    "gn:dem":4621,
    "gn:feature_class":"P",
    "gn:feature_code":"PPL",
    "gn:name":"Chapuma",
    "gn:population":0,
    "gn:timezone":"America/Santiago",
    "iso:country":"CL",
    "wof:name":"Chapuma",
    "wof:placetype":"locality"
},
  "geometry": {"coordinates":[-69.52389000000001,-17.84887999999999],"type":"Point"}
}