{
  "type": "Feature",
  "properties": {
    "gn:admin1_code":"8.0",
    "gn:admin2_code":"63.0",
    "gn:admin3_code":"6310.0",
    "gn:asciiname":"Rincon de Panama",
    "gn:country_code":"CL",
    "gn:dem":185,
    "gn:feature_class":"P",
    "gn:feature_code":"PPL",
    "gn:name":"Rinc\u00f3n de Panam\u00e1",
    "gn:population":0,
    "gn:timezone":"America/Santiago",
    "iso:country":"CL",
    "wof:name":"Rincon de Panama",
    "wof:placetype":"locality"
},
  "geometry": {"coordinates":[-71.43965,-34.73243],"type":"Point"}
}