{
  "type": "Feature",
  "properties": {
    "gn:admin1_code":"12.0",
    "gn:admin2_code":"134.0",
    "gn:asciiname":"La Turbina",
    "gn:country_code":"CL",
    "gn:dem":403,
    "gn:feature_class":"P",
    "gn:feature_code":"PPL",
    "gn:name":"La Turbina",
    "gn:population":0,
    "gn:timezone":"America/Santiago",
    "iso:country":"CL",
    "wof:name":"La Turbina",
    "wof:placetype":"locality"
},
  "geometry": {"coordinates":[-70.64461,-33.88643],"type":"Point"}
}