{
  "type": "Feature",
  "properties": {
    "gn:country":"CL",
    "gn:fcode":"PPLA3",
    "gn:population":0,
    "iso:country":"CL",
    "name:ara_x_preferred":[
        "\u0622\u064a\u0644 \u062a\u0627\u0628\u0648"
    ],
    "name:ceb_x_preferred":[
        "El Tabo"
    ],
    "name:eus_x_preferred":[
        "El Tabo"
    ],
    "name:fas_x_preferred":[
        "\u0627\u0644 \u062a\u0627\u0628\u0648"
    ],
    "name:fra_x_preferred":[
        "El Tabo"
    ],
    "name:ita_x_preferred":[
        "El Tabo"
    ],
    "name:kor_x_preferred":[
        "\uc5d8\ud0c0\ubcf4"
    ],
    "name:nld_x_preferred":[
        "El Tabo"
    ],
    "name:por_x_preferred":[
        "El Tabo"
    ],
    "name:ron_x_preferred":[
        "El Tabo"
    ],
    "name:rus_x_preferred":[
        "\u042d\u043b\u044c-\u0422\u0430\u0431\u043e"
    ],
    "name:spa_x_preferred":[
        "El Tabo"
    ],
    "name:swe_x_preferred":[
        "El Tabo"
    ],
    "name:zho_x_preferred":[
        "\u57c3\u723e\u5854\u6ce2"
    ],
    "qs_pg:aaroncc":"CL",
    "qs_pg:gn_country":"CL",
    "qs_pg:gn_fcode":"PPLA3",
    "qs_pg:gn_pop":0,
    "qs_pg:name":"El Tabo",
    "qs_pg:name_adm0":"Chile",
    "qs_pg:name_adm1":"Valpara\u00edso",
    "qs_pg:photos":1,
    "qs_pg:photos_1k":1,
    "qs_pg:photos_9k":10,
    "qs_pg:photos_9r":9,
    "qs_pg:photos_all":2276,
    "qs_pg:photos_sr":1,
    "qs_pg:pop_sr":0,
    "qs_pg:qs_pg_placetype":"localadmin",
    "qs_pg:qs_pg_placetype_gp":"LocalAdmin",
    "qs_pg:woe_adm0":23424782,
    "woe:adm0_id":23424782,
    "woe:name_adm0":"Chile",
    "woe:name_adm1":"Valpara\u00edso",
    "woe:placetype":"LocalAdmin",
    "wof:name":"El Tabo",
    "wof:placetype":"localadmin"
},
  "geometry": {"coordinates":[-71.66667,-33.45],"type":"Point"}
}