{
  "type": "Feature",
  "properties": {
    "gn:gn_country":"CL",
    "gn:gn_fcode":"PPLA3",
    "gn:gn_pop":0,
    "iso:country":"CL",
    "qs_pg:aaroncc":"CL",
    "qs_pg:gn_country":"CL",
    "qs_pg:gn_fcode":"PPLA3",
    "qs_pg:gn_pop":0,
    "qs_pg:name":"El Tabo",
    "qs_pg:name_adm0":"Chile",
    "qs_pg:name_adm1":"Valpara\u00edso",
    "qs_pg:photos":1,
    "qs_pg:photos_1k":1,
    "qs_pg:photos_9k":10,
    "qs_pg:photos_9r":9,
    "qs_pg:photos_all":2276,
    "qs_pg:photos_sr":1,
    "qs_pg:pop_sr":0,
    "qs_pg:qs_pg_placetype":"localadmin",
    "qs_pg:qs_pg_placetype_gp":"LocalAdmin",
    "qs_pg:woe_adm0":23424782,
    "woe:adm0_id":23424782,
    "woe:name_adm0":"Chile",
    "woe:name_adm1":"Valpara\u00edso",
    "woe:placetype":"LocalAdmin",
    "wof:name":"El Tabo",
    "wof:placetype":"localadmin"
},
  "geometry": {"coordinates":[-71.66667,-33.45],"type":"Point"}
}