{
  "type": "Feature",
  "properties": {
    "gn:admin1_code":"10.0",
    "gn:admin2_code":"121.0",
    "gn:asciiname":"Rinconada Bulnes",
    "gn:country_code":"CL",
    "gn:dem":44,
    "gn:feature_class":"P",
    "gn:feature_code":"PPL",
    "gn:name":"Rinconada Bulnes",
    "gn:population":0,
    "gn:timezone":"America/Punta_Arenas",
    "iso:country":"CL",
    "name:spa_x_preferred":[
        "Rinconada Bulnes"
    ],
    "wof:name":"Rinconada Bulnes",
    "wof:placetype":"locality"
},
  "geometry": {"coordinates":[-70.94469000000002,-53.58756999999999],"type":"Point"}
}