{
  "type": "Feature",
  "properties": {
    "gn:admin1_code":"10.0",
    "gn:admin2_code":"121.0",
    "gn:asciiname":"Puesto Romero",
    "gn:country_code":"CL",
    "gn:dem":159,
    "gn:feature_class":"P",
    "gn:feature_code":"PPL",
    "gn:name":"Puesto Romero",
    "gn:population":0,
    "gn:timezone":"America/Punta_Arenas",
    "iso:country":"CL",
    "name:spa_x_preferred":[
        "Puesto Romero"
    ],
    "wof:name":"Puesto Romero",
    "wof:placetype":"locality"
},
  "geometry": {"coordinates":[-70.44508,-52.35704000000001],"type":"Point"}
}