{
  "type": "Feature",
  "properties": {
    "iso:country":"CL",
    "qs:name":"Aguapie",
    "qs:name_adm0":"Chile",
    "qs:name_adm1":"Biobio",
    "qs:photos":115,
    "qs:photos_1k":23,
    "qs:photos_9k":1,
    "qs:photos_9r":3,
    "qs:photos_all":115,
    "qs:photos_sr":3,
    "qs:placetype":"Town",
    "qs:pop_sr":"0",
    "wof:name":"Aguapie",
    "wof:placetype":"locality"
},
  "geometry": {"coordinates":[-73.56325099999999,-37.199022],"type":"Point"}
}