{
  "type": "Feature",
  "properties": {
    "gn:admin1_code":"16.0",
    "gn:admin2_code":"152.0",
    "gn:admin3_code":"15202.0",
    "gn:asciiname":"Pucara",
    "gn:country_code":"CL",
    "gn:dem":4144,
    "gn:feature_class":"P",
    "gn:feature_code":"PPL",
    "gn:name":"Pucara",
    "gn:population":0,
    "gn:timezone":"America/Santiago",
    "iso:country":"CL",
    "name:spa_x_preferred":[
        "Pucara"
    ],
    "wof:name":"Pucara",
    "wof:placetype":"locality"
},
  "geometry": {"coordinates":[-69.31618,-17.82],"type":"Point"}
}