{
  "type": "Feature",
  "properties": {
    "gn:admin1_code":"11.0",
    "gn:admin2_code":"73.0",
    "gn:admin3_code":"7302.0",
    "gn:asciiname":"Quilico",
    "gn:country_code":"CL",
    "gn:dem":25,
    "gn:feature_class":"P",
    "gn:feature_code":"PPL",
    "gn:name":"Quilico",
    "gn:population":0,
    "gn:timezone":"America/Santiago",
    "iso:country":"CL",
    "wof:name":"Quilico",
    "wof:placetype":"locality"
},
  "geometry": {"coordinates":[-71.91444,-34.87416],"type":"Point"}
}