{
  "type": "Feature",
  "properties": {
    "gn:admin1_code":"11.0",
    "gn:admin2_code":"74.0",
    "gn:admin3_code":"7404.0",
    "gn:asciiname":"Quinchamavida",
    "gn:country_code":"CL",
    "gn:dem":139,
    "gn:feature_class":"P",
    "gn:feature_code":"PPL",
    "gn:name":"Quincham\u00e1vida",
    "gn:population":0,
    "gn:timezone":"America/Santiago",
    "iso:country":"CL",
    "wof:name":"Quinchamavida",
    "wof:placetype":"locality"
},
  "geometry": {"coordinates":[-72.0882,-36.10847],"type":"Point"}
}