{
  "type": "Feature",
  "properties": {
    "gn:admin1_code":"15.0",
    "gn:admin2_code":"14.0",
    "gn:admin3_code":"1405.0",
    "gn:asciiname":"Collacagua",
    "gn:country_code":"CL",
    "gn:dem":3926,
    "gn:feature_class":"P",
    "gn:feature_code":"PPL",
    "gn:name":"Collacagua",
    "gn:population":0,
    "gn:timezone":"America/Santiago",
    "iso:country":"CL",
    "name:und_x_variant":[
        "Collagua",
        "Collacagua"
    ],
    "wof:name":"Collacagua",
    "wof:placetype":"locality"
},
  "geometry": {"coordinates":[-68.83048000000001,-20.03918],"type":"Point"}
}