{
  "type": "Feature",
  "properties": {
    "gn:admin1_code":"5.0",
    "gn:admin2_code":"33.0",
    "gn:admin3_code":"3302.0",
    "gn:asciiname":"Alto del Carmen",
    "gn:country":"CL",
    "gn:country_code":"CL",
    "gn:dem":814,
    "gn:fcode":"PPL",
    "gn:feature_class":"P",
    "gn:feature_code":"PPL",
    "gn:name":"Alto del Carmen",
    "gn:population":0,
    "gn:timezone":"America/Santiago",
    "iso:country":"CL",
    "name:ara_x_preferred":[
        "\u0623\u0644\u062a\u0648 \u062f\u064a\u0644 \u0643\u0627\u0631\u0645\u0646"
    ],
    "name:arz_x_preferred":[
        "\u0627\u0644\u062a\u0648 \u062f\u064a\u0644 \u0643\u0627\u0631\u0645\u0646"
    ],
    "name:bak_x_preferred":[
        "\u0410\u043b\u044c\u0442\u043e-\u0434\u0435\u043b\u044c-\u041a\u0430\u0440\u043c\u0435\u043d"
    ],
    "name:cat_x_preferred":[
        "Alto del Carmen"
    ],
    "name:ceb_x_preferred":[
        "Alto del Carmen"
    ],
    "name:deu_x_preferred":[
        "Alto del Carmen"
    ],
    "name:eng_x_preferred":[
        "Alto del Carmen"
    ],
    "name:eus_x_preferred":[
        "Alto del Carmen"
    ],
    "name:fas_x_preferred":[
        "\u0627\u0644\u062a\u0648 \u062f\u0644 \u06a9\u0627\u0631\u0645\u0646"
    ],
    "name:fra_x_preferred":[
        "Alto del Carmen"
    ],
    "name:hye_x_preferred":[
        "\u0531\u056c\u057f\u0578 \u0564\u0565\u056c \u053f\u0561\u0580\u0574\u0565\u0576"
    ],
    "name:ita_x_preferred":[
        "Alto del Carmen"
    ],
    "name:jpn_x_preferred":[
        "\u30a2\u30eb\u30c8\u30fb\u30c7\u30eb\u30fb\u30ab\u30eb\u30e1\u30f3"
    ],
    "name:kan_x_preferred":[
        "\u0c86\u0cb2\u0ccd\u0c9f\u0ccb \u0ca1\u0cc6\u0cb2\u0ccd \u0c95\u0cbe\u0cb0\u0ccd\u0cae\u0cc6\u0ca8\u0ccd"
    ],
    "name:kor_x_preferred":[
        "\uc54c\ud1a0\ub378\uce74\ub974\uba58"
    ],
    "name:lit_x_preferred":[
        "Alto del Karmenas"
    ],
    "name:nan_x_preferred":[
        "Alto del Carmen"
    ],
    "name:nld_x_preferred":[
        "Alto del Carmen"
    ],
    "name:oci_x_preferred":[
        "Alto del Carmen"
    ],
    "name:por_x_preferred":[
        "Alto del Carmen"
    ],
    "name:ron_x_preferred":[
        "Alto del Carmen"
    ],
    "name:rus_x_preferred":[
        "\u0410\u043b\u044c\u0442\u043e-\u0434\u0435\u043b\u044c-\u041a\u0430\u0440\u043c\u0435\u043d"
    ],
    "name:spa_x_preferred":[
        "Alto del Carmen"
    ],
    "name:swe_x_preferred":[
        "Alto del Carmen"
    ],
    "name:tur_x_preferred":[
        "Alto del Carmen"
    ],
    "name:ukr_x_preferred":[
        "\u0410\u043b\u044c\u0442\u043e-\u0434\u0435\u043b\u044c-\u041a\u0430\u0440\u043c\u0435\u043d"
    ],
    "name:und_x_variant":[
        "Alto del Caimen"
    ],
    "name:zho_x_preferred":[
        "\u963f\u6258\u5fb7\u723e\u5361\u9580"
    ],
    "qs:name":"Alto del Carmen",
    "qs:name_adm0":"Chile",
    "qs:name_adm1":"Atacama",
    "qs:photos":70,
    "qs:photos_1k":14,
    "qs:photos_9k":1,
    "qs:photos_9r":2,
    "qs:photos_all":70,
    "qs:photos_sr":2,
    "qs:placetype":"Town",
    "qs:pop_sr":"0",
    "wd:wordcount":196,
    "wof:name":"Alto del Carmen",
    "wof:placetype":"locality",
    "wof:population":0
},
  "geometry": {"coordinates":[-70.48651,-28.75946],"type":"Point"}
}