{
  "type": "Feature",
  "properties": {
    "gn:admin1_code":"1.0",
    "gn:admin2_code":"54.0",
    "gn:admin3_code":"5404.0",
    "gn:asciiname":"El Sobrante",
    "gn:country_code":"CL",
    "gn:dem":810,
    "gn:feature_class":"P",
    "gn:feature_code":"PPL",
    "gn:name":"El Sobrante",
    "gn:population":0,
    "gn:timezone":"America/Santiago",
    "iso:country":"CL",
    "wof:name":"El Sobrante",
    "wof:placetype":"locality"
},
  "geometry": {"coordinates":[-70.79399000000002,-32.22971],"type":"Point"}
}