{
  "type": "Feature",
  "properties": {
    "gn:country":"CL",
    "gn:fcode":"PPL",
    "gn:pop":21823,
    "iso:country":"CL",
    "name:ara_x_preferred":[
        "\u0643\u0648\u064a\u0644\u0648\u0646"
    ],
    "name:cat_x_preferred":[
        "Quell\u00f3n"
    ],
    "name:ceb_x_preferred":[
        "Quellon"
    ],
    "name:ces_x_preferred":[
        "Quell\u00f3n"
    ],
    "name:deu_x_preferred":[
        "Quell\u00f3n"
    ],
    "name:eng_x_preferred":[
        "Quell\u00f3n"
    ],
    "name:eus_x_preferred":[
        "Quell\u00f3n"
    ],
    "name:fas_x_preferred":[
        "\u06a9\u06cc\u0648\u0646"
    ],
    "name:fra_x_preferred":[
        "Quell\u00f3n"
    ],
    "name:glg_x_preferred":[
        "Quell\u00f3n"
    ],
    "name:grn_x_preferred":[
        "Quell\u00f3n"
    ],
    "name:ita_x_preferred":[
        "Quell\u00f3n"
    ],
    "name:jpn_x_preferred":[
        "\u30b1\u30b8\u30e7\u30f3"
    ],
    "name:kor_x_preferred":[
        "\ucf00\uc698"
    ],
    "name:nah_x_preferred":[
        "Quell\u00f3n"
    ],
    "name:nan_x_preferred":[
        "Quell\u00f3n"
    ],
    "name:nld_x_preferred":[
        "Quell\u00f3n"
    ],
    "name:oci_x_preferred":[
        "Quell\u00f3n"
    ],
    "name:pms_x_preferred":[
        "Quell\u00f3n"
    ],
    "name:pol_x_preferred":[
        "Quell\u00f3n"
    ],
    "name:por_x_preferred":[
        "Quell\u00f3n"
    ],
    "name:ron_x_preferred":[
        "Quell\u00f3n"
    ],
    "name:rus_x_preferred":[
        "\u041a\u0435\u043b\u044c\u043e\u043d"
    ],
    "name:spa_x_preferred":[
        "Quell\u00f3n"
    ],
    "name:swe_x_preferred":[
        "Quellon"
    ],
    "name:vol_x_preferred":[
        "Quell\u00f3n"
    ],
    "name:war_x_preferred":[
        "Quell\u00f3n"
    ],
    "name:zho_x_preferred":[
        "\u514b\u5229\u7fc1"
    ],
    "qs:name":"Puerto Quell\u00f3n",
    "qs:photos_9r":0,
    "qs:photos_sr":0,
    "qs:pop_sr":"7",
    "wof:name":"Puerto Quell\u00f3n",
    "wof:placetype":"locality",
    "wof:population":21823
},
  "geometry": {"coordinates":[-73.61660999999999,-43.11819],"type":"Point"}
}