{
  "type": "Feature",
  "properties": {
    "gn:admin1_code":"16.0",
    "gn:admin2_code":"152.0",
    "gn:admin3_code":"15202.0",
    "gn:asciiname":"Caamana",
    "gn:country_code":"CL",
    "gn:dem":4369,
    "gn:feature_class":"P",
    "gn:feature_code":"PPL",
    "gn:name":"Caama\u00f1a",
    "gn:population":0,
    "gn:timezone":"America/Santiago",
    "iso:country":"CL",
    "name:und_x_variant":[
        "Comana",
        "Caama\u00f1a"
    ],
    "wof:name":"Caamana",
    "wof:placetype":"locality"
},
  "geometry": {"coordinates":[-69.42863,-17.80438],"type":"Point"}
}