{
  "type": "Feature",
  "properties": {
    "gn:admin1_code":"14.0",
    "gn:admin2_code":"101.0",
    "gn:admin3_code":"10103.0",
    "gn:asciiname":"Las Gualas",
    "gn:country_code":"CL",
    "gn:dem":40,
    "gn:feature_class":"P",
    "gn:feature_code":"PPL",
    "gn:name":"Las Gualas",
    "gn:population":0,
    "gn:timezone":"America/Santiago",
    "iso:country":"CL",
    "wof:name":"Las Gualas",
    "wof:placetype":"locality"
},
  "geometry": {"coordinates":[-72.23463000000002,-41.61895],"type":"Point"}
}