{
  "type": "Feature",
  "properties": {
    "gn:admin1_code":"14.0",
    "gn:admin2_code":"101.0",
    "gn:admin3_code":"10107.0",
    "gn:asciiname":"Colonia Loncotoro",
    "gn:country_code":"CL",
    "gn:dem":178,
    "gn:feature_class":"P",
    "gn:feature_code":"PPLL",
    "gn:name":"Colonia Loncotoro",
    "gn:population":0,
    "gn:timezone":"America/Santiago",
    "iso:country":"CL",
    "name:spa_x_preferred":[
        "Colonia Loncotoro"
    ],
    "wof:name":"Colonia Loncotoro",
    "wof:placetype":"locality"
},
  "geometry": {"coordinates":[-73.18485,-41.27756],"type":"Point"}
}