{
  "type": "Feature",
  "properties": {
    "gn:admin1_code":"16.0",
    "gn:admin2_code":"151.0",
    "gn:admin3_code":"15101.0",
    "gn:asciiname":"Casa Grande",
    "gn:country_code":"CL",
    "gn:dem":691,
    "gn:feature_class":"P",
    "gn:feature_code":"PPL",
    "gn:name":"Casa Grande",
    "gn:population":0,
    "gn:timezone":"America/Santiago",
    "iso:country":"CL",
    "name:ben_x_preferred":[
        "\u0995\u09be\u09b8\u09be \u0997\u09cd\u09b0\u09cd\u09af\u09be\u09a8\u09cd\u09a1\u09c7"
    ],
    "name:ell_x_preferred":[
        "\u039a\u03ac\u03b6\u03b1 \u0393\u03ba\u03c1\u03ac\u03bd\u03c4\u03b5"
    ],
    "name:hin_x_preferred":[
        "\u0915\u093e\u0938\u093e \u0917\u094d\u0930\u093e\u0902\u0921\u0947"
    ],
    "name:ind_x_preferred":[
        "Casa Grande"
    ],
    "name:urd_x_preferred":[
        "\u06a9\u06cc\u0633\u0627 \u06af\u0631\u06cc\u0646\u0688\u06d2"
    ],
    "name:vie_x_preferred":[
        "Casa Grande"
    ],
    "wof:name":"Casa Grande",
    "wof:placetype":"locality"
},
  "geometry": {"coordinates":[-70.00349,-18.58134],"type":"Point"}
}