{
  "type": "Feature",
  "properties": {
    "gn:admin1_code":"16.0",
    "gn:admin2_code":"151.0",
    "gn:admin3_code":"15101.0",
    "gn:asciiname":"Casa Grande",
    "gn:country_code":"CL",
    "gn:dem":691,
    "gn:feature_class":"P",
    "gn:feature_code":"PPL",
    "gn:name":"Casa Grande",
    "gn:population":0,
    "gn:timezone":"America/Santiago",
    "iso:country":"CL",
    "wof:name":"Casa Grande",
    "wof:placetype":"locality"
},
  "geometry": {"coordinates":[-70.00349,-18.58134],"type":"Point"}
}