{
  "type": "Feature",
  "properties": {
    "gn:admin1_code":"8.0",
    "gn:admin2_code":"62.0",
    "gn:admin3_code":"6201.0",
    "gn:asciiname":"Rodeillo",
    "gn:country_code":"CL",
    "gn:dem":86,
    "gn:feature_class":"P",
    "gn:feature_code":"PPL",
    "gn:name":"Rode\u00edllo",
    "gn:population":0,
    "gn:timezone":"America/Santiago",
    "iso:country":"CL",
    "name:und_x_variant":[
        "Rode\u00edllo"
    ],
    "wof:name":"Rodeillo",
    "wof:placetype":"locality"
},
  "geometry": {"coordinates":[-71.94249000000001,-34.52063],"type":"Point"}
}