{
  "type": "Feature",
  "properties": {
    "gn:admin1_code":"7.0",
    "gn:admin2_code":"41.0",
    "gn:admin3_code":"4105.0",
    "gn:asciiname":"Corral Munoz",
    "gn:country_code":"CL",
    "gn:dem":2801,
    "gn:feature_class":"P",
    "gn:feature_code":"PPL",
    "gn:name":"Corral Mu\u00f1oz",
    "gn:population":0,
    "gn:timezone":"America/Santiago",
    "iso:country":"CL",
    "name:und_x_variant":[
        "Corral de Mu\u00f1oz",
        "Corral Mu\u00f1oz"
    ],
    "wof:name":"Corral Munoz",
    "wof:placetype":"locality"
},
  "geometry": {"coordinates":[-70.27553,-30.31672],"type":"Point"}
}