{
  "type": "Feature",
  "properties": {
    "gn:admin1_code":"10.0",
    "gn:admin2_code":"121.0",
    "gn:admin3_code":"12104.0",
    "gn:asciiname":"Seccion San Jorge",
    "gn:country_code":"CL",
    "gn:dem":194,
    "gn:feature_class":"P",
    "gn:feature_code":"PPL",
    "gn:name":"Secci\u00f3n San Jorge",
    "gn:population":0,
    "gn:timezone":"America/Punta_Arenas",
    "iso:country":"CL",
    "name:spa_x_preferred":[
        "Secci\u00f3n San Jorge"
    ],
    "wof:name":"Seccion San Jorge",
    "wof:placetype":"locality"
},
  "geometry": {"coordinates":[-70.26389,-52.33393],"type":"Point"}
}