{
  "type": "Feature",
  "properties": {
    "iso:country":"CL",
    "name:ast_x_preferred":[
        "Saavedra"
    ],
    "name:ceb_x_preferred":[
        "Saavedra"
    ],
    "name:ces_x_preferred":[
        "Saavedra"
    ],
    "name:deu_x_preferred":[
        "Saavedra"
    ],
    "name:fra_x_preferred":[
        "Saavedra"
    ],
    "name:glg_x_preferred":[
        "Saavedra"
    ],
    "name:ita_x_preferred":[
        "Saavedra"
    ],
    "name:jpn_x_preferred":[
        "\u30b5\u30a2\u30d9\u30c9\u30e9"
    ],
    "name:nds_x_preferred":[
        "Saavedra"
    ],
    "name:nld_x_preferred":[
        "Saavedra"
    ],
    "name:por_x_preferred":[
        "Saavedra"
    ],
    "name:ron_x_preferred":[
        "Saavedra"
    ],
    "name:rus_x_preferred":[
        "\u0421\u0430\u0430\u0432\u0435\u0434\u0440\u0430"
    ],
    "name:spa_x_preferred":[
        "Saavedra"
    ],
    "name:swe_x_preferred":[
        "Saavedra"
    ],
    "name:ukr_x_preferred":[
        "\u0421\u0430\u0430\u0432\u0435\u0434\u0440\u0430"
    ],
    "qs:name":"Saavedra",
    "qs:name_adm0":"Chile",
    "qs:name_adm1":"Araucania",
    "qs:photos":6,
    "qs:photos_1k":1,
    "qs:photos_9k":1,
    "qs:photos_9r":4,
    "qs:photos_all":273,
    "qs:photos_sr":1,
    "qs:placetype":"LocalAdmin",
    "qs:pop_sr":"0",
    "wd:wordcount":61,
    "wof:name":"Saavedra",
    "wof:placetype":"localadmin"
},
  "geometry": {"coordinates":[-73.398498,-38.791155],"type":"Point"}
}