{
  "type": "Feature",
  "properties": {
    "gn:admin1_code":"8.0",
    "gn:admin2_code":"63.0",
    "gn:admin3_code":"6310.0",
    "gn:asciiname":"Chomedahue",
    "gn:country_code":"CL",
    "gn:dem":177,
    "gn:feature_class":"P",
    "gn:feature_code":"PPL",
    "gn:name":"Chomedahue",
    "gn:population":0,
    "gn:timezone":"America/Santiago",
    "iso:country":"CL",
    "name:sco_x_preferred":[
        "Chomedahue"
    ],
    "name:spa_x_preferred":[
        "Chomedahue"
    ],
    "wof:name":"Chomedahue",
    "wof:placetype":"locality"
},
  "geometry": {"coordinates":[-71.34155,-34.65595],"type":"Point"}
}