{
  "type": "Feature",
  "properties": {
    "gn:admin1_code":"14.0",
    "gn:admin2_code":"102.0",
    "gn:admin3_code":"10209.0",
    "gn:asciiname":"Quinterguen",
    "gn:country_code":"CL",
    "gn:dem":53,
    "gn:feature_class":"P",
    "gn:feature_code":"PPL",
    "gn:name":"Quintergu\u00e9n",
    "gn:population":0,
    "gn:timezone":"America/Santiago",
    "iso:country":"CL",
    "wof:name":"Quinterguen",
    "wof:placetype":"locality"
},
  "geometry": {"coordinates":[-73.36528,-42.14917],"type":"Point"}
}