{
  "type": "Feature",
  "properties": {
    "gn:admin1_code":"17.0",
    "gn:admin2_code":"141.0",
    "gn:asciiname":"Cruces",
    "gn:country_code":"CL",
    "gn:dem":20,
    "gn:feature_class":"P",
    "gn:feature_code":"PPL",
    "gn:name":"Cruces",
    "gn:population":0,
    "gn:timezone":"America/Santiago",
    "iso:country":"CL",
    "wof:name":"Cruces",
    "wof:placetype":"locality"
},
  "geometry": {"coordinates":[-73.15779000000001,-39.61852],"type":"Point"}
}