{
  "type": "Feature",
  "properties": {
    "gn:admin1_code":"14.0",
    "gn:admin2_code":"102.0",
    "gn:admin3_code":"10203.0",
    "gn:asciiname":"Chanquin",
    "gn:country_code":"CL",
    "gn:dem":57,
    "gn:feature_class":"P",
    "gn:feature_code":"PPL",
    "gn:name":"Chanqu\u00edn",
    "gn:population":0,
    "gn:timezone":"America/Santiago",
    "iso:country":"CL",
    "wof:name":"Chanquin",
    "wof:placetype":"locality"
},
  "geometry": {"coordinates":[-74.10351999999997,-42.61157],"type":"Point"}
}