{
  "type": "Feature",
  "properties": {
    "gn:admin1_code":"10.0",
    "gn:admin2_code":"122.0",
    "gn:admin3_code":"12201.0",
    "gn:asciiname":"Puerto Navarino",
    "gn:country_code":"CL",
    "gn:dem":7,
    "gn:feature_class":"P",
    "gn:feature_code":"PPL",
    "gn:name":"Puerto Navarino",
    "gn:population":0,
    "gn:timezone":"America/Punta_Arenas",
    "iso:country":"CL",
    "name:ita_x_preferred":[
        "Puerto Navarino"
    ],
    "name:pol_x_preferred":[
        "Puerto Navarino"
    ],
    "name:ron_x_preferred":[
        "Puerto Navarino"
    ],
    "name:spa_x_preferred":[
        "Puerto Navarino"
    ],
    "wof:name":"Puerto Navarino",
    "wof:placetype":"locality"
},
  "geometry": {"coordinates":[-68.31974,-54.9244],"type":"Point"}
}