{
  "type": "Feature",
  "properties": {
    "gn:country":"CL",
    "gn:fcode":"ADM3",
    "gn:pop":0,
    "iso:country":"CL",
    "qs:name":"Juan Fern\u00e1ndez",
    "qs:name_adm0":"Chile",
    "qs:name_adm1":"Valpara\u00edso",
    "qs:photos":2,
    "qs:photos_1k":1,
    "qs:photos_9k":1,
    "qs:photos_9r":2,
    "qs:photos_all":43,
    "qs:photos_sr":1,
    "qs:placetype":"LocalAdmin",
    "qs:pop_sr":"0",
    "wd:wordcount":248,
    "wof:name":"Juan Fern\u00e1ndez",
    "wof:placetype":"localadmin",
    "wof:population":0
},
  "geometry": {"coordinates":[-78.85299999999999,-33.64892],"type":"Point"}
}