{
  "type": "Feature",
  "properties": {
    "gn:country":"CL",
    "gn:fcode":"ADM3",
    "gn:pop":0,
    "iso:country":"CL",
    "name:bre_x_preferred":[
        "Juan Fern\u00e1ndez"
    ],
    "name:cat_x_preferred":[
        "Juan Fern\u00e1ndez"
    ],
    "name:ceb_x_preferred":[
        "Juan Fern\u00e1ndez"
    ],
    "name:deu_x_preferred":[
        "Juan Fern\u00e1ndez"
    ],
    "name:fra_x_preferred":[
        "Juan Fern\u00e1ndez"
    ],
    "name:glg_x_preferred":[
        "Juan Fern\u00e1ndez"
    ],
    "name:ita_x_preferred":[
        "Juan Fern\u00e1ndez"
    ],
    "name:jpn_x_preferred":[
        "\u30d5\u30a2\u30f3\u30fb\u30d5\u30a7\u30eb\u30ca\u30f3\u30c7\u30b9"
    ],
    "name:kor_x_preferred":[
        "\ud6c4\uc548 \ud398\ub974\ub09c\ub370\uc2a4"
    ],
    "name:nld_x_preferred":[
        "Juan Fern\u00e1ndez"
    ],
    "name:nor_x_preferred":[
        "Juan Fern\u00e1ndez"
    ],
    "name:pol_x_preferred":[
        "Juan Fern\u00e1ndez"
    ],
    "name:ron_x_preferred":[
        "Juan Fern\u00e1ndez"
    ],
    "name:spa_x_preferred":[
        "Juan Fern\u00e1ndez"
    ],
    "name:swe_x_preferred":[
        "Juan Fern\u00e1ndez"
    ],
    "qs:name":"Juan Fern\u00e1ndez",
    "qs:name_adm0":"Chile",
    "qs:name_adm1":"Valpara\u00edso",
    "qs:photos":2,
    "qs:photos_1k":1,
    "qs:photos_9k":1,
    "qs:photos_9r":2,
    "qs:photos_all":43,
    "qs:photos_sr":1,
    "qs:placetype":"LocalAdmin",
    "qs:pop_sr":"0",
    "wd:wordcount":248,
    "wof:name":"Juan Fern\u00e1ndez",
    "wof:placetype":"localadmin",
    "wof:population":0
},
  "geometry": {"coordinates":[-78.85299999999999,-33.64892],"type":"Point"}
}