{
  "type": "Feature",
  "properties": {
    "gn:admin1_code":"3.0",
    "gn:admin2_code":"22.0",
    "gn:admin3_code":"2201.0",
    "gn:asciiname":"Cupo",
    "gn:country_code":"CL",
    "gn:dem":3391,
    "gn:feature_class":"P",
    "gn:feature_code":"PPL",
    "gn:name":"Cupo",
    "gn:population":0,
    "gn:timezone":"America/Santiago",
    "iso:country":"CL",
    "name:spa_x_preferred":[
        "Cupo"
    ],
    "wof:name":"Cupo",
    "wof:placetype":"locality"
},
  "geometry": {"coordinates":[-68.31563,-22.11363],"type":"Point"}
}