{
  "type": "Feature",
  "properties": {
    "gn:admin1_code":"7.0",
    "gn:admin2_code":"43.0",
    "gn:admin3_code":"4304.0",
    "gn:asciiname":"Majada Blanca",
    "gn:country_code":"CL",
    "gn:dem":663,
    "gn:feature_class":"P",
    "gn:feature_code":"PPL",
    "gn:name":"Majada Blanca",
    "gn:population":0,
    "gn:timezone":"America/Santiago",
    "iso:country":"CL",
    "wof:name":"Majada Blanca",
    "wof:placetype":"locality"
},
  "geometry": {"coordinates":[-71.18921,-30.88705],"type":"Point"}
}