{
  "type": "Feature",
  "properties": {
    "gn:admin1_code":"14.0",
    "gn:admin2_code":"104.0",
    "gn:admin3_code":"10404.0",
    "gn:asciiname":"El Diablo",
    "gn:country_code":"CL",
    "gn:dem":117,
    "gn:feature_class":"P",
    "gn:feature_code":"PPL",
    "gn:name":"El Diablo",
    "gn:population":0,
    "gn:timezone":"America/Santiago",
    "iso:country":"CL",
    "name:ceb_x_preferred":[
        "El Diablo"
    ],
    "name:ita_x_preferred":[
        "El Diablo"
    ],
    "name:spa_x_preferred":[
        "El Diablo"
    ],
    "name:swe_x_preferred":[
        "El Diablo"
    ],
    "wof:name":"El Diablo",
    "wof:placetype":"locality"
},
  "geometry": {"coordinates":[-72.08275,-43.57659],"type":"Point"}
}