{
  "type": "Feature",
  "properties": {
    "gn:admin1_code":"14.0",
    "gn:admin2_code":"102.0",
    "gn:admin3_code":"10202.0",
    "gn:asciiname":"Guabun",
    "gn:country_code":"CL",
    "gn:dem":58,
    "gn:feature_class":"P",
    "gn:feature_code":"PPL",
    "gn:name":"Guab\u00fan",
    "gn:population":0,
    "gn:timezone":"America/Santiago",
    "iso:country":"CL",
    "name:und_x_variant":[
        "Gualbun",
        "Guab\u00fan"
    ],
    "wof:name":"Guabun",
    "wof:placetype":"locality"
},
  "geometry": {"coordinates":[-74.03523,-41.8205],"type":"Point"}
}