{
  "type": "Feature",
  "properties": {
    "gn:admin1_code":"15.0",
    "gn:admin2_code":"14.0",
    "gn:admin3_code":"1405.0",
    "gn:asciiname":"Chara",
    "gn:country_code":"CL",
    "gn:dem":3408,
    "gn:feature_class":"P",
    "gn:feature_code":"PPL",
    "gn:name":"Chara",
    "gn:population":0,
    "gn:timezone":"America/Santiago",
    "iso:country":"CL",
    "wof:name":"Chara",
    "wof:placetype":"locality"
},
  "geometry": {"coordinates":[-68.95573,-20.61371],"type":"Point"}
}