{
  "type": "Feature",
  "properties": {
    "gn:admin1_code":"15.0",
    "gn:admin2_code":"14.0",
    "gn:admin3_code":"1405.0",
    "gn:asciiname":"Chara",
    "gn:country_code":"CL",
    "gn:dem":3408,
    "gn:feature_class":"P",
    "gn:feature_code":"PPL",
    "gn:name":"Chara",
    "gn:population":0,
    "gn:timezone":"America/Santiago",
    "iso:country":"CL",
    "name:ceb_x_preferred":[
        "Chara"
    ],
    "name:deu_x_preferred":[
        "Chara"
    ],
    "name:ell_x_preferred":[
        "\u03a7\u03b1\u03c1\u03ac"
    ],
    "name:fin_x_preferred":[
        "Chara"
    ],
    "name:fra_x_preferred":[
        "Chara"
    ],
    "name:hrv_x_preferred":[
        "Chara"
    ],
    "name:ita_x_preferred":[
        "Chara"
    ],
    "name:jpn_x_preferred":[
        "Chara"
    ],
    "name:rus_x_preferred":[
        "\u0427\u0430\u0440\u0430"
    ],
    "name:slk_x_preferred":[
        "Chara"
    ],
    "name:spa_x_preferred":[
        "Chara"
    ],
    "name:swe_x_preferred":[
        "Chara"
    ],
    "name:ukr_x_preferred":[
        "\u0427\u0430\u0440\u0430"
    ],
    "wof:name":"Chara",
    "wof:placetype":"locality"
},
  "geometry": {"coordinates":[-68.95573,-20.61371],"type":"Point"}
}