{
  "type": "Feature",
  "properties": {
    "gn:admin1_code":"16.0",
    "gn:admin2_code":"152.0",
    "gn:admin3_code":"15201.0",
    "gn:asciiname":"Pujune",
    "gn:country_code":"CL",
    "gn:dem":4068,
    "gn:feature_class":"P",
    "gn:feature_code":"PPL",
    "gn:name":"Pujune",
    "gn:population":0,
    "gn:timezone":"America/Santiago",
    "iso:country":"CL",
    "name:spa_x_preferred":[
        "Pujune"
    ],
    "wof:name":"Pujune",
    "wof:placetype":"locality"
},
  "geometry": {"coordinates":[-69.10597,-18.59028],"type":"Point"}
}