{
  "type": "Feature",
  "properties": {
    "iso:country":"CL",
    "qs:name":"Salamanca",
    "qs:name_adm0":"Chile",
    "qs:name_adm1":"Coquimbo",
    "qs:photos":1,
    "qs:photos_1k":1,
    "qs:photos_9k":1,
    "qs:photos_9r":2,
    "qs:photos_all":58,
    "qs:photos_sr":1,
    "qs:placetype":"LocalAdmin",
    "qs:pop_sr":"0",
    "wof:name":"Salamanca",
    "wof:placetype":"localadmin"
},
  "geometry": {"coordinates":[-70.97442599999999,-31.777504],"type":"Point"}
}