{
  "type": "Feature",
  "properties": {
    "gn:admin1_code":"2.0",
    "gn:admin2_code":"111.0",
    "gn:admin3_code":"11101.0",
    "gn:asciiname":"Nirehuao",
    "gn:country_code":"CL",
    "gn:dem":541,
    "gn:feature_class":"P",
    "gn:feature_code":"PPL",
    "gn:name":"\u00d1irehuao",
    "gn:population":0,
    "gn:timezone":"America/Santiago",
    "iso:country":"CL",
    "wof:name":"Nirehuao",
    "wof:placetype":"locality"
},
  "geometry": {"coordinates":[-71.71600000000002,-45.26921],"type":"Point"}
}