{
  "type": "Feature",
  "properties": {
    "gn:admin1_code":"11.0",
    "gn:admin2_code":"71.0",
    "gn:admin3_code":"7102.0",
    "gn:asciiname":"Huillin",
    "gn:country_code":"CL",
    "gn:dem":464,
    "gn:feature_class":"P",
    "gn:feature_code":"PPL",
    "gn:name":"Huill\u00edn",
    "gn:population":0,
    "gn:timezone":"America/Santiago",
    "iso:country":"CL",
    "wof:name":"Huillin",
    "wof:placetype":"locality"
},
  "geometry": {"coordinates":[-72.25093000000003,-35.49907],"type":"Point"}
}