{
  "type": "Feature",
  "properties": {
    "gn:admin1_code":"7.0",
    "gn:admin2_code":"42.0",
    "gn:admin3_code":"4201.0",
    "gn:asciiname":"Barranca de la Canela",
    "gn:country_code":"CL",
    "gn:dem":1085,
    "gn:feature_class":"P",
    "gn:feature_code":"PPL",
    "gn:name":"Barranca de la Canela",
    "gn:population":0,
    "gn:timezone":"America/Santiago",
    "iso:country":"CL",
    "wof:name":"Barranca de la Canela",
    "wof:placetype":"locality"
},
  "geometry": {"coordinates":[-70.86667,-31.56667],"type":"Point"}
}