{
  "type": "Feature",
  "properties": {
    "gn:admin1_code":"11.0",
    "gn:admin2_code":"71.0",
    "gn:admin3_code":"7105.0",
    "gn:asciiname":"Quinepeumo",
    "gn:country_code":"CL",
    "gn:dem":135,
    "gn:feature_class":"P",
    "gn:feature_code":"PPL",
    "gn:name":"Qui\u00f1epeumo",
    "gn:population":0,
    "gn:timezone":"America/Santiago",
    "iso:country":"CL",
    "wof:name":"Quinepeumo",
    "wof:placetype":"locality"
},
  "geometry": {"coordinates":[-71.64166,-35.5499],"type":"Point"}
}