{
  "type": "Feature",
  "properties": {
    "gn:admin1_code":"5.0",
    "gn:admin2_code":"31.0",
    "gn:admin3_code":"3101.0",
    "gn:asciiname":"Piedra Colgada",
    "gn:country_code":"CL",
    "gn:dem":260,
    "gn:feature_class":"P",
    "gn:feature_code":"PPL",
    "gn:name":"Piedra Colgada",
    "gn:population":0,
    "gn:timezone":"America/Santiago",
    "iso:country":"CL",
    "wof:name":"Piedra Colgada",
    "wof:placetype":"locality"
},
  "geometry": {"coordinates":[-70.49558,-27.3113],"type":"Point"}
}