{
  "type": "Feature",
  "properties": {
    "gn:admin1_code":"7.0",
    "gn:admin2_code":"41.0",
    "gn:admin3_code":"4106.0",
    "gn:asciiname":"Guanta",
    "gn:country_code":"CL",
    "gn:dem":1217,
    "gn:feature_class":"P",
    "gn:feature_code":"PPL",
    "gn:name":"Guanta",
    "gn:population":0,
    "gn:timezone":"America/Santiago",
    "iso:country":"CL",
    "name:und_x_variant":[
        "Huanta",
        "Guanta"
    ],
    "wof:name":"Guanta",
    "wof:placetype":"locality"
},
  "geometry": {"coordinates":[-70.38783000000002,-29.84731],"type":"Point"}
}