{
  "type": "Feature",
  "properties": {
    "gn:admin1_code":"1.0",
    "gn:admin2_code":"57.0",
    "gn:admin3_code":"5705.0",
    "gn:asciiname":"Comunidad las Coimas",
    "gn:country_code":"CL",
    "gn:dem":740,
    "gn:feature_class":"P",
    "gn:feature_code":"PPL",
    "gn:name":"Comunidad las Coimas",
    "gn:population":0,
    "gn:timezone":"America/Santiago",
    "iso:country":"CL",
    "name:und_x_variant":[
        "Las Coimas",
        "Ermita",
        "Coimas",
        "Comunidad las Coimas"
    ],
    "wof:name":"Comunidad las Coimas",
    "wof:placetype":"locality"
},
  "geometry": {"coordinates":[-70.71795,-32.6634],"type":"Point"}
}