{
  "type": "Feature",
  "properties": {
    "gn:admin1_code":"10.0",
    "gn:admin2_code":"121.0",
    "gn:asciiname":"Cien Aguilas",
    "gn:country_code":"CL",
    "gn:dem":80,
    "gn:feature_class":"P",
    "gn:feature_code":"PPL",
    "gn:name":"Cien \u00c1guilas",
    "gn:population":0,
    "gn:timezone":"America/Punta_Arenas",
    "iso:country":"CL",
    "name:spa_x_preferred":[
        "Cien \u00c1guilas"
    ],
    "wof:name":"Cien Aguilas",
    "wof:placetype":"locality"
},
  "geometry": {"coordinates":[-71.09987,-53.39718000000001],"type":"Point"}
}