{
  "type": "Feature",
  "properties": {
    "gn:admin1_code":"15.0",
    "gn:admin2_code":"14.0",
    "gn:admin3_code":"1401.0",
    "gn:asciiname":"Cautenicsa",
    "gn:country_code":"CL",
    "gn:dem":2545,
    "gn:feature_class":"P",
    "gn:feature_code":"PPL",
    "gn:name":"Cautenicsa",
    "gn:population":0,
    "gn:timezone":"America/Santiago",
    "iso:country":"CL",
    "name:und_x_variant":[
        "Cautinicsa",
        "Cautinisca",
        "Cautenisca",
        "Cautenicsa"
    ],
    "wof:name":"Cautenicsa",
    "wof:placetype":"locality"
},
  "geometry": {"coordinates":[-69.01673000000001,-20.933],"type":"Point"}
}