{
  "type": "Feature",
  "properties": {
    "iso:country":"CL",
    "qs:name":"Bolsico",
    "qs:name_adm0":"Chile",
    "qs:name_adm1":"Antofagasta",
    "qs:photos":83,
    "qs:photos_1k":17,
    "qs:photos_9k":1,
    "qs:photos_9r":3,
    "qs:photos_all":83,
    "qs:photos_sr":3,
    "qs:placetype":"Town",
    "qs:pop_sr":"0",
    "wof:name":"Bolsico",
    "wof:placetype":"locality"
},
  "geometry": {"coordinates":[-70.609224,-23.467655],"type":"Point"}
}