{
  "type": "Feature",
  "properties": {
    "gn:admin1_code":"5.0",
    "gn:admin2_code":"33.0",
    "gn:admin3_code":"3304.0",
    "gn:asciiname":"Portezuelo",
    "gn:country_code":"CL",
    "gn:dem":582,
    "gn:feature_class":"P",
    "gn:feature_code":"PPL",
    "gn:name":"Portezuelo",
    "gn:population":0,
    "gn:timezone":"America/Santiago",
    "iso:country":"CL",
    "wof:name":"Portezuelo",
    "wof:placetype":"locality"
},
  "geometry": {"coordinates":[-70.86108,-28.07836],"type":"Point"}
}